Workbook

Sheet BOM
A1: Category | B1: Item | C1: Spec/notes | D1: Used for | E1: Qty needed | F1: Have it | G1: Qty to buy | H1: Unit price CAD | I1: Line total | J1: Store | K1: Link | L1: Search link | M1: Price checked date | N1: Price status | O1: Cart #
A2: Computer & displays (owned) | B2: Gaming PC (Ryzen 9 5900X, RX 6800 XT 16 GB, 32 GB RAM) | C2: Linux Mint; RX 6800 XT: 2x DP 1.4, 1x HDMI 2.1, 1x USB-C, max 4 displays | D2: Runs the Godot game (3 windows) | E2: 1 | F2: =TRUE() -> TRUE | G2: =IF(OR(F2=TRUE(),F2="TRUE"),0,E2) -> 0 | H2: 0 | I2: =IF(H2="","",G2*H2) -> 0 | J2: Owned | N2: Owned | O2: =IF(AND(J2="Amazon.ca",G2>0,ISERROR(SEARCH("ALTERNATIVE",A2))),MAX(O$1:O1)+1,"")
A3: Computer & displays (owned) | B3: Sceptre C275B-144R 27" curved monitor | C3: 1920x1080 144 Hz, 1800R, VESA 100 M4, HDMI/DP/DVI, 3.80 kg | D3: PILOT window (left kid), in the pod | E3: 1 | F3: =TRUE() -> TRUE | G3: =IF(OR(F3=TRUE(),F3="TRUE"),0,E3) -> 0 | H3: 0 | I3: =IF(H3="","",G3*H3) -> 0 | J3: Owned | N3: Owned | O3: =IF(AND(J3="Amazon.ca",G3>0,ISERROR(SEARCH("ALTERNATIVE",A3))),MAX(O$1:O2)+1,"")
A4: Computer & displays (owned) | B4: Sceptre C275W-1920RN 27" curved monitor | C4: 1920x1080 75 Hz, 1800R, VESA 75 M4, HDMI + VGA only, 3.40 kg | D4: OPS window (right kid), in the pod | E4: 1 | F4: =TRUE() -> TRUE | G4: =IF(OR(F4=TRUE(),F4="TRUE"),0,E4) -> 0 | H4: 0 | I4: =IF(H4="","",G4*H4) -> 0 | J4: Owned | N4: Owned | O4: =IF(AND(J4="Amazon.ca",G4>0,ISERROR(SEARCH("ALTERNATIVE",A4))),MAX(O$1:O3)+1,"")
A5: Computer & displays (owned) | B5: ViewSonic TD2220 22" touchscreen | C5: 21.5" 1920x1080, optical 2-point touch over USB-B, VGA + DVI-D only, VESA 100 | D5: Centre console touchscreen (in the cradle) | E5: 1 | F5: =TRUE() -> TRUE | G5: =IF(OR(F5=TRUE(),F5="TRUE"),0,E5) -> 0 | H5: 0 | I5: =IF(H5="","",G5*H5) -> 0 | J5: Owned | N5: Owned | O5: =IF(AND(J5="Amazon.ca",G5>0,ISERROR(SEARCH("ALTERNATIVE",A5))),MAX(O$1:O4)+1,"")
A6: Computer & displays (owned) | B6: HY300 mini projectors | C6: Only in the projector-dome feasibility study (docs/mechanical/projector_dome_study.md); not in the core build | D6: Optional dome / ambient projection | E6: 3 | F6: =TRUE() -> TRUE | G6: =IF(OR(F6=TRUE(),F6="TRUE"),0,E6) -> 0 | H6: 0 | I6: =IF(H6="","",G6*H6) -> 0 | J6: Owned | N6: Owned | O6: =IF(AND(J6="Amazon.ca",G6>0,ISERROR(SEARCH("ALTERNATIVE",A6))),MAX(O$1:O5)+1,"")
A7: Computer & displays (owned) | B7: 3-axis joysticks with top button (X, Y, twist pots + button) | C7: "A couple" owned; assumed potentiometer sticks (see electronics README). Mounting pattern still to measure | D7: PILOT and OPS sticks | E7: 2 | F7: =TRUE() -> TRUE | G7: =IF(OR(F7=TRUE(),F7="TRUE"),0,E7) -> 0 | H7: 0 | I7: =IF(H7="","",G7*H7) -> 0 | J7: Owned | N7: Owned | O7: =IF(AND(J7="Amazon.ca",G7>0,ISERROR(SEARCH("ALTERNATIVE",A7))),MAX(O$1:O6)+1,"")
A8: Video & USB cabling | B8: DisplayPort 1.4 cable, 3 m (10 ft), VESA certified | C8: Latching connectors; 3-5 m per displays.md - measure from the PC location | Listing: "Silkland VESA Certified DisplayPort Cable, Long DP Cable 10FT, Braided" | D8: GPU DP1 -> C275B-144R (1080p 144 Hz) | E8: 1 | F8: =FALSE() -> FALSE | G8: =IF(OR(F8=TRUE(),F8="TRUE"),0,E8) -> 1 | H8: 16.99 | I8: =IF(H8="","",G8*H8) -> 16.99 | J8: Amazon.ca | K8: https://www.amazon.ca/dp/B0BRPZHK36 | L8: https://www.amazon.ca/s?k=displayport+1.4+cable+10+ft | M8: 2026-10-08 | N8: Verified amazon.ca price | O8: =IF(AND(J8="Amazon.ca",G8>0,ISERROR(SEARCH("ALTERNATIVE",A8))),MAX(O$1:O7)+1,"") -> 1
A9: Video & USB cabling | B9: HDMI cable, 3 m (10 ft) | C9: High speed; C275W only has HDMI/VGA | Listing: "Amazon Basics High-Speed 4K HDMI Cable - 10 Feet" | D9: GPU HDMI -> C275W-1920RN (1080p 75 Hz) | E9: 1 | F9: =FALSE() -> FALSE | G9: =IF(OR(F9=TRUE(),F9="TRUE"),0,E9) -> 1 | H9: 10.76 | I9: =IF(H9="","",G9*H9) -> 10.76 | J9: Amazon.ca | K9: https://www.amazon.ca/dp/B014I8T0YQ | L9: https://www.amazon.ca/s?k=hdmi+cable+10+ft | M9: 2026-10-08 | N9: Verified amazon.ca price | O9: =IF(AND(J9="Amazon.ca",G9>0,ISERROR(SEARCH("ALTERNATIVE",A9))),MAX(O$1:O8)+1,"") -> 2
A10: Video & USB cabling | B10: DisplayPort -> DVI-D adapter cable, passive, 3 m (10 ft) | C10: Single-link DVI-D, 1080p60, passive DP++ is fine. One-piece cable = no separate DVI cable needed. Alternative if you already have the TD2220 DVI cable: StarTech DP2DVI2 passive adapter https://www.amazon.ca/dp/B0035PS57C | Listing: "BENFEI DisplayPort to DVI 10 Feet Cable, Uni-Directional" | D10: GPU DP2 -> TD2220 DVI-D in | E10: 1 | F10: =FALSE() -> FALSE | G10: =IF(OR(F10=TRUE(),F10="TRUE"),0,E10) -> 1 | H10: 16.99 | I10: =IF(H10="","",G10*H10) -> 16.99 | J10: Amazon.ca | K10: https://www.amazon.ca/dp/B06WD33P34 | L10: https://www.amazon.ca/s?k=displayport+to+dvi-d+cable+10+ft | M10: 2026-10-08 | N10: Verified amazon.ca price | O10: =IF(AND(J10="Amazon.ca",G10>0,ISERROR(SEARCH("ALTERNATIVE",A10))),MAX(O$1:O9)+1,"") -> 3
A11: Video & USB cabling | B11: USB-A to USB-B cable, 3 m (10 ft) | C11: USB 2.0; <= 5 m (or use an active extension) | Listing: "AINOPE USB Printer Cable 10FT, Nylon Braided USB A to USB B MIDI Cable" | D11: PC -> TD2220 touch (HID) | E11: 1 | F11: =FALSE() -> FALSE | G11: =IF(OR(F11=TRUE(),F11="TRUE"),0,E11) -> 1 | H11: 12.99 | I11: =IF(H11="","",G11*H11) -> 12.99 | J11: Amazon.ca | K11: https://www.amazon.ca/dp/B07ZRBRDHG | L11: https://www.amazon.ca/s?k=usb+a+to+usb+b+cable+10+ft | M11: 2026-10-08 | N11: Verified amazon.ca price | O11: =IF(AND(J11="Amazon.ca",G11>0,ISERROR(SEARCH("ALTERNATIVE",A11))),MAX(O$1:O10)+1,"") -> 4
A12: Video & USB cabling | B12: USB-A to USB-C data cables 1.8 m (6 ft), 3-pack | C12: Must be DATA cables; plug into each board's "USB" port (not "UART") | Listing: "Cable Matters 3-Pack USB A to USB C Cable, 6ft, Black" | D12: 3x ESP32-S3 boards -> PC / hub | E12: 1 | F12: =FALSE() -> FALSE | G12: =IF(OR(F12=TRUE(),F12="TRUE"),0,E12) -> 1 | H12: 9.99 | I12: =IF(H12="","",G12*H12) -> 9.99 | J12: Amazon.ca | K12: https://www.amazon.ca/dp/B0CLZ9J2F5 | L12: https://www.amazon.ca/s?k=usb+a+to+usb+c+data+cable+6+ft+3+pack | M12: 2026-10-08 | N12: Verified amazon.ca price | O12: =IF(AND(J12="Amazon.ca",G12>0,ISERROR(SEARCH("ALTERNATIVE",A12))),MAX(O$1:O11)+1,"") -> 5
A13: Video & USB cabling | B13: Powered USB 3.0 hub, 7-port, with power adapter | C13: Electronics README: a powered USB 3 hub is fine | Listing: "TP-Link UH720, Powered USB 3.0 Hub, 7 Data + 2 Charging Ports" | D13: 3x ESP32-S3 + TD2220 touch | E13: 1 | F13: =FALSE() -> FALSE | G13: =IF(OR(F13=TRUE(),F13="TRUE"),0,E13) -> 1 | H13: 39.99 | I13: =IF(H13="","",G13*H13) -> 39.99 | J13: Amazon.ca | K13: https://www.amazon.ca/dp/B00SCX6I8A | L13: https://www.amazon.ca/s?k=powered+usb+3.0+hub+7+port | M13: 2026-10-08 | N13: Verified amazon.ca price | O13: =IF(AND(J13="Amazon.ca",G13>0,ISERROR(SEARCH("ALTERNATIVE",A13))),MAX(O$1:O12)+1,"") -> 6
A14: Video & USB cabling | B14: Expandable braided sleeve 25 mm (1"), 7.6 m (25 ft) | C14: BOM: 5 m of 25-30 mm sleeve | Listing: "25ft - 1 inch PET Expandable Braided Sleeving – Black – Alex Tech Braided Cable Sleeve" | D14: 200 mm U service loops at the pod + cradle pivots | E14: 1 | F14: =FALSE() -> FALSE | G14: =IF(OR(F14=TRUE(),F14="TRUE"),0,E14) -> 1 | H14: 15.98 | I14: =IF(H14="","",G14*H14) -> 15.98 | J14: Amazon.ca | K14: https://www.amazon.ca/dp/B073YLYBJF | L14: https://www.amazon.ca/s?k=braided+cable+sleeve+1+inch+25+ft | M14: 2026-10-08 | N14: Verified amazon.ca price | O14: =IF(AND(J14="Amazon.ca",G14>0,ISERROR(SEARCH("ALTERNATIVE",A14))),MAX(O$1:O13)+1,"") -> 7
A15: Controllers & logic | B15: ESP32-S3-DevKitC-1-N8R8, 5-pack | C15: Must be the S3 DevKitC-1 with both "USB" + "UART" ports. 3 needed + 2 spares | Listing: "5pcs ESP32 S3 Development Board ESP32-S3-DevKitC-1-N8R8 MCU Module" | D15: Falcon Pilot / Ops / Command | E15: 1 | F15: =FALSE() -> FALSE | G15: =IF(OR(F15=TRUE(),F15="TRUE"),0,E15) -> 1 | H15: 71.98 | I15: =IF(H15="","",G15*H15) -> 71.98 | J15: Amazon.ca | K15: https://www.amazon.ca/dp/B0D93FLZLH | L15: https://www.amazon.ca/s?k=ESP32-S3-DevKitC-1+N8R8 | M15: 2026-10-08 | N15: Verified amazon.ca price | O15: =IF(AND(J15="Amazon.ca",G15>0,ISERROR(SEARCH("ALTERNATIVE",A15))),MAX(O$1:O14)+1,"") -> 8
A16: Controllers & logic | B16: 74HC165 shift register DIP-16, 25 pcs | C16: 10 needed (3 Pilot, 3 Ops, 4 Command) + 2 spares | Listing: "SING F LTD 25Pcs DIP16 IC 8BIT Parallel-in/Serial-Out Shift Register 16 Pin Computer Through Hole De" | D16: Switch inputs | E16: 1 | F16: =FALSE() -> FALSE | G16: =IF(OR(F16=TRUE(),F16="TRUE"),0,E16) -> 1 | H16: 18.49 | I16: =IF(H16="","",G16*H16) -> 18.49 | J16: Amazon.ca | K16: https://www.amazon.ca/dp/B0D2THXFQ6 | L16: https://www.amazon.ca/s?k=SN74HC165N+DIP-16 | M16: 2026-10-08 | N16: Verified amazon.ca price | O16: =IF(AND(J16="Amazon.ca",G16>0,ISERROR(SEARCH("ALTERNATIVE",A16))),MAX(O$1:O15)+1,"") -> 9
A17: Controllers & logic | B17: DIP IC socket assortment (incl. 14- and 16-pin) | C17: 12x DIP-16 for the 74HC165s + 1x DIP-14 for the 74AHCT125 | Listing: "Glarks 122Pcs 2.54mm Pitch DIP IC Sockets Solder Type Adaptor Assortment Kit (6 / 8 / 14 / 16 / 18 /" | D17: Socketed chips on the perfboards | E17: 1 | F17: =FALSE() -> FALSE | G17: =IF(OR(F17=TRUE(),F17="TRUE"),0,E17) -> 1 | H17: 16.99 | I17: =IF(H17="","",G17*H17) -> 16.99 | J17: Amazon.ca | K17: https://www.amazon.ca/dp/B01GOLSUAU | L17: https://www.amazon.ca/s?k=dip+ic+socket+assortment | M17: 2026-10-08 | N17: Verified amazon.ca price | O17: =IF(AND(J17="Amazon.ca",G17>0,ISERROR(SEARCH("ALTERNATIVE",A17))),MAX(O$1:O16)+1,"") -> 10
A18: Controllers & logic | B18: 10 kOhm bussed resistor network SIP-9 (A103J), 20 pcs | C18: 12 needed (one per 74HC165, 8 pull-ups) | Listing: "20pcs A103J 9pin 10K ohm DIP Exclusion 9 PINS Network Resistor Array" | D18: 74HC165 input pull-ups | E18: 1 | F18: =FALSE() -> FALSE | G18: =IF(OR(F18=TRUE(),F18="TRUE"),0,E18) -> 1 | H18: 8.88 | I18: =IF(H18="","",G18*H18) -> 8.88 | J18: Amazon.ca | K18: https://www.amazon.ca/dp/B0D4BXJ1SX | L18: https://www.amazon.ca/s?k=10k+bussed+resistor+network+sip+9+A103J | M18: 2026-10-08 | N18: Verified amazon.ca price | O18: =IF(AND(J18="Amazon.ca",G18>0,ISERROR(SEARCH("ALTERNATIVE",A18))),MAX(O$1:O17)+1,"") -> 11
A19: Controllers & logic | B19: 100 nF ceramic capacitors, 100 pcs | C19: 52 needed: 20 at chips/boards + 32 at the WS2812D-F5 LEDs | Listing: "50V Ceramic Capacitor,50V 100NF(104 100pcs" | D19: Decoupling | E19: 1 | F19: =FALSE() -> FALSE | G19: =IF(OR(F19=TRUE(),F19="TRUE"),0,E19) -> 1 | H19: 6.55 | I19: =IF(H19="","",G19*H19) -> 6.55 | J19: Amazon.ca | K19: https://www.amazon.ca/dp/B09JWTW1GT | L19: https://www.amazon.ca/s?k=100nf+ceramic+capacitor+104+100pcs | M19: 2026-10-08 | N19: Verified amazon.ca price | O19: =IF(AND(J19="Amazon.ca",G19>0,ISERROR(SEARCH("ALTERNATIVE",A19))),MAX(O$1:O18)+1,"") -> 12
... A40: LED backlighting | B40: WS2812B LED strip 5 V, 60 LED/m, 5 m, IP30 (no sleeve) | C40: BTF-LIGHTING ECO; this ASIN is the Black PCB / IP30 / 5 m 60 LED/m variant (checked). 10 mm wide strip fits the 12 mm channels; ~136 label LEDs + panel hops | Listing: "BTF-LIGHTING WS2812B IC ECO Individually Addressable RGB LED Strip Lights" | D40: Backlit labels, one continuous strip | E40: 1 | F40: =FALSE() -> FALSE | G40: =IF(OR(F40=TRUE(),F40="TRUE"),0,E40) -> 1 | H40: 25.99 | I40: =IF(H40="","",G40*H40) -> 25.99 | J40: Amazon.ca | K40: https://www.amazon.ca/dp/B0F8VDHK22 | L40: https://www.amazon.ca/s?k=ws2812b+5m+60+led+ip30 | M40: 2026-10-08 | N40: Verified amazon.ca price | O40: =IF(AND(J40="Amazon.ca",G40>0,ISERROR(SEARCH("ALTERNATIVE",A40))),MAX(O$1:O39)+1,"") -> 33
A41: LED backlighting | B41: WS2812D-F5 5 mm through-hole addressable RGB LEDs, ~40 pcs | C41: 32 status holes + spares; spliced into the same data line. NOT found on amazon.ca (only plain 4-pin RGB). Try AliExpress / Digi-Key, or use plain LEDs + 74HC595 (firmware change) | D41: Status/indicator LEDs (*_LED ids) | E41: 1 | F41: =FALSE() -> FALSE | G41: =IF(OR(F41=TRUE(),F41="TRUE"),0,E41) -> 1 | H41: 20 | I41: =IF(H41="","",G41*H41) -> 20 | J41: Amazon.ca | L41: https://www.amazon.ca/s?k=WS2812D-F5+5mm+addressable+RGB+LED | N41: No suitable listing found - estimate | O41: =IF(AND(J41="Amazon.ca",G41>0,ISERROR(SEARCH("ALTERNATIVE",A41))),MAX(O$1:O40)+1,"") -> 34
A42: LED backlighting | B42: 5 mm LED holders / bezels, 50 pcs | C42: 32 needed. Note: you may already own some of these (tick Have it if so). | Listing: "PATIKIL 5mm Emitting Diode Holder, 50 Pcs Plastic Flat LED Holder Clip Mounting Bracket Socket Cap f" | D42: Status LED holes | E42: 1 | F42: =FALSE() -> FALSE | G42: =IF(OR(F42=TRUE(),F42="TRUE"),0,E42) -> 1 | H42: 9.19 | I42: =IF(H42="","",G42*H42) -> 9.19 | J42: Amazon.ca | K42: https://www.amazon.ca/dp/B0DJR583BY | L42: https://www.amazon.ca/s?k=5mm+led+holder+bezel | M42: 2026-10-08 | N42: Verified amazon.ca price | O42: =IF(AND(J42="Amazon.ca",G42>0,ISERROR(SEARCH("ALTERNATIVE",A42))),MAX(O$1:O41)+1,"") -> 35
A43: LED backlighting | B43: Mean Well LRS-50-5 (5 V 10 A) power supply | C43: Firmware caps strip at 8 A; inject power at start/middle/end | Listing: "Mean Well LRS-50-5 Switching Power Supply, Single Output, 5V, 10A, 50W, 3.9" L x 3.23" W x 1.18" H" | D43: LED strip power | E43: 1 | F43: =FALSE() -> FALSE | G43: =IF(OR(F43=TRUE(),F43="TRUE"),0,E43) -> 1 | H43: 31.75 | I43: =IF(H43="","",G43*H43) -> 31.75 | J43: Amazon.ca | K43: https://www.amazon.ca/dp/B019GYOCMM | L43: https://www.amazon.ca/s?k=mean+well+lrs-50-5 | M43: 2026-10-08 | N43: Verified amazon.ca price | O43: =IF(AND(J43="Amazon.ca",G43>0,ISERROR(SEARCH("ALTERNATIVE",A43))),MAX(O$1:O42)+1,"") -> 36
A44: LED backlighting | B44: Inline 5x20 mm fuse holders + fast-blow fuse kit | C44: Use a 10 A fuse at the PSU output | Listing: "Fuse Kit Car Fuses - 10pcs 5x20mm AGC Inline Fuse Holder + 100pcs 5x20mm Fast-Blow Glass Fuses Quick" | D44: LED PSU output fuse | E44: 1 | F44: =FALSE() -> FALSE | G44: =IF(OR(F44=TRUE(),F44="TRUE"),0,E44) -> 1 | H44: 14.99 | I44: =IF(H44="","",G44*H44) -> 14.99 | J44: Amazon.ca | K44: https://www.amazon.ca/dp/B07X8WL5TC | L44: https://www.amazon.ca/s?k=inline+fuse+holder+5x20+kit | M44: 2026-10-08 | N44: Verified amazon.ca price | O44: =IF(AND(J44="Amazon.ca",G44>0,ISERROR(SEARCH("ALTERNATIVE",A44))),MAX(O$1:O43)+1,"") -> 37
A45: LED backlighting | B45: 16 AWG red/black 2-conductor wire, 15 m (50 ft) | C45: LED power trunk. Prefer pure copper (check listing) | Listing: "VIABRICO 16AWG 50FT Electrical Wire Cable 2 Conductors Red Black Cable Hookup LED Lighting Strips Fl" | D45: LED 5 V trunk | E45: 1 | F45: =FALSE() -> FALSE | G45: =IF(OR(F45=TRUE(),F45="TRUE"),0,E45) -> 1 | H45: 16.99 | I45: =IF(H45="","",G45*H45) -> 16.99 | J45: Amazon.ca | K45: https://www.amazon.ca/dp/B0CNRTZ4N3 | L45: https://www.amazon.ca/s?k=16+awg+red+black+wire+copper | M45: 2026-10-08 | N45: Verified amazon.ca price | O45: =IF(AND(J45="Amazon.ca",G45>0,ISERROR(SEARCH("ALTERNATIVE",A45))),MAX(O$1:O44)+1,"") -> 38
A46: LED backlighting | B46: 18 AWG red/black silicone wire, 7.6 m (25 ft) | C46: Injection drops; 2nd roll for the 12 V switch circuits of the interlock | Listing: "BNTECHGO 18 AWG Silicone Wire Red Black 25ft Stranded Tinned Copper Wire" | D46: LED injection + interlock switch wiring | E46: 2 | F46: =FALSE() -> FALSE | G46: =IF(OR(F46=TRUE(),F46="TRUE"),0,E46) -> 2 | H46: 19.82 | I46: =IF(H46="","",G46*H46) -> 39.64 | J46: Amazon.ca | K46: https://www.amazon.ca/dp/B07HGTKQ89 | L46: https://www.amazon.ca/s?k=18+awg+red+black+silicone+wire | M46: 2026-10-08 | N46: Verified amazon.ca price | O46: =IF(AND(J46="Amazon.ca",G46>0,ISERROR(SEARCH("ALTERNATIVE",A46))),MAX(O$1:O45)+1,"") -> 39
A47: LED backlighting | B47: JST-SM 3-pin pigtails (WS2812), 60 pcs | C47: Panel-to-panel strip hops, removable panels | Listing: "JST SM 3 Pin Connectors for WS2812B WS2812 WS2811, 22AWG LED Male/Female Connector Adapter Open Wire" | D47: LED strip connectors | E47: 1 | F47: =FALSE() -> FALSE | G47: =IF(OR(F47=TRUE(),F47="TRUE"),0,E47) -> 1 | H47: 18.59 | I47: =IF(H47="","",G47*H47) -> 18.59 | J47: Amazon.ca | K47: https://www.amazon.ca/dp/B0CP94DL4F | L47: https://www.amazon.ca/s?k=jst+sm+3+pin+connector+ws2812 | M47: 2026-10-08 | N47: Verified amazon.ca price | O47: =IF(AND(J47="Amazon.ca",G47>0,ISERROR(SEARCH("ALTERNATIVE",A47))),MAX(O$1:O46)+1,"") -> 40
A48: Printed parts: filament & inserts | B48: PETG filament 1.75 mm BLACK, 1 kg | C48: Estimate 5.3 kg incl. 15 % waste (see Notes sheet) -> 6 spools. Panels, enclosures, mounts, harness hub (PETG required there) | Listing: "ELEGOO PETG 3D Printer Filament 1.75mm Black 1KG, Strong & Durable" | D48: All black printed parts | E48: 6 | F48: =FALSE() -> FALSE | G48: =IF(OR(F48=TRUE(),F48="TRUE"),0,E48) -> 6 | H48: 19.94 | I48: =IF(H48="","",G48*H48) -> 119.64 | J48: Amazon.ca | K48: https://www.amazon.ca/dp/B0D41Y3WWZ | L48: https://www.amazon.ca/s?k=petg+filament+1.75+black+1kg | M48: 2026-10-08 | N48: Verified amazon.ca price | O48: =IF(AND(J48="Amazon.ca",G48>0,ISERROR(SEARCH("ALTERNATIVE",A48))),MAX(O$1:O47)+1,"") -> 41
A49: Printed parts: filament & inserts | B49: PETG filament 1.75 mm WHITE, 1 kg | C49: Estimate only ~0.06 kg (letters/inserts) - 1 spool is plenty | Listing: "ELEGOO Rapid PETG 3D Printer Filament 1.75mm White 1KG" | D49: Backlit letters / letter inserts | E49: 1 | F49: =FALSE() -> FALSE | G49: =IF(OR(F49=TRUE(),F49="TRUE"),0,E49) -> 1 | H49: 20.89 | I49: =IF(H49="","",G49*H49) -> 20.89 | J49: Amazon.ca | K49: https://www.amazon.ca/dp/B0CMC78XKT | L49: https://www.amazon.ca/s?k=petg+filament+1.75+white+1kg | M49: 2026-10-08 | N49: Verified amazon.ca price | O49: =IF(AND(J49="Amazon.ca",G49>0,ISERROR(SEARCH("ALTERNATIVE",A49))),MAX(O$1:O48)+1,"") -> 42
A50: Printed parts: filament & inserts | B50: Brass heat-set inserts kit M2-M6 (360 pcs) | C50: Harness hub 5x M3 each; pivot cable clamps M4 | Listing: "Besitu 360Pcs Threaded Inserts M2 M2.5 M3 M4 M5 M6 Brass Heat Set Insert for Plastic Metric Knurled " | D50: Harness hub, pivot cable clamps | E50: 1 | F50: =FALSE() -> FALSE | G50: =IF(OR(F50=TRUE(),F50="TRUE"),0,E50) -> 1 | H50: 26.99 | I50: =IF(H50="","",G50*H50) -> 26.99 | J50: Amazon.ca | K50: https://www.amazon.ca/dp/B0CNRSJ1B2 | L50: https://www.amazon.ca/s?k=heat+set+inserts+kit+m3+m4 | M50: 2026-10-08 | N50: Verified amazon.ca price | O50: =IF(AND(J50="Amazon.ca",G50>0,ISERROR(SEARCH("ALTERNATIVE",A50))),MAX(O$1:O49)+1,"") -> 43
A51: Printed parts: filament & inserts | B51: Metric socket screw assortment M2-M5 (1760 pcs) | C51: Covers M3x20 (hub), M3x12, M4x12/16/20/25 (TD2220, monitors, clamps). Check M4 lengths vs your VESA inserts | Listing: "Besitu 1760pcs M2 M3 M4 M5 Metric Screw Assortment, Grade 12.9 Alloy Steel Hex Socket Head Cap Metri" | D51: Printed-part and display screws | E51: 1 | F51: =FALSE() -> FALSE | G51: =IF(OR(F51=TRUE(),F51="TRUE"),0,E51) -> 1 | H51: 28.99 | I51: =IF(H51="","",G51*H51) -> 28.99 | J51: Amazon.ca | K51: https://www.amazon.ca/dp/B0C38YFL3D | L51: https://www.amazon.ca/s?k=m2+m3+m4+m5+socket+head+screw+assortment | M51: 2026-10-08 | N51: Verified amazon.ca price | O51: =IF(AND(J51="Amazon.ca",G51>0,ISERROR(SEARCH("ALTERNATIVE",A51))),MAX(O$1:O50)+1,"") -> 44
A52: Printed parts: filament & inserts | B52: Self-tapping screw assortment M2 / M2.5 / M3 | C52: 12x M2.5x6 (perfboards) + 12x M3x10 (enclosure lids) | Listing: "1200Pcs M2 M2.5 M3 Small Phillips Flat Head Self Tapping Screws for Wood,Plastic and Soft Metal,Coun" | D52: ESP32 enclosures | E52: 1 | F52: =FALSE() -> FALSE | G52: =IF(OR(F52=TRUE(),F52="TRUE"),0,E52) -> 1 | H52: 16.99 | I52: =IF(H52="","",G52*H52) -> 16.99 | J52: Amazon.ca | K52: https://www.amazon.ca/dp/B09CT54JJZ | L52: https://www.amazon.ca/s?k=self+tapping+screw+assortment+m2.5+m3 | M52: 2026-10-08 | N52: Verified amazon.ca price | O52: =IF(AND(J52="Amazon.ca",G52>0,ISERROR(SEARCH("ALTERNATIVE",A52))),MAX(O$1:O51)+1,"") -> 45
A53: Frame lumber & sheet goods | B53: 2x4 SPF stud 8 ft (2438 mm), kiln dried | C53: 22 used by the cut list + 2 spares. 38 x 89 mm (1.5" x 3.5"). Pick straight boards. Kent Fredericton price (South/Bishop Dr and North/Two Nations Crossing, same price) checked 2026-10-09 | D53: Frame (see frame/cut_list.md) | E53: 24 | F53: =FALSE() -> FALSE | G53: =IF(OR(F53=TRUE(),F53="TRUE"),0,E53) -> 24 | H53: 3.98 | I53: =IF(H53="","",G53*H53) -> 95.52 | J53: Kent | K53: https://kent.ca/en/2-x-4-x-8-spf-stud-kiln-dried-1016318 | L53: https://kent.ca/en/search?q=2x4x8+stud | M53: 2026-10-09 | N53: Kent.ca web price (Fredericton store) | O53: =IF(AND(J53="Amazon.ca",G53>0,ISERROR(SEARCH("ALTERNATIVE",A53))),MAX(O$1:O52)+1,"")
... A57: Frame lumber & sheet goods | B57: 6 mm (1/4") hardboard or plywood, 4x8 ft | C57: Small covers / templates. Price shown is Kent 1/4" meranti ply (hardboard is cheaper) | D57: Covers, templates | E57: 1 | F57: =FALSE() -> FALSE | G57: =IF(OR(F57=TRUE(),F57="TRUE"),0,E57) -> 1 | H57: 24.99 | I57: =IF(H57="","",G57*H57) -> 24.99 | J57: Kent | K57: https://kent.ca/en/1-4-x-4-x-8-meranti-plywood-1015821 | L57: https://kent.ca/en/search?q=1%2F4+hardboard+4x8 | M57: 2026-10-09 | N57: Kent.ca web price (Fredericton store) | O57: =IF(AND(J57="Amazon.ca",G57>0,ISERROR(SEARCH("ALTERNATIVE",A57))),MAX(O$1:O56)+1,"")
A58: Fasteners & general hardware | B58: Construction screws 5 x 80 mm (#10 x 3"), 1 box | C58: 2x4 joints, 2 per joint min. | D58: Frame | E58: 1 | F58: =FALSE() -> FALSE | G58: =IF(OR(F58=TRUE(),F58="TRUE"),0,E58) -> 1 | H58: 25 | I58: =IF(H58="","",G58*H58) -> 25 | J58: Kent / Home Depot | L58: https://kent.ca/en/search?q=construction+screws+%2310+x+3 | N58: Estimate - check in store | O58: =IF(AND(J58="Amazon.ca",G58>0,ISERROR(SEARCH("ALTERNATIVE",A58))),MAX(O$1:O57)+1,"")
A59: Fasteners & general hardware | B59: Wood screws 4 x 40 mm (#8 x 1-1/2"), 1 box | C59: Ply to 2x4 | D59: Frame | E59: 1 | F59: =FALSE() -> FALSE | G59: =IF(OR(F59=TRUE(),F59="TRUE"),0,E59) -> 1 | H59: 15 | I59: =IF(H59="","",G59*H59) -> 15 | J59: Kent / Home Depot | L59: https://kent.ca/en/search?q=wood+screws+%238+x+1-1%2F2 | N59: Estimate - check in store | O59: =IF(AND(J59="Amazon.ca",G59>0,ISERROR(SEARCH("ALTERNATIVE",A59))),MAX(O$1:O58)+1,"")
A60: Fasteners & general hardware | B60: Wood screws 4 x 25 mm (#8 x 1"), 1 box | C60: Skins, clips, limit-switch brackets; also the 30x M4x25 countersunk screws for the TD2220 trim laps | D60: Frame, trim ring | E60: 1 | F60: =FALSE() -> FALSE | G60: =IF(OR(F60=TRUE(),F60="TRUE"),0,E60) -> 1 | H60: 12 | I60: =IF(H60="","",G60*H60) -> 12 | J60: Kent / Home Depot | L60: https://kent.ca/en/search?q=wood+screws+%238+x+1 | N60: Estimate - check in store | O60: =IF(AND(J60="Amazon.ca",G60>0,ISERROR(SEARCH("ALTERNATIVE",A60))),MAX(O$1:O59)+1,"")
A61: Fasteners & general hardware | B61: PVA wood glue, 1 L | C61: Cheek laminations, boxes | D61: Frame | E61: 1 | F61: =FALSE() -> FALSE | G61: =IF(OR(F61=TRUE(),F61="TRUE"),0,E61) -> 1 | H61: 15 | I61: =IF(H61="","",G61*H61) -> 15 | J61: Kent / Home Depot | L61: https://kent.ca/en/search?q=wood+glue+1+l | N61: Estimate - check in store | O61: =IF(AND(J61="Amazon.ca",G61>0,ISERROR(SEARCH("ALTERNATIVE",A61))),MAX(O$1:O60)+1,"")
A62: Fasteners & general hardware | B62: M5 four-prong T-nuts, M5 x 8 mm, 200 pcs | C62: Drill the barrel hole (~7 mm, check) on the 40 mm grid, press in from the back | Listing: "M4 M5 M6 M8 M10 M12 Carbon Steel 4 Prongs T Nut Tee Nuts Furniture Wood Insert (200,M5 x 8mm)" | D62: Panel bays | E62: 1 | F62: =FALSE() -> FALSE | G62: =IF(OR(F62=TRUE(),F62="TRUE"),0,E62) -> 1 | H62: 44.38 | I62: =IF(H62="","",G62*H62) -> 44.38 | J62: Amazon.ca | K62: https://www.amazon.ca/dp/B0FF4HDSK3 | L62: https://www.amazon.ca/s?k=m5+tee+nut+4+prong+200 | M62: 2026-10-08 | N62: Verified amazon.ca price | O62: =IF(AND(J62="Amazon.ca",G62>0,ISERROR(SEARCH("ALTERNATIVE",A62))),MAX(O$1:O61)+1,"") -> 46
A63: Fasteners & general hardware | B63: M5 x 20 flanged button-head socket screws, black, 50 pcs | C63: 200 needed -> 4 packs (flanged, washers optional) | Listing: "50Pcs M5 x 20mm Flanged Button Head Socket Cap Screws Bolts, Allen Socket Drive M5 Screws Bolts Blac" | D63: Panels into T-nuts | E63: 4 | F63: =FALSE() -> FALSE | G63: =IF(OR(F63=TRUE(),F63="TRUE"),0,E63) -> 4 | H63: 14.99 | I63: =IF(H63="","",G63*H63) -> 59.96 | J63: Amazon.ca | K63: https://www.amazon.ca/dp/B0FR1FQ1B7 | L63: https://www.amazon.ca/s?k=m5+x+20+button+head+socket+screw+black | M63: 2026-10-08 | N63: Verified amazon.ca price | O63: =IF(AND(J63="Amazon.ca",G63>0,ISERROR(SEARCH("ALTERNATIVE",A63))),MAX(O$1:O62)+1,"") -> 47
A64: Fasteners & general hardware | B64: M5 flat washers, 200 pcs | C64: Optional with flanged screws | Listing: "M5 Flat Washers Carbon Steel 200HV Color Zinc Plated, 200 PCS Metric Plain Washers Heavy Duty Hardwa" | D64: Panels | E64: 1 | F64: =FALSE() -> FALSE | G64: =IF(OR(F64=TRUE(),F64="TRUE"),0,E64) -> 1 | H64: 9.99 | I64: =IF(H64="","",G64*H64) -> 9.99 | J64: Amazon.ca | K64: https://www.amazon.ca/dp/B0GX28963L | L64: https://www.amazon.ca/s?k=m5+flat+washers+200 | M64: 2026-10-08 | N64: Verified amazon.ca price | O64: =IF(AND(J64="Amazon.ca",G64>0,ISERROR(SEARCH("ALTERNATIVE",A64))),MAX(O$1:O63)+1,"") -> 48
A65: Fasteners & general hardware | B65: M6 x 50 carriage bolts + fender washers + nylocks | C65: 2 printed monitor standoffs x 4 bolts through the pod back sheet | D65: Monitor standoffs | E65: 8 | F65: =FALSE() -> FALSE | G65: =IF(OR(F65=TRUE(),F65="TRUE"),0,E65) -> 8 | H65: 1.5 | I65: =IF(H65="","",G65*H65) -> 12 | J65: Kent / Home Depot | L65: https://kent.ca/en/search?q=m6+x+50+carriage+bolt | N65: Estimate - check in store | O65: =IF(AND(J65="Amazon.ca",G65>0,ISERROR(SEARCH("ALTERNATIVE",A65))),MAX(O$1:O64)+1,"")
A66: Fasteners & general hardware | B66: 2 mm stainless safety cable with loops, 300 mm (12"), 5 pcs | C66: REQUIRED: one per monitor, VESA screw -> eye screw in the back sheet, <= 50 mm slack (the pod parks monitors face-down). Plus 2 eye screws (Kent) | Listing: "PATIKIL 2mmD x 12" L Outdoor Travel Security Cable, 5PCS 304 Stainless Steel Safety Wire Rope Luggag" | D66: Monitor safety tethers | E66: 1 | F66: =FALSE() -> FALSE | G66: =IF(OR(F66=TRUE(),F66="TRUE"),0,E66) -> 1 | H66: 9.99 | I66: =IF(H66="","",G66*H66) -> 9.99 | J66: Amazon.ca | K66: https://www.amazon.ca/dp/B0FQP7W6J3 | L66: https://www.amazon.ca/s?k=2mm+stainless+safety+cable+loops+12+inch | M66: 2026-10-08 | N66: Verified amazon.ca price | O66: =IF(AND(J66="Amazon.ca",G66>0,ISERROR(SEARCH("ALTERNATIVE",A66))),MAX(O$1:O65)+1,"") -> 49
A67: Fasteners & general hardware | B67: Pivot bolts M6 x 30 + M4 x 40 with nylocks | C67: Throttle lever pivot (M6x30), gear lever pivot (M4x40) | D67: Throttle + gear lever | E67: 1 | F67: =FALSE() -> FALSE | G67: =IF(OR(F67=TRUE(),F67="TRUE"),0,E67) -> 1 | H67: 4 | I67: =IF(H67="","",G67*H67) -> 4 | J67: Kent / Home Depot | L67: https://kent.ca/en/search?q=m6+x+30+bolt | N67: Estimate - check in store | O67: =IF(AND(J67="Amazon.ca",G67>0,ISERROR(SEARCH("ALTERNATIVE",A67))),MAX(O$1:O66)+1,"")
A68: Motion system: pivots, shafts, bearings | B68: 25 mm linear shaft, 1000 mm, 2 pcs | C68: Cradle shaft (one per side). Case-hardened chrome rod is hard to cut - bright steel h9 from a metal supplier is the BOM spec and cuts easily | Listing: "VEVOR 2PCS Linear Motion Rod, 25 mm x 1000 mm (0.98 x 39.4 in), SFC25 Carbon Steel Linear Rod Shaft," | D68: Cradle pivot | E68: 1 | F68: =FALSE() -> FALSE | G68: =IF(OR(F68=TRUE(),F68="TRUE"),0,E68) -> 1 | H68: 46.99 | I68: =IF(H68="","",G68*H68) -> 46.99 | J68: Amazon.ca | K68: https://www.amazon.ca/dp/B0G5ZDQB47 | L68: https://www.amazon.ca/s?k=25mm+shaft+1000mm | M68: 2026-10-08 | N68: Verified amazon.ca price | O68: =IF(AND(J68="Amazon.ca",G68>0,ISERROR(SEARCH("ALTERNATIVE",A68))),MAX(O$1:O67)+1,"") -> 50
A69: Motion system: pivots, shafts, bearings | B69: 25 mm bright steel round bar (h9), 2 x ~250 mm | C69: Pod shaft stubs (tower post outer -> inner). Local metal supplier / cut from bar | D69: Pod pivot | E69: 1 | F69: =FALSE() -> FALSE | G69: =IF(OR(F69=TRUE(),F69="TRUE"),0,E69) -> 1 | H69: 30 | I69: =IF(H69="","",G69*H69) -> 30 | J69: Local metal supplier | L69: https://www.google.com/search?q=25mm+steel+round+bar+Fredericton+NB | N69: Estimate - get a quote | O69: =IF(AND(J69="Amazon.ca",G69>0,ISERROR(SEARCH("ALTERNATIVE",A69))),MAX(O$1:O68)+1,"")
A70: Motion system: pivots, shafts, bearings | B70: SHF25 shaft supports, 4 pcs | C70: 6 needed (cradle shaft on 2 pedestals, pod shaft on inner tower posts + 2 spare positions) -> 2 packs | Listing: "PATIKIL SHF25 Aluminum Linear Motion Rod Rail Clamping Guide Support, 4 Pcs for 25mm Dia Shaft" | D70: Cradle + pod shafts | E70: 2 | F70: =FALSE() -> FALSE | G70: =IF(OR(F70=TRUE(),F70="TRUE"),0,E70) -> 2 | H70: 13.49 | I70: =IF(H70="","",G70*H70) -> 26.98 | J70: Amazon.ca | K70: https://www.amazon.ca/dp/B0D9RTBQF2 | L70: https://www.amazon.ca/s?k=shf25+shaft+support | M70: 2026-10-08 | N70: Verified amazon.ca price | O70: =IF(AND(J70="Amazon.ca",G70>0,ISERROR(SEARCH("ALTERNATIVE",A70))),MAX(O$1:O69)+1,"") -> 51
A71: Motion system: pivots, shafts, bearings | B71: UCP205 pillow block bearings 25 mm, 2-pack | C71: Under the rear ends of the cradle rails | Listing: "XIKE UCP205 Pillow Block Bearing, 25 mm Bore, Self-Aligning Mounted Bearing Unit, 2-Pack" | D71: Cradle pivot | E71: 1 | F71: =FALSE() -> FALSE | G71: =IF(OR(F71=TRUE(),F71="TRUE"),0,E71) -> 1 | H71: 37.75 | I71: =IF(H71="","",G71*H71) -> 37.75 | J71: Amazon.ca | K71: https://www.amazon.ca/dp/B08HJYZK1X | L71: https://www.amazon.ca/s?k=ucp205+pillow+block+bearing+25mm | M71: 2026-10-08 | N71: Verified amazon.ca price | O71: =IF(AND(J71="Amazon.ca",G71>0,ISERROR(SEARCH("ALTERNATIVE",A71))),MAX(O$1:O70)+1,"") -> 52
A72: Motion system: pivots, shafts, bearings | B72: UCF205 4-bolt flange bearing 25 mm | C72: In the pod cheeks (one each side) | Listing: "uxcell UCF205 Flange Block Bearings 25mm Bore Cast Iron Bearing Unit Set Screw Lock" | D72: Pod pivot | E72: 2 | F72: =FALSE() -> FALSE | G72: =IF(OR(F72=TRUE(),F72="TRUE"),0,E72) -> 2 | H72: 20.79 | I72: =IF(H72="","",G72*H72) -> 41.58 | J72: Amazon.ca | K72: https://www.amazon.ca/dp/B0BLLVF9DB | L72: https://www.amazon.ca/s?k=ucf205+flange+bearing+25mm | M72: 2026-10-08 | N72: Verified amazon.ca price | O72: =IF(AND(J72="Amazon.ca",G72>0,ISERROR(SEARCH("ALTERNATIVE",A72))),MAX(O$1:O71)+1,"") -> 53
A73: Motion system: pivots, shafts, bearings | B73: 25 mm steel double-split shaft collars, 2 pcs | C73: 4 needed -> 2 packs | Listing: "uxcell 2pcs Double Split Shaft Collars 25mm Bore, Two-Piece Clamping Collar 38mm OD 12mm Thickness C" | D73: Stop shafts walking | E73: 2 | F73: =FALSE() -> FALSE | G73: =IF(OR(F73=TRUE(),F73="TRUE"),0,E73) -> 2 | H73: 17.49 | I73: =IF(H73="","",G73*H73) -> 34.98 | J73: Amazon.ca | K73: https://www.amazon.ca/dp/B0G2Q98L26 | L73: https://www.amazon.ca/s?k=25mm+shaft+collar+steel | M73: 2026-10-08 | N73: Verified amazon.ca price | O73: =IF(AND(J73="Amazon.ca",G73>0,ISERROR(SEARCH("ALTERNATIVE",A73))),MAX(O$1:O72)+1,"") -> 54
A74: Motion system: pivots, shafts, bearings | B74: 6 mm steel plate 120 x 120 mm with 4 holes | C74: Under the pod bearings / supports on the tower posts. Metal shop or cut from flat bar | D74: Pod pivot | E74: 4 | F74: =FALSE() -> FALSE | G74: =IF(OR(F74=TRUE(),F74="TRUE"),0,E74) -> 4 | H74: 10 | I74: =IF(H74="","",G74*H74) -> 40 | J74: Local metal supplier | L74: https://www.google.com/search?q=6mm+steel+plate+Fredericton+NB | N74: Estimate - get a quote | O74: =IF(AND(J74="Amazon.ca",G74>0,ISERROR(SEARCH("ALTERNATIVE",A74))),MAX(O$1:O73)+1,"")
A75: Motion system: pivots, shafts, bearings | B75: M10 x 90 coach screws + washers | C75: Bearings and shaft supports to the frame (~4 per bearing/support) | D75: Bearings | E75: 20 | F75: =FALSE() -> FALSE | G75: =IF(OR(F75=TRUE(),F75="TRUE"),0,E75) -> 20 | H75: 1.25 | I75: =IF(H75="","",G75*H75) -> 25 | J75: Kent / Home Depot | L75: https://kent.ca/en/search?q=m10+x+90+lag+screw | N75: Estimate - check in store | O75: =IF(AND(J75="Amazon.ca",G75>0,ISERROR(SEARCH("ALTERNATIVE",A75))),MAX(O$1:O74)+1,"")
A76: Motion system: pivots, shafts, bearings | B76: M8 x 60 bolts + nylocks + washers | C76: Actuator clevises (use your actuators' pin size) + strut brackets | D76: Actuators, struts | E76: 8 | F76: =FALSE() -> FALSE | G76: =IF(OR(F76=TRUE(),F76="TRUE"),0,E76) -> 8 | H76: 1.5 | I76: =IF(H76="","",G76*H76) -> 12 | J76: Kent / Home Depot | L76: https://kent.ca/en/search?q=m8+x+60+bolt | N76: Estimate - check in store | O76: =IF(AND(J76="Amazon.ca",G76>0,ISERROR(SEARCH("ALTERNATIVE",A76))),MAX(O$1:O75)+1,"")
A77: Motion system: drive & locks | B77: Cradle linear actuator 12 V, 10" (254 mm) stroke, 1500 N (330 lbf), self-locking | C77: Spec: ~364 mm (14.3") retracted pin-to-pin +-10 mm, <= 10 mm/s, internal limits, PUSH to recline; worst case ~775 N each. Listing (checked 2026-10-08): 250 mm stroke, retracted 370 mm (within +-10), extended 620 mm, self-locking, built-in limits, 4 A, brackets + polarity switch included | Listing: "Fast Linear Motion Actuator 10mm/s 12V Linear Actuator, 10" Stroke 330lb (1500N) Heavy Duty Actuator" | D77: Seat recline (2 per cradle) | E77: 2 | F77: =FALSE() -> FALSE | G77: =IF(OR(F77=TRUE(),F77="TRUE"),0,E77) -> 2 | H77: 62.33 | I77: =IF(H77="","",G77*H77) -> 124.66 | J77: Amazon.ca | K77: https://www.amazon.ca/dp/B0FKMS7Y12 | L77: https://www.amazon.ca/s?k=12v+linear+actuator+10+inch+stroke+330+lbs | M77: 2026-10-08 | N77: Verified amazon.ca price | O77: =IF(AND(J77="Amazon.ca",G77>0,ISERROR(SEARCH("ALTERNATIVE",A77))),MAX(O$1:O76)+1,"") -> 55
A78: Motion system: drive & locks | B78: Pod linear actuator 12 V, 12" (300 mm) stroke, 1500 N (330 lbf), self-locking - ONE (left casing) | C78: Spec: 420 mm retracted pin-to-pin (model uses 436 -> 706 mm of 420 -> 720), <= 10 mm/s, EXTEND to lower / RETRACT to raise; <= 561 N normally, 850 N if both struts fail (1.8x margin). Listing (checked 2026-10-10, CA$67.82): RVMARINEPAT LA03-12-300-1500N, 300 mm stroke, 420/720 mm, 10 mm/s, self-locking, built-in limits, 4 A, brackets + polarity switch; same family as the cradle actuators. Pick size "300-1500N" | Listing: "Electric Actuator 12V 12 Inch Stroke, 330lb Heavy Duty Linear Actuator Lift, High Speed Linear Actua" | D78: Pod rotate up/down (single actuator + torque tube) | E78: 1 | F78: =FALSE() -> FALSE | G78: =IF(OR(F78=TRUE(),F78="TRUE"),0,E78) -> 1 | H78: 67.82 | I78: =IF(H78="","",G78*H78) -> 67.82 | J78: Amazon.ca | K78: https://www.amazon.ca/dp/B0FKMVCQPC | L78: https://www.amazon.ca/s?k=12v+linear+actuator+12+inch+stroke+330+lbs+1500N | M78: 2026-10-08 | N78: Verified amazon.ca price | O78: =IF(AND(J78="Amazon.ca",G78>0,ISERROR(SEARCH("ALTERNATIVE",A78))),MAX(O$1:O77)+1,"") -> 56
A79: Motion system: drive & locks | B79: Gas struts (pair), ~250 mm extended, ~1050 N (235 lbf) each, M8 eye ends | C79: SPEC: F1 ~1050 N (buy 1000-1100 N), ~240 mm extended, >= 71 mm stroke, 10 mm rod / 22-28 mm body, M8 eyelets (NOT 10 mm ball studs - only ~890 N rated). Sized so the pod is LIFT-biased (+16..+88 N m): an actuator failure sends it UP. Candidate (not verifiable today): YLLL 250 mm universal gas strut pair, 1000/1100 N, 8 mm eye hole, https://www.amazon.ca/dp/B09VDN2PX8 - price is an estimate | D79: Pod counterbalance | E79: 1 | F79: =FALSE() -> FALSE | G79: =IF(OR(F79=TRUE(),F79="TRUE"),0,E79) -> 1 | H79: 60 | I79: =IF(H79="","",G79*H79) -> 60 | J79: Amazon.ca | L79: https://www.amazon.ca/s?k=gas+strut+1000N+250mm+M8+eyelet+pair | N79: No suitable listing found - estimate | O79: =IF(AND(J79="Amazon.ca",G79>0,ISERROR(SEARCH("ALTERNATIVE",A79))),MAX(O$1:O78)+1,"") -> 57
A80: Motion system: drive & locks | B80: Steel angle brackets 50 x 50 x 5 mm with M8 hole | C80: 2 strut anchors + 1 pod actuator anchor on the casings (heavy, not shelf brackets) | D80: Strut + actuator anchors | E80: 3 | F80: =FALSE() -> FALSE | G80: =IF(OR(F80=TRUE(),F80="TRUE"),0,E80) -> 3 | H80: 8 | I80: =IF(H80="","",G80*H80) -> 24 | J80: Kent / Home Depot | L80: https://kent.ca/en/search?q=heavy+steel+angle+bracket | N80: Estimate - check in store | O80: =IF(AND(J80="Amazon.ca",G80>0,ISERROR(SEARCH("ALTERNATIVE",A80))),MAX(O$1:O79)+1,"")
A81: Motion system: drive & locks | B81: Torque tube: 2" x 2" x 1/8" square steel tube (HSS / A500), 1600 mm | C81: Ties the right cheek to the driven left cheek, behind the back sheet between the 2x4 stiffener rails. 298 N m/deg: 0.42 deg (6 mm at the chin) with both struts failed; 1.5 deg / 32 MPa if the actuator stalls against a right-side stop. Cut to length at the metal shop | D81: Pod: one actuator drives both cheeks without racking | E81: 1 | F81: =FALSE() -> FALSE | G81: =IF(OR(F81=TRUE(),F81="TRUE"),0,E81) -> 1 | H81: 45 | I81: =IF(H81="","",G81*H81) -> 45 | J81: Local metal supplier | L81: https://www.google.com/search?q=2x2x1%2F8+square+steel+tube+Fredericton+NB | N81: Estimate - get a quote | O81: =IF(AND(J81="Amazon.ca",G81>0,ISERROR(SEARCH("ALTERNATIVE",A81))),MAX(O$1:O80)+1,"")
A82: Motion system: drive & locks | B82: 6 mm steel plates 150 x 61 mm, 4 x 11 mm holes (2 welded tube end plates + 2 backing plates) | C82: End plates welded square to the tube (or no-weld: 2 x 50x50x5 angles per end); backing plates on the outside of each cheek | D82: Torque tube to cheeks | E82: 4 | F82: =FALSE() -> FALSE | G82: =IF(OR(F82=TRUE(),F82="TRUE"),0,E82) -> 4 | H82: 10 | I82: =IF(H82="","",G82*H82) -> 40 | J82: Local metal supplier | L82: https://www.google.com/search?q=6mm+steel+plate+cut+to+size+welding+Fredericton+NB | N82: Estimate - get a quote | O82: =IF(AND(J82="Amazon.ca",G82>0,ISERROR(SEARCH("ALTERNATIVE",A82))),MAX(O$1:O81)+1,"")
A83: Motion system: drive & locks | B83: M10 x 70 bolts grade 8.8 + nylocks + washers | C83: 4 per tube end through the 36 mm cheek + backing plate; 1 mm reamed holes, torque to spec | D83: Torque tube to cheeks | E83: 8 | F83: =FALSE() -> FALSE | G83: =IF(OR(F83=TRUE(),F83="TRUE"),0,E83) -> 8 | H83: 2 | I83: =IF(H83="","",G83*H83) -> 16 | J83: Kent / Home Depot | L83: https://kent.ca/en/search?q=m10+x+70+bolt+grade+8.8 | N83: Estimate - check in store | O83: =IF(AND(J83="Amazon.ca",G83>0,ISERROR(SEARCH("ALTERNATIVE",A83))),MAX(O$1:O82)+1,"")
A84: Motion system: drive & locks | B84: 6 mm steel latch plates with UP and DOWN notches | C84: Laser cut / filed from cheek template drawing 06; bolted to the cheeks | D84: Pod mechanical locks | E84: 2 | F84: =FALSE() -> FALSE | G84: =IF(OR(F84=TRUE(),F84="TRUE"),0,E84) -> 2 | H84: 25 | I84: =IF(H84="","",G84*H84) -> 50 | J84: Local metal supplier | L84: https://www.google.com/search?q=laser+cutting+steel+plate+Fredericton+NB | N84: Estimate - get a quote | O84: =IF(AND(J84="Amazon.ca",G84>0,ISERROR(SEARCH("ALTERNATIVE",A84))),MAX(O$1:O83)+1,"")
A85: Motion system: drive & locks | B85: Spring-loaded steel pawl (barrel bolt / gate latch) | C85: Engages the latch plates, one per casing | Listing: "PEAKTOW PTT0023 Heavy Duty 6-7/8” Metal Lock Barrel Bolt Spring Loaded Latch W/Hardware for Gate Doo" | D85: Pod mechanical locks | E85: 2 | F85: =FALSE() -> FALSE | G85: =IF(OR(F85=TRUE(),F85="TRUE"),0,E85) -> 2 | H85: 16.99 | I85: =IF(H85="","",G85*H85) -> 33.98 | J85: Amazon.ca | K85: https://www.amazon.ca/dp/B07GZHSCP6 | L85: https://www.amazon.ca/s?k=spring+loaded+barrel+bolt+latch+heavy+duty | M85: 2026-10-08 | N85: Verified amazon.ca price | O85: =IF(AND(J85="Amazon.ca",G85>0,ISERROR(SEARCH("ALTERNATIVE",A85))),MAX(O$1:O84)+1,"") -> 58
A86: Motion system: drive & locks | B86: Bowden cables + levers (bike brake lever set) | C86: Release both pawls from the lever box left of dad's seat (second hand needed for pod motion) | Listing: "Glarks 8Pcs Bike Brake Set Including 2 Pairs Black V-Type Brakes, 1 Pair Handlebars Brake Levers, 2P" | D86: Pod lock release | E86: 1 | F86: =FALSE() -> FALSE | G86: =IF(OR(F86=TRUE(),F86="TRUE"),0,E86) -> 1 | H86: 23.99 | I86: =IF(H86="","",G86*H86) -> 23.99 | J86: Amazon.ca | K86: https://www.amazon.ca/dp/B0B8C66T4Q | L86: https://www.amazon.ca/s?k=bicycle+brake+lever+cable+set | M86: 2026-10-08 | N86: Verified amazon.ca price | O86: =IF(AND(J86="Amazon.ca",G86>0,ISERROR(SEARCH("ALTERNATIVE",A86))),MAX(O$1:O85)+1,"") -> 59
A87: Motion system: drive & locks | B87: Steel stop pins 12 mm (or 1/2" bolts) for hard stops | C87: Pod UP / DOWN hard stops on the cheeks hitting steel angles | D87: Pod hard stops | E87: 4 | F87: =FALSE() -> FALSE | G87: =IF(OR(F87=TRUE(),F87="TRUE"),0,E87) -> 4 | H87: 4 | I87: =IF(H87="","",G87*H87) -> 16 | J87: Kent / Home Depot | L87: https://kent.ca/en/search?q=1%2F2+inch+clevis+pin | N87: Estimate - check in store | O87: =IF(AND(J87="Amazon.ca",G87>0,ISERROR(SEARCH("ALTERNATIVE",A87))),MAX(O$1:O86)+1,"")
A88: Motion system: drive & locks | B88: Rubber bumper / stop pads with screws (assorted) | C88: Bumpers on the pod stop pins; cradle recline stop (10 mm) and upright stop (6 mm) pads | Listing: "Swpeet 52 Sets 3 Sizes 18mm & 24mm & 30mm Round Black Furniture Pads with Screws, Heavy Duty Rubber " | D88: Hard stops | E88: 1 | F88: =FALSE() -> FALSE | G88: =IF(OR(F88=TRUE(),F88="TRUE"),0,E88) -> 1 | H88: 17.99 | I88: =IF(H88="","",G88*H88) -> 17.99 | J88: Amazon.ca | K88: https://www.amazon.ca/dp/B0D1XSZ8SF | L88: https://www.amazon.ca/s?k=rubber+bumper+pads+with+screws | M88: 2026-10-08 | N88: Verified amazon.ca price | O88: =IF(AND(J88="Amazon.ca",G88>0,ISERROR(SEARCH("ALTERNATIVE",A88))),MAX(O$1:O87)+1,"") -> 60
A89: Motion system: hardwired interlock | B89: 12 V 20 A (240 W) enclosed power supply | C89: BOM: 12 V 20 A, enclosed, mains fused. Only one motion runs at a time (cradle: 2 actuators in parallel, pod: 1 actuator) | Listing: "inShareplus 12V 20A 240W, DC Universal Regulated Switching Power Supply, Converter AC 100-240V to DC" | D89: Actuator power | E89: 1 | F89: =FALSE() -> FALSE | G89: =IF(OR(F89=TRUE(),F89="TRUE"),0,E89) -> 1 | H89: 33.99 | I89: =IF(H89="","",G89*H89) -> 33.99 | J89: Amazon.ca | K89: https://www.amazon.ca/dp/B07RJMG3FB | L89: https://www.amazon.ca/s?k=12v+20a+power+supply+enclosed | M89: 2026-10-08 | N89: Verified amazon.ca price | O89: =IF(AND(J89="Amazon.ca",G89>0,ISERROR(SEARCH("ALTERNATIVE",A89))),MAX(O$1:O88)+1,"") -> 61
A90: Motion system: hardwired interlock | B90: Inline ATC fuse holder 12 AWG with 20/30/40 A fuses | C90: Use the 20 A blade fuse, right at the PSU | Listing: "DaierTek Inline Fuse Holder 12 AWG Waterproof ATC/ATO Blade Fuse Holder with 20 Amp 30 Amp 40 Amp In" | D90: Actuator circuit fuse | E90: 1 | F90: =FALSE() -> FALSE | G90: =IF(OR(F90=TRUE(),F90="TRUE"),0,E90) -> 1 | H90: 18.99 | I90: =IF(H90="","",G90*H90) -> 18.99 | J90: Amazon.ca | K90: https://www.amazon.ca/dp/B0BHY1RQQR | L90: https://www.amazon.ca/s?k=12+awg+inline+atc+fuse+holder | M90: 2026-10-08 | N90: Verified amazon.ca price | O90: =IF(AND(J90="Amazon.ca",G90>0,ISERROR(SEARCH("ALTERNATIVE",A90))),MAX(O$1:O89)+1,"") -> 62
A91: Motion system: hardwired interlock | B91: 19 mm key switch, 2 position (MOTION key) - drives a 30 A relay | C91: Key out = no motion. Same part as MASTER POWER | Listing: "19mm 3/4" ON/OFF Rotary Key Switch, Metal Lock Switch with Kept Lock and Wired Lock (19mm 2 Position" | D91: CMD_B MOTION key | E91: 1 | F91: =FALSE() -> FALSE | G91: =IF(OR(F91=TRUE(),F91="TRUE"),0,E91) -> 1 | H91: 26.11 | I91: =IF(H91="","",G91*H91) -> 26.11 | J91: Amazon.ca | K91: https://www.amazon.ca/dp/B09M849WCK | L91: https://www.amazon.ca/s?k=19mm+key+switch+2+position | M91: 2026-10-08 | N91: Verified amazon.ca price | O91: =IF(AND(J91="Amazon.ca",G91>0,ISERROR(SEARCH("ALTERNATIVE",A91))),MAX(O$1:O90)+1,"") -> 63
A92: Motion system: hardwired interlock | B92: 22 mm mushroom E-stop, NC, latching, twist release | C92: In series with the whole motion circuit | Listing: "uxcell 22mm NC N/C Red Mushroom Emergency Stop Push Button Switch 600V 10A Plastic Mounting" | D92: CMD_B STOP | E92: 1 | F92: =FALSE() -> FALSE | G92: =IF(OR(F92=TRUE(),F92="TRUE"),0,E92) -> 1 | H92: 16.24 | I92: =IF(H92="","",G92*H92) -> 16.24 | J92: Amazon.ca | K92: https://www.amazon.ca/dp/B019DSZWPC | L92: https://www.amazon.ca/s?k=22mm+emergency+stop+nc | M92: 2026-10-08 | N92: Verified amazon.ca price | O92: =IF(AND(J92="Amazon.ca",G92>0,ISERROR(SEARCH("ALTERNATIVE",A92))),MAX(O$1:O91)+1,"") -> 64
A93: Motion system: hardwired interlock | B93: DPDT (ON)-OFF-(ON) momentary toggle, 12 mm bushing | C93: Hold-to-run FLT / BRD (CREW POS); relays carry the motor current. Check bushing/hole size | Listing: "Joinfworld Momentary Toggle Switch 12V DC 3 Way 30 Amp DPDT 6 Pin (ON)-Off-(ON) Waterproof Marine To" | D93: CMD_B hold-to-run | E93: 1 | F93: =FALSE() -> FALSE | G93: =IF(OR(F93=TRUE(),F93="TRUE"),0,E93) -> 1 | H93: 13.98 | I93: =IF(H93="","",G93*H93) -> 13.98 | J93: Amazon.ca | K93: https://www.amazon.ca/dp/B0C22K75FZ | L93: https://www.amazon.ca/s?k=dpdt+momentary+toggle+on+off+on | M93: 2026-10-08 | N93: Verified amazon.ca price | O93: =IF(AND(J93="Amazon.ca",G93>0,ISERROR(SEARCH("ALTERNATIVE",A93))),MAX(O$1:O92)+1,"") -> 65
A94: Motion system: hardwired interlock | B94: 12 V 30/40 A automotive relays SPDT 5-pin, 10 pcs | C94: 5 needed: 4 as two H-bridges (cradle: 2 actuators in parallel; pod: the single actuator) + 1 for the key. Add relay sockets/harnesses | Listing: "10 Pcs 5-Pin Automotive Relays, 12V 30/40 A SPDT Relays, Electrical Relays Switch for Truck Marine B" | D94: Motor switching | E94: 1 | F94: =FALSE() -> FALSE | G94: =IF(OR(F94=TRUE(),F94="TRUE"),0,E94) -> 1 | H94: 22.99 | I94: =IF(H94="","",G94*H94) -> 22.99 | J94: Amazon.ca | K94: https://www.amazon.ca/dp/B0DNJVMMF9 | L94: https://www.amazon.ca/s?k=12v+30a+relay+spdt+5+pin | M94: 2026-10-08 | N94: Verified amazon.ca price | O94: =IF(AND(J94="Amazon.ca",G94>0,ISERROR(SEARCH("ALTERNATIVE",A94))),MAX(O$1:O93)+1,"") -> 66
A95: Motion system: hardwired interlock | B95: V-15 roller-lever micro switches 15 A, 10 pcs | C95: 10 needed (8 motor-path limit/lock switches: CRADLE_UPRIGHT, CRADLE_RECLINED x2, ONE pod limit set POD_UP + POD_DOWN on the left/driven cheek only, POD_UP_LOCKED x2, lever switch; + 2 READ contacts) + printed limit_switch_mount; 2nd pack = spares | Listing: "10pcs Micro Switches V-156-1C25 15A 125/250VAC Hinge Roller Lever Switch" | D95: Limit + lock switches | E95: 2 | F95: =FALSE() -> FALSE | G95: =IF(OR(F95=TRUE(),F95="TRUE"),0,E95) -> 2 | H95: 16.69 | I95: =IF(H95="","",G95*H95) -> 33.38 | J95: Amazon.ca | K95: https://www.amazon.ca/dp/B0F8HJ4V9J | L95: https://www.amazon.ca/s?k=v-156-1c25+roller+lever+micro+switch+15a | M95: 2026-10-08 | N95: Verified amazon.ca price | O95: =IF(AND(J95="Amazon.ca",G95>0,ISERROR(SEARCH("ALTERNATIVE",A95))),MAX(O$1:O94)+1,"") -> 67
A96: Motion system: hardwired interlock | B96: 6A10 rectifier diodes (6 A, 1000 V), 20 pcs | C96: 8 needed across the motor-path limit switches (frame BOM says 1N5408 3 A; 6A10 per electronics README is the stronger choice) | Listing: "(Pack of 20 Pieces) Chanzon 6A10 Rectifier Diode 6A 1000V R-6 Axial 6 Amp 1000 Volt Electronic Silic" | D96: Limit switch drive-back diodes | E96: 1 | F96: =FALSE() -> FALSE | G96: =IF(OR(F96=TRUE(),F96="TRUE"),0,E96) -> 1 | H96: 8.99 | I96: =IF(H96="","",G96*H96) -> 8.99 | J96: Amazon.ca | K96: https://www.amazon.ca/dp/B079KF3VJG | L96: https://www.amazon.ca/s?k=6a10+diode | M96: 2026-10-08 | N96: Verified amazon.ca price | O96: =IF(AND(J96="Amazon.ca",G96>0,ISERROR(SEARCH("ALTERNATIVE",A96))),MAX(O$1:O95)+1,"") -> 68
A97: Motion system: hardwired interlock | B97: Pressure-sensitive safety edge (NC), ~900 mm, with mounting profile | C97: Along the pod chin, in series with "pod DOWN". Not found on amazon.ca - industrial / gate-operator supplier; price is a placeholder | D97: Pod pinch protection | E97: 1 | F97: =FALSE() -> FALSE | G97: =IF(OR(F97=TRUE(),F97="TRUE"),0,E97) -> 1 | H97: 150 | I97: =IF(H97="","",G97*H97) -> 150 | J97: Industrial supplier | L97: https://www.amazon.ca/s?k=pressure+sensitive+safety+edge+NC | N97: Estimate - get a quote | O97: =IF(AND(J97="Amazon.ca",G97>0,ISERROR(SEARCH("ALTERNATIVE",A97))),MAX(O$1:O96)+1,"")
A98: Motion system: hardwired interlock | B98: 14 AWG red/black 2-conductor wire, 15 m (50 ft) | C98: 20 m needed -> 2 rolls. Use pure copper (not CCA) for motor current | Listing: "14 Gauge Electrical Wire 50FT, 14 AWG 2 Pin Red and Black Cable 12V" | D98: Actuator power path | E98: 2 | F98: =FALSE() -> FALSE | G98: =IF(OR(F98=TRUE(),F98="TRUE"),0,E98) -> 2 | H98: 17.09 | I98: =IF(H98="","",G98*H98) -> 34.18 | J98: Amazon.ca | K98: https://www.amazon.ca/dp/B0CXY76JGX | L98: https://www.amazon.ca/s?k=14+awg+red+black+copper+wire+50+ft | M98: 2026-10-08 | N98: Verified amazon.ca price | O98: =IF(AND(J98="Amazon.ca",G98>0,ISERROR(SEARCH("ALTERNATIVE",A98))),MAX(O$1:O97)+1,"") -> 69
A99: Motion system: hardwired interlock | B99: Heat-shrink ring terminal kit, 260 pcs (22-10 AWG) | C99: Plus heat shrink; printed cable clips | Listing: "260PCS Heat Shrink Ring Connectors with Thicker Red Copper, AWG22-10 Waterproof Electrical Terminals" | D99: Interlock wiring | E99: 1 | F99: =FALSE() -> FALSE | G99: =IF(OR(F99=TRUE(),F99="TRUE"),0,E99) -> 1 | H99: 29.99 | I99: =IF(H99="","",G99*H99) -> 29.99 | J99: Amazon.ca | K99: https://www.amazon.ca/dp/B0B569WMNP | L99: https://www.amazon.ca/s?k=heat+shrink+ring+terminal+kit | M99: 2026-10-08 | N99: Verified amazon.ca price | O99: =IF(AND(J99="Amazon.ca",G99>0,ISERROR(SEARCH("ALTERNATIVE",A99))),MAX(O$1:O98)+1,"") -> 70
A100: Motion system: guards | B100: Strip brush 25 mm in aluminium holder, ~5 m | C100: 4 m for the cheek slots (2 edges each) + 1 m for the nose-box actuator slots. Not found as a good match on amazon.ca; placeholder price | D100: Slot guards | E100: 1 | F100: =FALSE() -> FALSE | G100: =IF(OR(F100=TRUE(),F100="TRUE"),0,E100) -> 1 | H100: 60 | I100: =IF(H100="","",G100*H100) -> 60 | J100: Amazon.ca | L100: https://www.amazon.ca/s?k=strip+brush+aluminum+holder+25mm | N100: No suitable listing found - estimate | O100: =IF(AND(J100="Amazon.ca",G100>0,ISERROR(SEARCH("ALTERNATIVE",A100))),MAX(O$1:O99)+1,"") -> 71
A101: Motion system: guards | B101: High-density foam 25 mm (1") x 610 x 1830 mm | C101: Pod chin (behind the safety edge) and pod lower edges; cover with the vinyl below | Listing: "FoamTouch High Density Upholstery Foam (1" x 24" x 72"), 1.79LB Density-45LB ILD, Made in USA – Idea" | D101: Pod edge padding | E101: 1 | F101: =FALSE() -> FALSE | G101: =IF(OR(F101=TRUE(),F101="TRUE"),0,E101) -> 1 | H101: 32.15 | I101: =IF(H101="","",G101*H101) -> 32.15 | J101: Amazon.ca | K101: https://www.amazon.ca/dp/B0DQXC46NQ | L101: https://www.amazon.ca/s?k=high+density+foam+1+inch+24+x+72 | M101: 2026-10-08 | N101: Verified amazon.ca price | O101: =IF(AND(J101="Amazon.ca",G101>0,ISERROR(SEARCH("ALTERNATIVE",A101))),MAX(O$1:O100)+1,"") -> 72
A102: Seats & harnesses | B102: Buckle kit: 25 mm side-release buckles + 9 m webbing (REDAPRIC) | C102: REQUIRED LINK per design. WARNING: plastic (POM) luggage/backpack buckles, seller quotes ~50-136 kg breaking load, NOT safety-rated. Positioning harness only (see docs/mechanical/README.md safety note). Use the kit webbing for nothing structural. 2 kid seats x 4 buckles = 8 of 10. No featured offer on 2026-10-08 (other sellers only): price is a placeholder | Listing: "1 Inch 10 Yards Nylon Webbing Strap Kit with 10 Quick Release Side Buckles & 20 Tri-Glide Slides, No" | D102: Kid 4-point harness + printed harness_hub | E102: 1 | F102: =FALSE() -> FALSE | G102: =IF(OR(F102=TRUE(),F102="TRUE"),0,E102) -> 1 | H102: 13 | I102: =IF(H102="","",G102*H102) -> 13 | J102: Amazon.ca | K102: https://www.amazon.ca/dp/B0B3J1GCVQ | L102: https://www.amazon.ca/s?k=1+inch+side+release+buckle+kit | M102: 2026-10-08 | N102: Link verified; price NOT shown (placeholder estimate) | O102: =IF(AND(J102="Amazon.ca",G102>0,ISERROR(SEARCH("ALTERNATIVE",A102))),MAX(O$1:O101)+1,"") -> 73
A103: Seats & harnesses | B103: Rated 25 mm (1") webbing, >= 700 kg | C103: BOM asks polyester >= 700 kg; this is 1" nylon tubular climbing webbing Listing: UIAA/CE certified, 17.8 kN (4000 lb). Choose the 10 yd length variant | Listing: "NewDoar 1 Inch Nylon Webbing Strap/Tubular Climbing Webbing - Heavy Duty Strap for Rescue, Climbing," | D103: Kid harness straps (sewn bar-tack loops) | E103: 1 | F103: =FALSE() -> FALSE | G103: =IF(OR(F103=TRUE(),F103="TRUE"),0,E103) -> 1 | H103: 19.99 | I103: =IF(H103="","",G103*H103) -> 19.99 | J103: Amazon.ca | K103: https://www.amazon.ca/dp/B0B7RHCFMV | L103: https://www.amazon.ca/s?k=1+inch+rated+webbing+4000+lb+polyester | M103: 2026-10-08 | N103: Verified amazon.ca price | O103: =IF(AND(J103="Amazon.ca",G103>0,ISERROR(SEARCH("ALTERNATIVE",A103))),MAX(O$1:O102)+1,"") -> 74
A104: Seats & harnesses | B104: Welded steel O-rings 50 mm (2") OD | C104: Listing: 50 mm ID, 5 mm wire, 304 stainless, 6-pack, NOT load-rated (BOM asks 50 mm OD, 6 mm wire, rated - a rated welded ring from a rigging supplier is better) | Listing: "BEYOURD 2 inch Metal O Rings, Stainless Steel Round Ring Buckles, Solid Welded Metal Loop for Dog Co" | D104: Harness hub load ring (2 needed) | E104: 1 | F104: =FALSE() -> FALSE | G104: =IF(OR(F104=TRUE(),F104="TRUE"),0,E104) -> 1 | H104: 15.99 | I104: =IF(H104="","",G104*H104) -> 15.99 | J104: Amazon.ca | K104: https://www.amazon.ca/dp/B0D781P6JB | L104: https://www.amazon.ca/s?k=welded+steel+o+ring+2+inch+heavy+duty | M104: 2026-10-08 | N104: Verified amazon.ca price | O104: =IF(AND(J104="Amazon.ca",G104>0,ISERROR(SEARCH("ALTERNATIVE",A104))),MAX(O$1:O103)+1,"") -> 75
A105: Seats & harnesses | B105: Welded steel D-rings 25 mm (1") | C105: Optional - you asked for D-rings; frame BOM v0.2 only uses the O-ring. Useful as strap adjust/anchor points | Listing: "BEYOURD Metal D Rings, Heavy Duty 304 Stainless Steel Welded Dee Rings" | D105: Harness adjusters (optional) | E105: 1 | F105: =FALSE() -> FALSE | G105: =IF(OR(F105=TRUE(),F105="TRUE"),0,E105) -> 1 | H105: 15.97 | I105: =IF(H105="","",G105*H105) -> 15.97 | J105: Amazon.ca | K105: https://www.amazon.ca/dp/B0CS9SL864 | L105: https://www.amazon.ca/s?k=welded+steel+d+ring+1+inch | M105: 2026-10-08 | N105: Verified amazon.ca price | O105: =IF(AND(J105="Amazon.ca",G105>0,ISERROR(SEARCH("ALTERNATIVE",A105))),MAX(O$1:O104)+1,"") -> 76
A106: Seats & harnesses | B106: 3/8" (M10) forged eye bolts + fender washers + nylocks | C106: Forged, not bent-wire. Anchors THROUGH the cradle rails / seat-back frames, never plywood alone | D106: Harness anchors | E106: 10 | F106: =FALSE() -> FALSE | G106: =IF(OR(F106=TRUE(),F106="TRUE"),0,E106) -> 10 | H106: 6 | I106: =IF(H106="","",G106*H106) -> 60 | J106: Kent / Home Depot | L106: https://kent.ca/en/search?q=forged+eye+bolt+3%2F8 | N106: Estimate - check in store | O106: =IF(AND(J106="Amazon.ca",G106>0,ISERROR(SEARCH("ALTERNATIVE",A106))),MAX(O$1:O105)+1,"")
A107: Seats & harnesses | B107: 2-point adjustable lap belt | C107: Dad: fixed seat, no recline | Listing: "Universal 2 Point Seat Belt - Adjustable Lap Replacement for Most Cars, Strap with Buckle, Safety Ca" | D107: Commander seat | E107: 1 | F107: =FALSE() -> FALSE | G107: =IF(OR(F107=TRUE(),F107="TRUE"),0,E107) -> 1 | H107: 24.99 | I107: =IF(H107="","",G107*H107) -> 24.99 | J107: Amazon.ca | K107: https://www.amazon.ca/dp/B0BFPZ5ZGW | L107: https://www.amazon.ca/s?k=2+point+lap+belt+adjustable | M107: 2026-10-08 | N107: Verified amazon.ca price | O107: =IF(AND(J107="Amazon.ca",G107>0,ISERROR(SEARCH("ALTERNATIVE",A107))),MAX(O$1:O106)+1,"") -> 77
A108: Seats & harnesses | B108: High-density upholstery foam 50 mm (2") x 610 x 1830 mm | C108: Cushions: kids 340 x 380, dad 520 x 480; offcut stacked as the 60-80 mm booster for the 6 yr | Listing: "AK TRADING CO. AK-Trading Upholstery High Density 2" Height x 24" Width x 72" Length-Home or Commerc" | D108: Seat cushions | E108: 1 | F108: =FALSE() -> FALSE | G108: =IF(OR(F108=TRUE(),F108="TRUE"),0,E108) -> 1 | H108: 54.54 | I108: =IF(H108="","",G108*H108) -> 54.54 | J108: Amazon.ca | K108: https://www.amazon.ca/dp/B078SJ86G7 | L108: https://www.amazon.ca/s?k=high+density+foam+2+inch+24+x+72 | M108: 2026-10-08 | N108: Verified amazon.ca price | O108: =IF(AND(J108="Amazon.ca",G108>0,ISERROR(SEARCH("ALTERNATIVE",A108))),MAX(O$1:O107)+1,"") -> 78
A109: Seats & harnesses | B109: Marine vinyl, black, 1.5 m x 1.37 m (5 ft x 54") | C109: Covers for 3 cushions + pod chin foam | Listing: "VViViD Black Weatherproof Faux Leather Finish Marine Vinyl Fabric - 5ft x 54 Inch" | D109: Upholstery | E109: 1 | F109: =FALSE() -> FALSE | G109: =IF(OR(F109=TRUE(),F109="TRUE"),0,E109) -> 1 | H109: 43.69 | I109: =IF(H109="","",G109*H109) -> 43.69 | J109: Amazon.ca | K109: https://www.amazon.ca/dp/B0744QFFS8 | L109: https://www.amazon.ca/s?k=marine+vinyl+fabric+black | M109: 2026-10-08 | N109: Verified amazon.ca price | O109: =IF(AND(J109="Amazon.ca",G109>0,ISERROR(SEARCH("ALTERNATIVE",A109))),MAX(O$1:O108)+1,"") -> 79
A110: Seats & harnesses - ALTERNATIVE (not in totals) | B110: ALTERNATIVE: complete 4-point harness, 50 mm (2") straps, metal buckle | C110: Instead of the DIY buckle-kit harness: a bought go-kart/sim 4-point harness with metal latch (frame BOM v0.1 recommendation). Check it fits a kid (6-12 yr) torso. Excluded from Grand total and Amazon cart | Listing: "RASTP 4 Point Racing Safety Harness Set with 2" Straps for Racing Seat&Go Kart Seat,Dark Red(Pack of" | D110: Kid seats (instead of buckle kit + webbing + O-rings) | E110: 2 | F110: =FALSE() -> FALSE | G110: =IF(OR(F110=TRUE(),F110="TRUE"),0,E110) -> 2 | H110: 55.99 | I110: =IF(H110="","",G110*H110) -> 111.98 | J110: Amazon.ca | K110: https://www.amazon.ca/dp/B08TB7NLJB | L110: https://www.amazon.ca/s?k=4+point+harness+metal+buckle+2+inch | M110: 2026-10-08 | N110: Verified amazon.ca price | O110: =IF(AND(J110="Amazon.ca",G110>0,ISERROR(SEARCH("ALTERNATIVE",A110))),MAX(O$1:O109)+1,"")

Sheet Summary
A1: Category | B1: Lines | C1: Lines still to buy | D1: Total to buy CAD
A2: Computer & displays (owned) | B2: =COUNTIF(BOM!$A$2:$A$110,A2) -> 6 | C2: =COUNTIFS(BOM!$A$2:$A$110,A2,BOM!$G$2:$G$110,">0") -> 0 | D2: =SUMIF(BOM!$A$2:$A$110,A2,BOM!$I$2:$I$110) -> 0
A3: Video & USB cabling | B3: =COUNTIF(BOM!$A$2:$A$110,A3) -> 7 | C3: =COUNTIFS(BOM!$A$2:$A$110,A3,BOM!$G$2:$G$110,">0") -> 7 | D3: =SUMIF(BOM!$A$2:$A$110,A3,BOM!$I$2:$I$110) -> 123.69
A4: Controllers & logic | B4: =COUNTIF(BOM!$A$2:$A$110,A4) -> 16 | C4: =COUNTIFS(BOM!$A$2:$A$110,A4,BOM!$G$2:$G$110,">0") -> 16 | D4: =SUMIF(BOM!$A$2:$A$110,A4,BOM!$I$2:$I$110) -> 295.28
A5: Panel controls | B5: =COUNTIF(BOM!$A$2:$A$110,A5) -> 9 | C5: =COUNTIFS(BOM!$A$2:$A$110,A5,BOM!$G$2:$G$110,">0") -> 9 | D5: =SUMIF(BOM!$A$2:$A$110,A5,BOM!$I$2:$I$110) -> 198.92
A6: LED backlighting | B6: =COUNTIF(BOM!$A$2:$A$110,A6) -> 8 | C6: =COUNTIFS(BOM!$A$2:$A$110,A6,BOM!$G$2:$G$110,">0") -> 8 | D6: =SUMIF(BOM!$A$2:$A$110,A6,BOM!$I$2:$I$110) -> 177.14
A7: Printed parts: filament & inserts | B7: =COUNTIF(BOM!$A$2:$A$110,A7) -> 5 | C7: =COUNTIFS(BOM!$A$2:$A$110,A7,BOM!$G$2:$G$110,">0") -> 5 | D7: =SUMIF(BOM!$A$2:$A$110,A7,BOM!$I$2:$I$110) -> 213.5
A8: Frame lumber & sheet goods | B8: =COUNTIF(BOM!$A$2:$A$110,A8) -> 5 | C8: =COUNTIFS(BOM!$A$2:$A$110,A8,BOM!$G$2:$G$110,">0") -> 5 | D8: =SUMIF(BOM!$A$2:$A$110,A8,BOM!$I$2:$I$110) -> 676.07
A9: Fasteners & general hardware | B9: =COUNTIF(BOM!$A$2:$A$110,A9) -> 10 | C9: =COUNTIFS(BOM!$A$2:$A$110,A9,BOM!$G$2:$G$110,">0") -> 10 | D9: =SUMIF(BOM!$A$2:$A$110,A9,BOM!$I$2:$I$110) -> 207.32
A10: Motion system: pivots, shafts, bearings | B10: =COUNTIF(BOM!$A$2:$A$110,A10) -> 9 | C10: =COUNTIFS(BOM!$A$2:$A$110,A10,BOM!$G$2:$G$110,">0") -> 9 | D10: =SUMIF(BOM!$A$2:$A$110,A10,BOM!$I$2:$I$110) -> 295.28
A11: Motion system: drive & locks | B11: =COUNTIF(BOM!$A$2:$A$110,A11) -> 12 | C11: =COUNTIFS(BOM!$A$2:$A$110,A11,BOM!$G$2:$G$110,">0") -> 12 | D11: =SUMIF(BOM!$A$2:$A$110,A11,BOM!$I$2:$I$110) -> 519.44
A12: Motion system: hardwired interlock | B12: =COUNTIF(BOM!$A$2:$A$110,A12) -> 11 | C12: =COUNTIFS(BOM!$A$2:$A$110,A12,BOM!$G$2:$G$110,">0") -> 11 | D12: =SUMIF(BOM!$A$2:$A$110,A12,BOM!$I$2:$I$110) -> 388.84
A13: Motion system: guards | B13: =COUNTIF(BOM!$A$2:$A$110,A13) -> 2 | C13: =COUNTIFS(BOM!$A$2:$A$110,A13,BOM!$G$2:$G$110,">0") -> 2 | D13: =SUMIF(BOM!$A$2:$A$110,A13,BOM!$I$2:$I$110) -> 92.15
... A15: Seats & harnesses - ALTERNATIVE (not in totals) | B15: =COUNTIF(BOM!$A$2:$A$110,A15) -> 1 | C15: =COUNTIFS(BOM!$A$2:$A$110,A15,BOM!$G$2:$G$110,">0") -> 1 | D15: =SUMIF(BOM!$A$2:$A$110,A15,BOM!$I$2:$I$110) -> 111.98
A17: GRAND TOTAL to buy (excl. ALTERNATIVE rows) | C17: =SUMPRODUCT((ISERROR(SEARCH("ALTERNATIVE",A2:A15)))*C2:C15) -> 102 | D17: =SUMPRODUCT((ISERROR(SEARCH("ALTERNATIVE",A2:A15)))*D2:D15) -> 3435.8
A18: of which Amazon.ca | D18: =SUMPRODUCT((BOM!$J$2:$J$110="Amazon.ca")*ISERROR(SEARCH("ALTERNATIVE",BOM!$A$2:$A$110))*N(+BOM!$I$2:$I$110)) -> 2168.73
A19: of which Kent / Home Depot | D19: =SUMPRODUCT(ISNUMBER(SEARCH("Kent",BOM!$J$2:$J$110))*N(+BOM!$I$2:$I$110)) -> 912.07
A20: of which local / industrial suppliers | D20: =SUMPRODUCT((ISNUMBER(SEARCH("supplier",BOM!$J$2:$J$110)))*N(+BOM!$I$2:$I$110)) -> 355
A21: of which based on VERIFIED prices (amazon.ca / kent.ca) | D21: =SUMPRODUCT((ISNUMBER(SEARCH("Verified amazon.ca price",BOM!$N$2:$N$110))+ISNUMBER(SEARCH("Kent.ca web price",BOM!$N$2:$N$110))>0)*ISERROR(SEARCH("ALTERNATIVE",BOM!$A$2:$A$110))*N(+BOM!$I$2:$I$110)) -> 2691.8
A22: of which ESTIMATES / placeholders | D22: =SUMPRODUCT((ISNUMBER(SEARCH("estimate",BOM!$N$2:$N$110)))*ISERROR(SEARCH("ALTERNATIVE",BOM!$A$2:$A$110))*N(+BOM!$I$2:$I$110)) -> 744
A23: ALTERNATIVE rated harness option (if chosen) | D23: =SUMPRODUCT(ISNUMBER(SEARCH("ALTERNATIVE",BOM!$A$2:$A$110))*N(+BOM!$I$2:$I$110)) -> 111.98
A25: Totals update automatically when you change "Have it" on the BOM sheet (TRUE = already owned -> Qty to buy 0).
A26: Prices are before tax/shipping (NB HST 15 %). Amazon prices change daily; dates are in the BOM sheet.

Sheet Amazon cart
A1: # | B1: Item | C1: Qty to buy | D1: Unit price CAD | E1: Line total | F1: Link | G1: Search link | I1: Lists only Amazon.ca rows with Qty to buy > 0 (alternatives excluded). Built with INDEX/MATCH on a hidden helper column (BOM!O) so it works in every LibreOffice and Excel version (FILTER needs LO 24.8+/Excel 365). Updates when Have it changes.
A2: =IF(ISNA(MATCH(1,BOM!$O$2:$O$110,0)),"",1) -> 1 | B2: =IF($A2="","",INDEX(BOM!$B$2:$B$110,MATCH(1,BOM!$O$2:$O$110,0))) -> DisplayPort 1.4 cable, 3 m (10 ft), VESA certified | C2: =IF($A2="","",INDEX(BOM!$G$2:$G$110,MATCH(1,BOM!$O$2:$O$110,0))) -> 1 | D2: =IF($A2="","",INDEX(BOM!$H$2:$H$110,MATCH(1,BOM!$O$2:$O$110,0))) -> 16.99 | E2: =IF($A2="","",INDEX(BOM!$I$2:$I$110,MATCH(1,BOM!$O$2:$O$110,0))) -> 16.99 | F2: =IF($A2="","",IF(INDEX(BOM!$K$2:$K$110,MATCH(1,BOM!$O$2:$O$110,0))="","",HYPERLINK(INDEX(BOM!$K$2:$K$110,MATCH(1,BOM!$O$2:$O$110,0)),"open on amazon.ca"))) -> open on amazon.ca | G2: =IF($A2="","",HYPERLINK(INDEX(BOM!$L$2:$L$110,MATCH(1,BOM!$O$2:$O$110,0)),"search")) -> search
A3: =IF(ISNA(MATCH(2,BOM!$O$2:$O$110,0)),"",2) -> 2 | B3: =IF($A3="","",INDEX(BOM!$B$2:$B$110,MATCH(2,BOM!$O$2:$O$110,0))) -> HDMI cable, 3 m (10 ft) | C3: =IF($A3="","",INDEX(BOM!$G$2:$G$110,MATCH(2,BOM!$O$2:$O$110,0))) -> 1 | D3: =IF($A3="","",INDEX(BOM!$H$2:$H$110,MATCH(2,BOM!$O$2:$O$110,0))) -> 10.76 | E3: =IF($A3="","",INDEX(BOM!$I$2:$I$110,MATCH(2,BOM!$O$2:$O$110,0))) -> 10.76 | F3: =IF($A3="","",IF(INDEX(BOM!$K$2:$K$110,MATCH(2,BOM!$O$2:$O$110,0))="","",HYPERLINK(INDEX(BOM!$K$2:$K$110,MATCH(2,BOM!$O$2:$O$110,0)),"open on amazon.ca"))) -> open on amazon.ca | G3: =IF($A3="","",HYPERLINK(INDEX(BOM!$L$2:$L$110,MATCH(2,BOM!$O$2:$O$110,0)),"search")) -> search
A4: =IF(ISNA(MATCH(3,BOM!$O$2:$O$110,0)),"",3) -> 3 | B4: =IF($A4="","",INDEX(BOM!$B$2:$B$110,MATCH(3,BOM!$O$2:$O$110,0))) -> DisplayPort -> DVI-D adapter cable, passive, 3 m (10 ft) | C4: =IF($A4="","",INDEX(BOM!$G$2:$G$110,MATCH(3,BOM!$O$2:$O$110,0))) -> 1 | D4: =IF($A4="","",INDEX(BOM!$H$2:$H$110,MATCH(3,BOM!$O$2:$O$110,0))) -> 16.99 | E4: =IF($A4="","",INDEX(BOM!$I$2:$I$110,MATCH(3,BOM!$O$2:$O$110,0))) -> 16.99 | F4: =IF($A4="","",IF(INDEX(BOM!$K$2:$K$110,MATCH(3,BOM!$O$2:$O$110,0))="","",HYPERLINK(INDEX(BOM!$K$2:$K$110,MATCH(3,BOM!$O$2:$O$110,0)),"open on amazon.ca"))) -> open on amazon.ca | G4: =IF($A4="","",HYPERLINK(INDEX(BOM!$L$2:$L$110,MATCH(3,BOM!$O$2:$O$110,0)),"search")) -> search
A5: =IF(ISNA(MATCH(4,BOM!$O$2:$O$110,0)),"",4) -> 4 | B5: =IF($A5="","",INDEX(BOM!$B$2:$B$110,MATCH(4,BOM!$O$2:$O$110,0))) -> USB-A to USB-B cable, 3 m (10 ft) | C5: =IF($A5="","",INDEX(BOM!$G$2:$G$110,MATCH(4,BOM!$O$2:$O$110,0))) -> 1 | D5: =IF($A5="","",INDEX(BOM!$H$2:$H$110,MATCH(4,BOM!$O$2:$O$110,0))) -> 12.99 | E5: =IF($A5="","",INDEX(BOM!$I$2:$I$110,MATCH(4,BOM!$O$2:$O$110,0))) -> 12.99 | F5: =IF($A5="","",IF(INDEX(BOM!$K$2:$K$110,MATCH(4,BOM!$O$2:$O$110,0))="","",HYPERLINK(INDEX(BOM!$K$2:$K$110,MATCH(4,BOM!$O$2:$O$110,0)),"open on amazon.ca"))) -> open on amazon.ca | G5: =IF($A5="","",HYPERLINK(INDEX(BOM!$L$2:$L$110,MATCH(4,BOM!$O$2:$O$110,0)),"search")) -> search
A6: =IF(ISNA(MATCH(5,BOM!$O$2:$O$110,0)),"",5) -> 5 | B6: =IF($A6="","",INDEX(BOM!$B$2:$B$110,MATCH(5,BOM!$O$2:$O$110,0))) -> USB-A to USB-C data cables 1.8 m (6 ft), 3-pack | C6: =IF($A6="","",INDEX(BOM!$G$2:$G$110,MATCH(5,BOM!$O$2:$O$110,0))) -> 1 | D6: =IF($A6="","",INDEX(BOM!$H$2:$H$110,MATCH(5,BOM!$O$2:$O$110,0))) -> 9.99 | E6: =IF($A6="","",INDEX(BOM!$I$2:$I$110,MATCH(5,BOM!$O$2:$O$110,0))) -> 9.99 | F6: =IF($A6="","",IF(INDEX(BOM!$K$2:$K$110,MATCH(5,BOM!$O$2:$O$110,0))="","",HYPERLINK(INDEX(BOM!$K$2:$K$110,MATCH(5,BOM!$O$2:$O$110,0)),"open on amazon.ca"))) -> open on amazon.ca | G6: =IF($A6="","",HYPERLINK(INDEX(BOM!$L$2:$L$110,MATCH(5,BOM!$O$2:$O$110,0)),"search")) -> search
A7: =IF(ISNA(MATCH(6,BOM!$O$2:$O$110,0)),"",6) -> 6 | B7: =IF($A7="","",INDEX(BOM!$B$2:$B$110,MATCH(6,BOM!$O$2:$O$110,0))) -> Powered USB 3.0 hub, 7-port, with power adapter | C7: =IF($A7="","",INDEX(BOM!$G$2:$G$110,MATCH(6,BOM!$O$2:$O$110,0))) -> 1 | D7: =IF($A7="","",INDEX(BOM!$H$2:$H$110,MATCH(6,BOM!$O$2:$O$110,0))) -> 39.99 | E7: =IF($A7="","",INDEX(BOM!$I$2:$I$110,MATCH(6,BOM!$O$2:$O$110,0))) -> 39.99 | F7: =IF($A7="","",IF(INDEX(BOM!$K$2:$K$110,MATCH(6,BOM!$O$2:$O$110,0))="","",HYPERLINK(INDEX(BOM!$K$2:$K$110,MATCH(6,BOM!$O$2:$O$110,0)),"open on amazon.ca"))) -> open on amazon.ca | G7: =IF($A7="","",HYPERLINK(INDEX(BOM!$L$2:$L$110,MATCH(6,BOM!$O$2:$O$110,0)),"search")) -> search
A8: =IF(ISNA(MATCH(7,BOM!$O$2:$O$110,0)),"",7) -> 7 | B8: =IF($A8="","",INDEX(BOM!$B$2:$B$110,MATCH(7,BOM!$O$2:$O$110,0))) -> Expandable braided sleeve 25 mm (1"), 7.6 m (25 ft) | C8: =IF($A8="","",INDEX(BOM!$G$2:$G$110,MATCH(7,BOM!$O$2:$O$110,0))) -> 1 | D8: =IF($A8="","",INDEX(BOM!$H$2:$H$110,MATCH(7,BOM!$O$2:$O$110,0))) -> 15.98 | E8: =IF($A8="","",INDEX(BOM!$I$2:$I$110,MATCH(7,BOM!$O$2:$O$110,0))) -> 15.98 | F8: =IF($A8="","",IF(INDEX(BOM!$K$2:$K$110,MATCH(7,BOM!$O$2:$O$110,0))="","",HYPERLINK(INDEX(BOM!$K$2:$K$110,MATCH(7,BOM!$O$2:$O$110,0)),"open on amazon.ca"))) -> open on amazon.ca | G8: =IF($A8="","",HYPERLINK(INDEX(BOM!$L$2:$L$110,MATCH(7,BOM!$O$2:$O$110,0)),"search")) -> search
A9: =IF(ISNA(MATCH(8,BOM!$O$2:$O$110,0)),"",8) -> 8 | B9: =IF($A9="","",INDEX(BOM!$B$2:$B$110,MATCH(8,BOM!$O$2:$O$110,0))) -> ESP32-S3-DevKitC-1-N8R8, 5-pack | C9: =IF($A9="","",INDEX(BOM!$G$2:$G$110,MATCH(8,BOM!$O$2:$O$110,0))) -> 1 | D9: =IF($A9="","",INDEX(BOM!$H$2:$H$110,MATCH(8,BOM!$O$2:$O$110,0))) -> 71.98 | E9: =IF($A9="","",INDEX(BOM!$I$2:$I$110,MATCH(8,BOM!$O$2:$O$110,0))) -> 71.98 | F9: =IF($A9="","",IF(INDEX(BOM!$K$2:$K$110,MATCH(8,BOM!$O$2:$O$110,0))="","",HYPERLINK(INDEX(BOM!$K$2:$K$110,MATCH(8,BOM!$O$2:$O$110,0)),"open on amazon.ca"))) -> open on amazon.ca | G9: =IF($A9="","",HYPERLINK(INDEX(BOM!$L$2:$L$110,MATCH(8,BOM!$O$2:$O$110,0)),"search")) -> search
A10: =IF(ISNA(MATCH(9,BOM!$O$2:$O$110,0)),"",9) -> 9 | B10: =IF($A10="","",INDEX(BOM!$B$2:$B$110,MATCH(9,BOM!$O$2:$O$110,0))) -> 74HC165 shift register DIP-16, 25 pcs | C10: =IF($A10="","",INDEX(BOM!$G$2:$G$110,MATCH(9,BOM!$O$2:$O$110,0))) -> 1 | D10: =IF($A10="","",INDEX(BOM!$H$2:$H$110,MATCH(9,BOM!$O$2:$O$110,0))) -> 18.49 | E10: =IF($A10="","",INDEX(BOM!$I$2:$I$110,MATCH(9,BOM!$O$2:$O$110,0))) -> 18.49 | F10: =IF($A10="","",IF(INDEX(BOM!$K$2:$K$110,MATCH(9,BOM!$O$2:$O$110,0))="","",HYPERLINK(INDEX(BOM!$K$2:$K$110,MATCH(9,BOM!$O$2:$O$110,0)),"open on amazon.ca"))) -> open on amazon.ca | G10: =IF($A10="","",HYPERLINK(INDEX(BOM!$L$2:$L$110,MATCH(9,BOM!$O$2:$O$110,0)),"search")) -> search
A11: =IF(ISNA(MATCH(10,BOM!$O$2:$O$110,0)),"",10) -> 10 | B11: =IF($A11="","",INDEX(BOM!$B$2:$B$110,MATCH(10,BOM!$O$2:$O$110,0))) -> DIP IC socket assortment (incl. 14- and 16-pin) | C11: =IF($A11="","",INDEX(BOM!$G$2:$G$110,MATCH(10,BOM!$O$2:$O$110,0))) -> 1 | D11: =IF($A11="","",INDEX(BOM!$H$2:$H$110,MATCH(10,BOM!$O$2:$O$110,0))) -> 16.99 | E11: =IF($A11="","",INDEX(BOM!$I$2:$I$110,MATCH(10,BOM!$O$2:$O$110,0))) -> 16.99 | F11: =IF($A11="","",IF(INDEX(BOM!$K$2:$K$110,MATCH(10,BOM!$O$2:$O$110,0))="","",HYPERLINK(INDEX(BOM!$K$2:$K$110,MATCH(10,BOM!$O$2:$O$110,0)),"open on amazon.ca"))) -> open on amazon.ca | G11: =IF($A11="","",HYPERLINK(INDEX(BOM!$L$2:$L$110,MATCH(10,BOM!$O$2:$O$110,0)),"search")) -> search
A12: =IF(ISNA(MATCH(11,BOM!$O$2:$O$110,0)),"",11) -> 11 | B12: =IF($A12="","",INDEX(BOM!$B$2:$B$110,MATCH(11,BOM!$O$2:$O$110,0))) -> 10 kOhm bussed resistor network SIP-9 (A103J), 20 pcs | C12: =IF($A12="","",INDEX(BOM!$G$2:$G$110,MATCH(11,BOM!$O$2:$O$110,0))) -> 1 | D12: =IF($A12="","",INDEX(BOM!$H$2:$H$110,MATCH(11,BOM!$O$2:$O$110,0))) -> 8.88 | E12: =IF($A12="","",INDEX(BOM!$I$2:$I$110,MATCH(11,BOM!$O$2:$O$110,0))) -> 8.88 | F12: =IF($A12="","",IF(INDEX(BOM!$K$2:$K$110,MATCH(11,BOM!$O$2:$O$110,0))="","",HYPERLINK(INDEX(BOM!$K$2:$K$110,MATCH(11,BOM!$O$2:$O$110,0)),"open on amazon.ca"))) -> open on amazon.ca | G12: =IF($A12="","",HYPERLINK(INDEX(BOM!$L$2:$L$110,MATCH(11,BOM!$O$2:$O$110,0)),"search")) -> search
A13: =IF(ISNA(MATCH(12,BOM!$O$2:$O$110,0)),"",12) -> 12 | B13: =IF($A13="","",INDEX(BOM!$B$2:$B$110,MATCH(12,BOM!$O$2:$O$110,0))) -> 100 nF ceramic capacitors, 100 pcs | C13: =IF($A13="","",INDEX(BOM!$G$2:$G$110,MATCH(12,BOM!$O$2:$O$110,0))) -> 1 | D13: =IF($A13="","",INDEX(BOM!$H$2:$H$110,MATCH(12,BOM!$O$2:$O$110,0))) -> 6.55 | E13: =IF($A13="","",INDEX(BOM!$I$2:$I$110,MATCH(12,BOM!$O$2:$O$110,0))) -> 6.55 | F13: =IF($A13="","",IF(INDEX(BOM!$K$2:$K$110,MATCH(12,BOM!$O$2:$O$110,0))="","",HYPERLINK(INDEX(BOM!$K$2:$K$110,MATCH(12,BOM!$O$2:$O$110,0)),"open on amazon.ca"))) -> open on amazon.ca | G13: =IF($A13="","",HYPERLINK(INDEX(BOM!$L$2:$L$110,MATCH(12,BOM!$O$2:$O$110,0)),"search")) -> search
A14: =IF(ISNA(MATCH(13,BOM!$O$2:$O$110,0)),"",13) -> 13 | B14: =IF($A14="","",INDEX(BOM!$B$2:$B$110,MATCH(13,BOM!$O$2:$O$110,0))) -> Electrolytic capacitor assortment 0.1-1000 uF (10-50 V) | C14: =IF($A14="","",INDEX(BOM!$G$2:$G$110,MATCH(13,BOM!$O$2:$O$110,0))) -> 1 | D14: =IF($A14="","",INDEX(BOM!$H$2:$H$110,MATCH(13,BOM!$O$2:$O$110,0))) -> 16.99 | E14: =IF($A14="","",INDEX(BOM!$I$2:$I$110,MATCH(13,BOM!$O$2:$O$110,0))) -> 16.99 | F14: =IF($A14="","",IF(INDEX(BOM!$K$2:$K$110,MATCH(13,BOM!$O$2:$O$110,0))="","",HYPERLINK(INDEX(BOM!$K$2:$K$110,MATCH(13,BOM!$O$2:$O$110,0)),"open on amazon.ca"))) -> open on amazon.ca | G14: =IF($A14="","",HYPERLINK(INDEX(BOM!$L$2:$L$110,MATCH(13,BOM!$O$2:$O$110,0)),"search")) -> search
A15: =IF(ISNA(MATCH(14,BOM!$O$2:$O$110,0)),"",14) -> 14 | B15: =IF($A15="","",INDEX(BOM!$B$2:$B$110,MATCH(14,BOM!$O$2:$O$110,0))) -> 74AHCT125N DIP-14 level shifter, 10 pcs | C15: =IF($A15="","",INDEX(BOM!$G$2:$G$110,MATCH(14,BOM!$O$2:$O$110,0))) -> 1 | D15: =IF($A15="","",INDEX(BOM!$H$2:$H$110,MATCH(14,BOM!$O$2:$O$110,0))) -> 11.56 | E15: =IF($A15="","",INDEX(BOM!$I$2:$I$110,MATCH(14,BOM!$O$2:$O$110,0))) -> 11.56 | F15: =IF($A15="","",IF(INDEX(BOM!$K$2:$K$110,MATCH(14,BOM!$O$2:$O$110,0))="","",HYPERLINK(INDEX(BOM!$K$2:$K$110,MATCH(14,BOM!$O$2:$O$110,0)),"open on amazon.ca"))) -> open on amazon.ca | G15: =IF($A15="","",HYPERLINK(INDEX(BOM!$L$2:$L$110,MATCH(14,BOM!$O$2:$O$110,0)),"search")) -> search
A16: =IF(ISNA(MATCH(15,BOM!$O$2:$O$110,0)),"",15) -> 15 | B16: =IF($A16="","",INDEX(BOM!$B$2:$B$110,MATCH(15,BOM!$O$2:$O$110,0))) -> Resistor kit 1/4 W 1%, 50 values | C16: =IF($A16="","",INDEX(BOM!$G$2:$G$110,MATCH(15,BOM!$O$2:$O$110,0))) -> 1 | D16: =IF($A16="","",INDEX(BOM!$H$2:$H$110,MATCH(15,BOM!$O$2:$O$110,0))) -> 19.99 | E16: =IF($A16="","",INDEX(BOM!$I$2:$I$110,MATCH(15,BOM!$O$2:$O$110,0))) -> 19.99 | F16: =IF($A16="","",IF(INDEX(BOM!$K$2:$K$110,MATCH(15,BOM!$O$2:$O$110,0))="","",HYPERLINK(INDEX(BOM!$K$2:$K$110,MATCH(15,BOM!$O$2:$O$110,0)),"open on amazon.ca"))) -> open on amazon.ca | G16: =IF($A16="","",HYPERLINK(INDEX(BOM!$L$2:$L$110,MATCH(15,BOM!$O$2:$O$110,0)),"search")) -> search
A17: =IF(ISNA(MATCH(16,BOM!$O$2:$O$110,0)),"",16) -> 16 | B17: =IF($A17="","",INDEX(BOM!$B$2:$B$110,MATCH(16,BOM!$O$2:$O$110,0))) -> 2.2 kOhm 1/2 W resistors, 10 pcs | C17: =IF($A17="","",INDEX(BOM!$G$2:$G$110,MATCH(16,BOM!$O$2:$O$110,0))) -> 1 | D17: =IF($A17="","",INDEX(BOM!$H$2:$H$110,MATCH(16,BOM!$O$2:$O$110,0))) -> 8.76 | E17: =IF($A17="","",INDEX(BOM!$I$2:$I$110,MATCH(16,BOM!$O$2:$O$110,0))) -> 8.76 | F17: =IF($A17="","",IF(INDEX(BOM!$K$2:$K$110,MATCH(16,BOM!$O$2:$O$110,0))="","",HYPERLINK(INDEX(BOM!$K$2:$K$110,MATCH(16,BOM!$O$2:$O$110,0)),"open on amazon.ca"))) -> open on amazon.ca | G17: =IF($A17="","",HYPERLINK(INDEX(BOM!$L$2:$L$110,MATCH(16,BOM!$O$2:$O$110,0)),"search")) -> search
A18: =IF(ISNA(MATCH(17,BOM!$O$2:$O$110,0)),"",17) -> 17 | B18: =IF($A18="","",INDEX(BOM!$B$2:$B$110,MATCH(17,BOM!$O$2:$O$110,0))) -> PC817 optocoupler DIP-4, 20 pcs | C18: =IF($A18="","",INDEX(BOM!$G$2:$G$110,MATCH(17,BOM!$O$2:$O$110,0))) -> 1 | D18: =IF($A18="","",INDEX(BOM!$H$2:$H$110,MATCH(17,BOM!$O$2:$O$110,0))) -> 10.68 | E18: =IF($A18="","",INDEX(BOM!$I$2:$I$110,MATCH(17,BOM!$O$2:$O$110,0))) -> 10.68 | F18: =IF($A18="","",IF(INDEX(BOM!$K$2:$K$110,MATCH(17,BOM!$O$2:$O$110,0))="","",HYPERLINK(INDEX(BOM!$K$2:$K$110,MATCH(17,BOM!$O$2:$O$110,0)),"open on amazon.ca"))) -> open on amazon.ca | G18: =IF($A18="","",HYPERLINK(INDEX(BOM!$L$2:$L$110,MATCH(17,BOM!$O$2:$O$110,0)),"search")) -> search
A19: =IF(ISNA(MATCH(18,BOM!$O$2:$O$110,0)),"",18) -> 18 | B19: =IF($A19="","",INDEX(BOM!$B$2:$B$110,MATCH(18,BOM!$O$2:$O$110,0))) -> Perfboard 7 x 9 cm, 10 pcs | C19: =IF($A19="","",INDEX(BOM!$G$2:$G$110,MATCH(18,BOM!$O$2:$O$110,0))) -> 1 | D19: =IF($A19="","",INDEX(BOM!$H$2:$H$110,MATCH(18,BOM!$O$2:$O$110,0))) -> 12.96 | E19: =IF($A19="","",INDEX(BOM!$I$2:$I$110,MATCH(18,BOM!$O$2:$O$110,0))) -> 12.96 | F19: =IF($A19="","",IF(INDEX(BOM!$K$2:$K$110,MATCH(18,BOM!$O$2:$O$110,0))="","",HYPERLINK(INDEX(BOM!$K$2:$K$110,MATCH(18,BOM!$O$2:$O$110,0)),"open on amazon.ca"))) -> open on amazon.ca | G19: =IF($A19="","",HYPERLINK(INDEX(BOM!$L$2:$L$110,MATCH(18,BOM!$O$2:$O$110,0)),"search")) -> search
A20: =IF(ISNA(MATCH(19,BOM!$O$2:$O$110,0)),"",19) -> 19 | B20: =IF($A20="","",INDEX(BOM!$B$2:$B$110,MATCH(19,BOM!$O$2:$O$110,0))) -> 2.54 mm male + female pin header kit | C20: =IF($A20="","",INDEX(BOM!$G$2:$G$110,MATCH(19,BOM!$O$2:$O$110,0))) -> 1 | D20: =IF($A20="","",INDEX(BOM!$H$2:$H$110,MATCH(19,BOM!$O$2:$O$110,0))) -> 18.99 | E20: =IF($A20="","",INDEX(BOM!$I$2:$I$110,MATCH(19,BOM!$O$2:$O$110,0))) -> 18.99 | F20: =IF($A20="","",IF(INDEX(BOM!$K$2:$K$110,MATCH(19,BOM!$O$2:$O$110,0))="","",HYPERLINK(INDEX(BOM!$K$2:$K$110,MATCH(19,BOM!$O$2:$O$110,0)),"open on amazon.ca"))) -> open on amazon.ca | G20: =IF($A20="","",HYPERLINK(INDEX(BOM!$L$2:$L$110,MATCH(19,BOM!$O$2:$O$110,0)),"search")) -> search
A21: =IF(ISNA(MATCH(20,BOM!$O$2:$O$110,0)),"",20) -> 20 | B21: =IF($A21="","",INDEX(BOM!$B$2:$B$110,MATCH(20,BOM!$O$2:$O$110,0))) -> JST-XH 2.54 mm connector kit with pre-crimped leads | C21: =IF($A21="","",INDEX(BOM!$G$2:$G$110,MATCH(20,BOM!$O$2:$O$110,0))) -> 1 | D21: =IF($A21="","",INDEX(BOM!$H$2:$H$110,MATCH(20,BOM!$O$2:$O$110,0))) -> 20.99 | E21: =IF($A21="","",INDEX(BOM!$I$2:$I$110,MATCH(20,BOM!$O$2:$O$110,0))) -> 20.99 | F21: =IF($A21="","",IF(INDEX(BOM!$K$2:$K$110,MATCH(20,BOM!$O$2:$O$110,0))="","",HYPERLINK(INDEX(BOM!$K$2:$K$110,MATCH(20,BOM!$O$2:$O$110,0)),"open on amazon.ca"))) -> open on amazon.ca | G21: =IF($A21="","",HYPERLINK(INDEX(BOM!$L$2:$L$110,MATCH(20,BOM!$O$2:$O$110,0)),"search")) -> search
A22: =IF(ISNA(MATCH(21,BOM!$O$2:$O$110,0)),"",21) -> 21 | B22: =IF($A22="","",INDEX(BOM!$B$2:$B$110,MATCH(21,BOM!$O$2:$O$110,0))) -> Dupont jumper wires, 120 pcs | C22: =IF($A22="","",INDEX(BOM!$G$2:$G$110,MATCH(21,BOM!$O$2:$O$110,0))) -> 1 | D22: =IF($A22="","",INDEX(BOM!$H$2:$H$110,MATCH(21,BOM!$O$2:$O$110,0))) -> 12.99 | E22: =IF($A22="","",INDEX(BOM!$I$2:$I$110,MATCH(21,BOM!$O$2:$O$110,0))) -> 12.99 | F22: =IF($A22="","",IF(INDEX(BOM!$K$2:$K$110,MATCH(21,BOM!$O$2:$O$110,0))="","",HYPERLINK(INDEX(BOM!$K$2:$K$110,MATCH(21,BOM!$O$2:$O$110,0)),"open on amazon.ca"))) -> open on amazon.ca | G22: =IF($A22="","",HYPERLINK(INDEX(BOM!$L$2:$L$110,MATCH(21,BOM!$O$2:$O$110,0)),"search")) -> search
A23: =IF(ISNA(MATCH(22,BOM!$O$2:$O$110,0)),"",22) -> 22 | B23: =IF($A23="","",INDEX(BOM!$B$2:$B$110,MATCH(22,BOM!$O$2:$O$110,0))) -> Cat6 patch cable 7.6 m (25 ft) | C23: =IF($A23="","",INDEX(BOM!$G$2:$G$110,MATCH(22,BOM!$O$2:$O$110,0))) -> 1 | D23: =IF($A23="","",INDEX(BOM!$H$2:$H$110,MATCH(22,BOM!$O$2:$O$110,0))) -> 17.99 | E23: =IF($A23="","",INDEX(BOM!$I$2:$I$110,MATCH(22,BOM!$O$2:$O$110,0))) -> 17.99 | F23: =IF($A23="","",IF(INDEX(BOM!$K$2:$K$110,MATCH(22,BOM!$O$2:$O$110,0))="","",HYPERLINK(INDEX(BOM!$K$2:$K$110,MATCH(22,BOM!$O$2:$O$110,0)),"open on amazon.ca"))) -> open on amazon.ca | G23: =IF($A23="","",HYPERLINK(INDEX(BOM!$L$2:$L$110,MATCH(22,BOM!$O$2:$O$110,0)),"search")) -> search
A24: =IF(ISNA(MATCH(23,BOM!$O$2:$O$110,0)),"",23) -> 23 | B24: =IF($A24="","",INDEX(BOM!$B$2:$B$110,MATCH(23,BOM!$O$2:$O$110,0))) -> 22 AWG stranded hookup wire kit (6 colours) | C24: =IF($A24="","",INDEX(BOM!$G$2:$G$110,MATCH(23,BOM!$O$2:$O$110,0))) -> 1 | D24: =IF($A24="","",INDEX(BOM!$H$2:$H$110,MATCH(23,BOM!$O$2:$O$110,0))) -> 20.49 | E24: =IF($A24="","",INDEX(BOM!$I$2:$I$110,MATCH(23,BOM!$O$2:$O$110,0))) -> 20.49 | F24: =IF($A24="","",IF(INDEX(BOM!$K$2:$K$110,MATCH(23,BOM!$O$2:$O$110,0))="","",HYPERLINK(INDEX(BOM!$K$2:$K$110,MATCH(23,BOM!$O$2:$O$110,0)),"open on amazon.ca"))) -> open on amazon.ca | G24: =IF($A24="","",HYPERLINK(INDEX(BOM!$L$2:$L$110,MATCH(23,BOM!$O$2:$O$110,0)),"search")) -> search
A25: =IF(ISNA(MATCH(24,BOM!$O$2:$O$110,0)),"",24) -> 24 | B25: =IF($A25="","",INDEX(BOM!$B$2:$B$110,MATCH(24,BOM!$O$2:$O$110,0))) -> Mini toggle switch MTS-102, 6 mm (1/4") bushing, 10 pcs | C25: =IF($A25="","",INDEX(BOM!$G$2:$G$110,MATCH(24,BOM!$O$2:$O$110,0))) -> 3 | D25: =IF($A25="","",INDEX(BOM!$H$2:$H$110,MATCH(24,BOM!$O$2:$O$110,0))) -> 8.45 | E25: =IF($A25="","",INDEX(BOM!$I$2:$I$110,MATCH(24,BOM!$O$2:$O$110,0))) -> 25.35 | F25: =IF($A25="","",IF(INDEX(BOM!$K$2:$K$110,MATCH(24,BOM!$O$2:$O$110,0))="","",HYPERLINK(INDEX(BOM!$K$2:$K$110,MATCH(24,BOM!$O$2:$O$110,0)),"open on amazon.ca"))) -> open on amazon.ca | G25: =IF($A25="","",HYPERLINK(INDEX(BOM!$L$2:$L$110,MATCH(24,BOM!$O$2:$O$110,0)),"search")) -> search
A26: =IF(ISNA(MATCH(25,BOM!$O$2:$O$110,0)),"",25) -> 25 | B26: =IF($A26="","",INDEX(BOM!$B$2:$B$110,MATCH(25,BOM!$O$2:$O$110,0))) -> Mini toggle MTS-103 ON-OFF-ON, 6 mm bushing, 10 pcs | C26: =IF($A26="","",INDEX(BOM!$G$2:$G$110,MATCH(25,BOM!$O$2:$O$110,0))) -> 1 | D26: =IF($A26="","",INDEX(BOM!$H$2:$H$110,MATCH(25,BOM!$O$2:$O$110,0))) -> 12.99 | E26: =IF($A26="","",INDEX(BOM!$I$2:$I$110,MATCH(25,BOM!$O$2:$O$110,0))) -> 12.99 | F26: =IF($A26="","",IF(INDEX(BOM!$K$2:$K$110,MATCH(25,BOM!$O$2:$O$110,0))="","",HYPERLINK(INDEX(BOM!$K$2:$K$110,MATCH(25,BOM!$O$2:$O$110,0)),"open on amazon.ca"))) -> open on amazon.ca | G26: =IF($A26="","",HYPERLINK(INDEX(BOM!$L$2:$L$110,MATCH(25,BOM!$O$2:$O$110,0)),"search")) -> search
A27: =IF(ISNA(MATCH(26,BOM!$O$2:$O$110,0)),"",26) -> 26 | B27: =IF($A27="","",INDEX(BOM!$B$2:$B$110,MATCH(26,BOM!$O$2:$O$110,0))) -> 22 mm momentary push buttons (LA38, 5 colours), 6 pcs | C27: =IF($A27="","",INDEX(BOM!$G$2:$G$110,MATCH(26,BOM!$O$2:$O$110,0))) -> 2 | D27: =IF($A27="","",INDEX(BOM!$H$2:$H$110,MATCH(26,BOM!$O$2:$O$110,0))) -> 19.49 | E27: =IF($A27="","",INDEX(BOM!$I$2:$I$110,MATCH(26,BOM!$O$2:$O$110,0))) -> 38.98 | F27: =IF($A27="","",IF(INDEX(BOM!$K$2:$K$110,MATCH(26,BOM!$O$2:$O$110,0))="","",HYPERLINK(INDEX(BOM!$K$2:$K$110,MATCH(26,BOM!$O$2:$O$110,0)),"open on amazon.ca"))) -> open on amazon.ca | G27: =IF($A27="","",HYPERLINK(INDEX(BOM!$L$2:$L$110,MATCH(26,BOM!$O$2:$O$110,0)),"search")) -> search
A28: =IF(ISNA(MATCH(27,BOM!$O$2:$O$110,0)),"",27) -> 27 | B28: =IF($A28="","",INDEX(BOM!$B$2:$B$110,MATCH(27,BOM!$O$2:$O$110,0))) -> 19 mm momentary metal push buttons, 2 pcs | C28: =IF($A28="","",INDEX(BOM!$G$2:$G$110,MATCH(27,BOM!$O$2:$O$110,0))) -> 2 | D28: =IF($A28="","",INDEX(BOM!$H$2:$H$110,MATCH(27,BOM!$O$2:$O$110,0))) -> 15.39 | E28: =IF($A28="","",INDEX(BOM!$I$2:$I$110,MATCH(27,BOM!$O$2:$O$110,0))) -> 30.78 | F28: =IF($A28="","",IF(INDEX(BOM!$K$2:$K$110,MATCH(27,BOM!$O$2:$O$110,0))="","",HYPERLINK(INDEX(BOM!$K$2:$K$110,MATCH(27,BOM!$O$2:$O$110,0)),"open on amazon.ca"))) -> open on amazon.ca | G28: =IF($A28="","",HYPERLINK(INDEX(BOM!$L$2:$L$110,MATCH(27,BOM!$O$2:$O$110,0)),"search")) -> search
A29: =IF(ISNA(MATCH(28,BOM!$O$2:$O$110,0)),"",28) -> 28 | B29: =IF($A29="","",INDEX(BOM!$B$2:$B$110,MATCH(28,BOM!$O$2:$O$110,0))) -> 16 mm momentary metal push buttons, 5 pcs | C29: =IF($A29="","",INDEX(BOM!$G$2:$G$110,MATCH(28,BOM!$O$2:$O$110,0))) -> 2 | D29: =IF($A29="","",INDEX(BOM!$H$2:$H$110,MATCH(28,BOM!$O$2:$O$110,0))) -> 11.99 | E29: =IF($A29="","",INDEX(BOM!$I$2:$I$110,MATCH(28,BOM!$O$2:$O$110,0))) -> 23.98 | F29: =IF($A29="","",IF(INDEX(BOM!$K$2:$K$110,MATCH(28,BOM!$O$2:$O$110,0))="","",HYPERLINK(INDEX(BOM!$K$2:$K$110,MATCH(28,BOM!$O$2:$O$110,0)),"open on amazon.ca"))) -> open on amazon.ca | G29: =IF($A29="","",HYPERLINK(INDEX(BOM!$L$2:$L$110,MATCH(28,BOM!$O$2:$O$110,0)),"search")) -> search
A30: =IF(ISNA(MATCH(29,BOM!$O$2:$O$110,0)),"",29) -> 29 | B30: =IF($A30="","",INDEX(BOM!$B$2:$B$110,MATCH(29,BOM!$O$2:$O$110,0))) -> EC11 rotary encoder with push switch + knob, 10 pcs | C30: =IF($A30="","",INDEX(BOM!$G$2:$G$110,MATCH(29,BOM!$O$2:$O$110,0))) -> 1 | D30: =IF($A30="","",INDEX(BOM!$H$2:$H$110,MATCH(29,BOM!$O$2:$O$110,0))) -> 17.99 | E30: =IF($A30="","",INDEX(BOM!$I$2:$I$110,MATCH(29,BOM!$O$2:$O$110,0))) -> 17.99 | F30: =IF($A30="","",IF(INDEX(BOM!$K$2:$K$110,MATCH(29,BOM!$O$2:$O$110,0))="","",HYPERLINK(INDEX(BOM!$K$2:$K$110,MATCH(29,BOM!$O$2:$O$110,0)),"open on amazon.ca"))) -> open on amazon.ca | G30: =IF($A30="","",HYPERLINK(INDEX(BOM!$L$2:$L$110,MATCH(29,BOM!$O$2:$O$110,0)),"search")) -> search
A31: =IF(ISNA(MATCH(30,BOM!$O$2:$O$110,0)),"",30) -> 30 | B31: =IF($A31="","",INDEX(BOM!$B$2:$B$110,MATCH(30,BOM!$O$2:$O$110,0))) -> B10K linear potentiometer, 16 mm, 6 mm D shaft | C31: =IF($A31="","",INDEX(BOM!$G$2:$G$110,MATCH(30,BOM!$O$2:$O$110,0))) -> 1 | D31: =IF($A31="","",INDEX(BOM!$H$2:$H$110,MATCH(30,BOM!$O$2:$O$110,0))) -> 6.95 | E31: =IF($A31="","",INDEX(BOM!$I$2:$I$110,MATCH(30,BOM!$O$2:$O$110,0))) -> 6.95 | F31: =IF($A31="","",IF(INDEX(BOM!$K$2:$K$110,MATCH(30,BOM!$O$2:$O$110,0))="","",HYPERLINK(INDEX(BOM!$K$2:$K$110,MATCH(30,BOM!$O$2:$O$110,0)),"open on amazon.ca"))) -> open on amazon.ca | G31: =IF($A31="","",HYPERLINK(INDEX(BOM!$L$2:$L$110,MATCH(30,BOM!$O$2:$O$110,0)),"search")) -> search
A32: =IF(ISNA(MATCH(31,BOM!$O$2:$O$110,0)),"",31) -> 31 | B32: =IF($A32="","",INDEX(BOM!$B$2:$B$110,MATCH(31,BOM!$O$2:$O$110,0))) -> KW11 lever micro switch, 10 pcs | C32: =IF($A32="","",INDEX(BOM!$G$2:$G$110,MATCH(31,BOM!$O$2:$O$110,0))) -> 1 | D32: =IF($A32="","",INDEX(BOM!$H$2:$H$110,MATCH(31,BOM!$O$2:$O$110,0))) -> 15.79 | E32: =IF($A32="","",INDEX(BOM!$I$2:$I$110,MATCH(31,BOM!$O$2:$O$110,0))) -> 15.79 | F32: =IF($A32="","",IF(INDEX(BOM!$K$2:$K$110,MATCH(31,BOM!$O$2:$O$110,0))="","",HYPERLINK(INDEX(BOM!$K$2:$K$110,MATCH(31,BOM!$O$2:$O$110,0)),"open on amazon.ca"))) -> open on amazon.ca | G32: =IF($A32="","",HYPERLINK(INDEX(BOM!$L$2:$L$110,MATCH(31,BOM!$O$2:$O$110,0)),"search")) -> search
A33: =IF(ISNA(MATCH(32,BOM!$O$2:$O$110,0)),"",32) -> 32 | B33: =IF($A33="","",INDEX(BOM!$B$2:$B$110,MATCH(32,BOM!$O$2:$O$110,0))) -> 19 mm key switch, 2 position, key removable in OFF | C33: =IF($A33="","",INDEX(BOM!$G$2:$G$110,MATCH(32,BOM!$O$2:$O$110,0))) -> 1 | D33: =IF($A33="","",INDEX(BOM!$H$2:$H$110,MATCH(32,BOM!$O$2:$O$110,0))) -> 26.11 | E33: =IF($A33="","",INDEX(BOM!$I$2:$I$110,MATCH(32,BOM!$O$2:$O$110,0))) -> 26.11 | F33: =IF($A33="","",IF(INDEX(BOM!$K$2:$K$110,MATCH(32,BOM!$O$2:$O$110,0))="","",HYPERLINK(INDEX(BOM!$K$2:$K$110,MATCH(32,BOM!$O$2:$O$110,0)),"open on amazon.ca"))) -> open on amazon.ca | G33: =IF($A33="","",HYPERLINK(INDEX(BOM!$L$2:$L$110,MATCH(32,BOM!$O$2:$O$110,0)),"search")) -> search
A34: =IF(ISNA(MATCH(33,BOM!$O$2:$O$110,0)),"",33) -> 33 | B34: =IF($A34="","",INDEX(BOM!$B$2:$B$110,MATCH(33,BOM!$O$2:$O$110,0))) -> WS2812B LED strip 5 V, 60 LED/m, 5 m, IP30 (no sleeve) | C34: =IF($A34="","",INDEX(BOM!$G$2:$G$110,MATCH(33,BOM!$O$2:$O$110,0))) -> 1 | D34: =IF($A34="","",INDEX(BOM!$H$2:$H$110,MATCH(33,BOM!$O$2:$O$110,0))) -> 25.99 | E34: =IF($A34="","",INDEX(BOM!$I$2:$I$110,MATCH(33,BOM!$O$2:$O$110,0))) -> 25.99 | F34: =IF($A34="","",IF(INDEX(BOM!$K$2:$K$110,MATCH(33,BOM!$O$2:$O$110,0))="","",HYPERLINK(INDEX(BOM!$K$2:$K$110,MATCH(33,BOM!$O$2:$O$110,0)),"open on amazon.ca"))) -> open on amazon.ca | G34: =IF($A34="","",HYPERLINK(INDEX(BOM!$L$2:$L$110,MATCH(33,BOM!$O$2:$O$110,0)),"search")) -> search
A35: =IF(ISNA(MATCH(34,BOM!$O$2:$O$110,0)),"",34) -> 34 | B35: =IF($A35="","",INDEX(BOM!$B$2:$B$110,MATCH(34,BOM!$O$2:$O$110,0))) -> WS2812D-F5 5 mm through-hole addressable RGB LEDs, ~40 pcs | C35: =IF($A35="","",INDEX(BOM!$G$2:$G$110,MATCH(34,BOM!$O$2:$O$110,0))) -> 1 | D35: =IF($A35="","",INDEX(BOM!$H$2:$H$110,MATCH(34,BOM!$O$2:$O$110,0))) -> 20 | E35: =IF($A35="","",INDEX(BOM!$I$2:$I$110,MATCH(34,BOM!$O$2:$O$110,0))) -> 20 | F35: =IF($A35="","",IF(INDEX(BOM!$K$2:$K$110,MATCH(34,BOM!$O$2:$O$110,0))="","",HYPERLINK(INDEX(BOM!$K$2:$K$110,MATCH(34,BOM!$O$2:$O$110,0)),"open on amazon.ca"))) | G35: =IF($A35="","",HYPERLINK(INDEX(BOM!$L$2:$L$110,MATCH(34,BOM!$O$2:$O$110,0)),"search")) -> search
A36: =IF(ISNA(MATCH(35,BOM!$O$2:$O$110,0)),"",35) -> 35 | B36: =IF($A36="","",INDEX(BOM!$B$2:$B$110,MATCH(35,BOM!$O$2:$O$110,0))) -> 5 mm LED holders / bezels, 50 pcs | C36: =IF($A36="","",INDEX(BOM!$G$2:$G$110,MATCH(35,BOM!$O$2:$O$110,0))) -> 1 | D36: =IF($A36="","",INDEX(BOM!$H$2:$H$110,MATCH(35,BOM!$O$2:$O$110,0))) -> 9.19 | E36: =IF($A36="","",INDEX(BOM!$I$2:$I$110,MATCH(35,BOM!$O$2:$O$110,0))) -> 9.19 | F36: =IF($A36="","",IF(INDEX(BOM!$K$2:$K$110,MATCH(35,BOM!$O$2:$O$110,0))="","",HYPERLINK(INDEX(BOM!$K$2:$K$110,MATCH(35,BOM!$O$2:$O$110,0)),"open on amazon.ca"))) -> open on amazon.ca | G36: =IF($A36="","",HYPERLINK(INDEX(BOM!$L$2:$L$110,MATCH(35,BOM!$O$2:$O$110,0)),"search")) -> search
A37: =IF(ISNA(MATCH(36,BOM!$O$2:$O$110,0)),"",36) -> 36 | B37: =IF($A37="","",INDEX(BOM!$B$2:$B$110,MATCH(36,BOM!$O$2:$O$110,0))) -> Mean Well LRS-50-5 (5 V 10 A) power supply | C37: =IF($A37="","",INDEX(BOM!$G$2:$G$110,MATCH(36,BOM!$O$2:$O$110,0))) -> 1 | D37: =IF($A37="","",INDEX(BOM!$H$2:$H$110,MATCH(36,BOM!$O$2:$O$110,0))) -> 31.75 | E37: =IF($A37="","",INDEX(BOM!$I$2:$I$110,MATCH(36,BOM!$O$2:$O$110,0))) -> 31.75 | F37: =IF($A37="","",IF(INDEX(BOM!$K$2:$K$110,MATCH(36,BOM!$O$2:$O$110,0))="","",HYPERLINK(INDEX(BOM!$K$2:$K$110,MATCH(36,BOM!$O$2:$O$110,0)),"open on amazon.ca"))) -> open on amazon.ca | G37: =IF($A37="","",HYPERLINK(INDEX(BOM!$L$2:$L$110,MATCH(36,BOM!$O$2:$O$110,0)),"search")) -> search
A38: =IF(ISNA(MATCH(37,BOM!$O$2:$O$110,0)),"",37) -> 37 | B38: =IF($A38="","",INDEX(BOM!$B$2:$B$110,MATCH(37,BOM!$O$2:$O$110,0))) -> Inline 5x20 mm fuse holders + fast-blow fuse kit | C38: =IF($A38="","",INDEX(BOM!$G$2:$G$110,MATCH(37,BOM!$O$2:$O$110,0))) -> 1 | D38: =IF($A38="","",INDEX(BOM!$H$2:$H$110,MATCH(37,BOM!$O$2:$O$110,0))) -> 14.99 | E38: =IF($A38="","",INDEX(BOM!$I$2:$I$110,MATCH(37,BOM!$O$2:$O$110,0))) -> 14.99 | F38: =IF($A38="","",IF(INDEX(BOM!$K$2:$K$110,MATCH(37,BOM!$O$2:$O$110,0))="","",HYPERLINK(INDEX(BOM!$K$2:$K$110,MATCH(37,BOM!$O$2:$O$110,0)),"open on amazon.ca"))) -> open on amazon.ca | G38: =IF($A38="","",HYPERLINK(INDEX(BOM!$L$2:$L$110,MATCH(37,BOM!$O$2:$O$110,0)),"search")) -> search
A39: =IF(ISNA(MATCH(38,BOM!$O$2:$O$110,0)),"",38) -> 38 | B39: =IF($A39="","",INDEX(BOM!$B$2:$B$110,MATCH(38,BOM!$O$2:$O$110,0))) -> 16 AWG red/black 2-conductor wire, 15 m (50 ft) | C39: =IF($A39="","",INDEX(BOM!$G$2:$G$110,MATCH(38,BOM!$O$2:$O$110,0))) -> 1 | D39: =IF($A39="","",INDEX(BOM!$H$2:$H$110,MATCH(38,BOM!$O$2:$O$110,0))) -> 16.99 | E39: =IF($A39="","",INDEX(BOM!$I$2:$I$110,MATCH(38,BOM!$O$2:$O$110,0))) -> 16.99 | F39: =IF($A39="","",IF(INDEX(BOM!$K$2:$K$110,MATCH(38,BOM!$O$2:$O$110,0))="","",HYPERLINK(INDEX(BOM!$K$2:$K$110,MATCH(38,BOM!$O$2:$O$110,0)),"open on amazon.ca"))) -> open on amazon.ca | G39: =IF($A39="","",HYPERLINK(INDEX(BOM!$L$2:$L$110,MATCH(38,BOM!$O$2:$O$110,0)),"search")) -> search
A40: =IF(ISNA(MATCH(39,BOM!$O$2:$O$110,0)),"",39) -> 39 | B40: =IF($A40="","",INDEX(BOM!$B$2:$B$110,MATCH(39,BOM!$O$2:$O$110,0))) -> 18 AWG red/black silicone wire, 7.6 m (25 ft) | C40: =IF($A40="","",INDEX(BOM!$G$2:$G$110,MATCH(39,BOM!$O$2:$O$110,0))) -> 2 | D40: =IF($A40="","",INDEX(BOM!$H$2:$H$110,MATCH(39,BOM!$O$2:$O$110,0))) -> 19.82 | E40: =IF($A40="","",INDEX(BOM!$I$2:$I$110,MATCH(39,BOM!$O$2:$O$110,0))) -> 39.64 | F40: =IF($A40="","",IF(INDEX(BOM!$K$2:$K$110,MATCH(39,BOM!$O$2:$O$110,0))="","",HYPERLINK(INDEX(BOM!$K$2:$K$110,MATCH(39,BOM!$O$2:$O$110,0)),"open on amazon.ca"))) -> open on amazon.ca | G40: =IF($A40="","",HYPERLINK(INDEX(BOM!$L$2:$L$110,MATCH(39,BOM!$O$2:$O$110,0)),"search")) -> search
A41: =IF(ISNA(MATCH(40,BOM!$O$2:$O$110,0)),"",40) -> 40 | B41: =IF($A41="","",INDEX(BOM!$B$2:$B$110,MATCH(40,BOM!$O$2:$O$110,0))) -> JST-SM 3-pin pigtails (WS2812), 60 pcs | C41: =IF($A41="","",INDEX(BOM!$G$2:$G$110,MATCH(40,BOM!$O$2:$O$110,0))) -> 1 | D41: =IF($A41="","",INDEX(BOM!$H$2:$H$110,MATCH(40,BOM!$O$2:$O$110,0))) -> 18.59 | E41: =IF($A41="","",INDEX(BOM!$I$2:$I$110,MATCH(40,BOM!$O$2:$O$110,0))) -> 18.59 | F41: =IF($A41="","",IF(INDEX(BOM!$K$2:$K$110,MATCH(40,BOM!$O$2:$O$110,0))="","",HYPERLINK(INDEX(BOM!$K$2:$K$110,MATCH(40,BOM!$O$2:$O$110,0)),"open on amazon.ca"))) -> open on amazon.ca | G41: =IF($A41="","",HYPERLINK(INDEX(BOM!$L$2:$L$110,MATCH(40,BOM!$O$2:$O$110,0)),"search")) -> search
A42: =IF(ISNA(MATCH(41,BOM!$O$2:$O$110,0)),"",41) -> 41 | B42: =IF($A42="","",INDEX(BOM!$B$2:$B$110,MATCH(41,BOM!$O$2:$O$110,0))) -> PETG filament 1.75 mm BLACK, 1 kg | C42: =IF($A42="","",INDEX(BOM!$G$2:$G$110,MATCH(41,BOM!$O$2:$O$110,0))) -> 6 | D42: =IF($A42="","",INDEX(BOM!$H$2:$H$110,MATCH(41,BOM!$O$2:$O$110,0))) -> 19.94 | E42: =IF($A42="","",INDEX(BOM!$I$2:$I$110,MATCH(41,BOM!$O$2:$O$110,0))) -> 119.64 | F42: =IF($A42="","",IF(INDEX(BOM!$K$2:$K$110,MATCH(41,BOM!$O$2:$O$110,0))="","",HYPERLINK(INDEX(BOM!$K$2:$K$110,MATCH(41,BOM!$O$2:$O$110,0)),"open on amazon.ca"))) -> open on amazon.ca | G42: =IF($A42="","",HYPERLINK(INDEX(BOM!$L$2:$L$110,MATCH(41,BOM!$O$2:$O$110,0)),"search")) -> search
A43: =IF(ISNA(MATCH(42,BOM!$O$2:$O$110,0)),"",42) -> 42 | B43: =IF($A43="","",INDEX(BOM!$B$2:$B$110,MATCH(42,BOM!$O$2:$O$110,0))) -> PETG filament 1.75 mm WHITE, 1 kg | C43: =IF($A43="","",INDEX(BOM!$G$2:$G$110,MATCH(42,BOM!$O$2:$O$110,0))) -> 1 | D43: =IF($A43="","",INDEX(BOM!$H$2:$H$110,MATCH(42,BOM!$O$2:$O$110,0))) -> 20.89 | E43: =IF($A43="","",INDEX(BOM!$I$2:$I$110,MATCH(42,BOM!$O$2:$O$110,0))) -> 20.89 | F43: =IF($A43="","",IF(INDEX(BOM!$K$2:$K$110,MATCH(42,BOM!$O$2:$O$110,0))="","",HYPERLINK(INDEX(BOM!$K$2:$K$110,MATCH(42,BOM!$O$2:$O$110,0)),"open on amazon.ca"))) -> open on amazon.ca | G43: =IF($A43="","",HYPERLINK(INDEX(BOM!$L$2:$L$110,MATCH(42,BOM!$O$2:$O$110,0)),"search")) -> search
A44: =IF(ISNA(MATCH(43,BOM!$O$2:$O$110,0)),"",43) -> 43 | B44: =IF($A44="","",INDEX(BOM!$B$2:$B$110,MATCH(43,BOM!$O$2:$O$110,0))) -> Brass heat-set inserts kit M2-M6 (360 pcs) | C44: =IF($A44="","",INDEX(BOM!$G$2:$G$110,MATCH(43,BOM!$O$2:$O$110,0))) -> 1 | D44: =IF($A44="","",INDEX(BOM!$H$2:$H$110,MATCH(43,BOM!$O$2:$O$110,0))) -> 26.99 | E44: =IF($A44="","",INDEX(BOM!$I$2:$I$110,MATCH(43,BOM!$O$2:$O$110,0))) -> 26.99 | F44: =IF($A44="","",IF(INDEX(BOM!$K$2:$K$110,MATCH(43,BOM!$O$2:$O$110,0))="","",HYPERLINK(INDEX(BOM!$K$2:$K$110,MATCH(43,BOM!$O$2:$O$110,0)),"open on amazon.ca"))) -> open on amazon.ca | G44: =IF($A44="","",HYPERLINK(INDEX(BOM!$L$2:$L$110,MATCH(43,BOM!$O$2:$O$110,0)),"search")) -> search
A45: =IF(ISNA(MATCH(44,BOM!$O$2:$O$110,0)),"",44) -> 44 | B45: =IF($A45="","",INDEX(BOM!$B$2:$B$110,MATCH(44,BOM!$O$2:$O$110,0))) -> Metric socket screw assortment M2-M5 (1760 pcs) | C45: =IF($A45="","",INDEX(BOM!$G$2:$G$110,MATCH(44,BOM!$O$2:$O$110,0))) -> 1 | D45: =IF($A45="","",INDEX(BOM!$H$2:$H$110,MATCH(44,BOM!$O$2:$O$110,0))) -> 28.99 | E45: =IF($A45="","",INDEX(BOM!$I$2:$I$110,MATCH(44,BOM!$O$2:$O$110,0))) -> 28.99 | F45: =IF($A45="","",IF(INDEX(BOM!$K$2:$K$110,MATCH(44,BOM!$O$2:$O$110,0))="","",HYPERLINK(INDEX(BOM!$K$2:$K$110,MATCH(44,BOM!$O$2:$O$110,0)),"open on amazon.ca"))) -> open on amazon.ca | G45: =IF($A45="","",HYPERLINK(INDEX(BOM!$L$2:$L$110,MATCH(44,BOM!$O$2:$O$110,0)),"search")) -> search
A46: =IF(ISNA(MATCH(45,BOM!$O$2:$O$110,0)),"",45) -> 45 | B46: =IF($A46="","",INDEX(BOM!$B$2:$B$110,MATCH(45,BOM!$O$2:$O$110,0))) -> Self-tapping screw assortment M2 / M2.5 / M3 | C46: =IF($A46="","",INDEX(BOM!$G$2:$G$110,MATCH(45,BOM!$O$2:$O$110,0))) -> 1 | D46: =IF($A46="","",INDEX(BOM!$H$2:$H$110,MATCH(45,BOM!$O$2:$O$110,0))) -> 16.99 | E46: =IF($A46="","",INDEX(BOM!$I$2:$I$110,MATCH(45,BOM!$O$2:$O$110,0))) -> 16.99 | F46: =IF($A46="","",IF(INDEX(BOM!$K$2:$K$110,MATCH(45,BOM!$O$2:$O$110,0))="","",HYPERLINK(INDEX(BOM!$K$2:$K$110,MATCH(45,BOM!$O$2:$O$110,0)),"open on amazon.ca"))) -> open on amazon.ca | G46: =IF($A46="","",HYPERLINK(INDEX(BOM!$L$2:$L$110,MATCH(45,BOM!$O$2:$O$110,0)),"search")) -> search
A47: =IF(ISNA(MATCH(46,BOM!$O$2:$O$110,0)),"",46) -> 46 | B47: =IF($A47="","",INDEX(BOM!$B$2:$B$110,MATCH(46,BOM!$O$2:$O$110,0))) -> M5 four-prong T-nuts, M5 x 8 mm, 200 pcs | C47: =IF($A47="","",INDEX(BOM!$G$2:$G$110,MATCH(46,BOM!$O$2:$O$110,0))) -> 1 | D47: =IF($A47="","",INDEX(BOM!$H$2:$H$110,MATCH(46,BOM!$O$2:$O$110,0))) -> 44.38 | E47: =IF($A47="","",INDEX(BOM!$I$2:$I$110,MATCH(46,BOM!$O$2:$O$110,0))) -> 44.38 | F47: =IF($A47="","",IF(INDEX(BOM!$K$2:$K$110,MATCH(46,BOM!$O$2:$O$110,0))="","",HYPERLINK(INDEX(BOM!$K$2:$K$110,MATCH(46,BOM!$O$2:$O$110,0)),"open on amazon.ca"))) -> open on amazon.ca | G47: =IF($A47="","",HYPERLINK(INDEX(BOM!$L$2:$L$110,MATCH(46,BOM!$O$2:$O$110,0)),"search")) -> search
A48: =IF(ISNA(MATCH(47,BOM!$O$2:$O$110,0)),"",47) -> 47 | B48: =IF($A48="","",INDEX(BOM!$B$2:$B$110,MATCH(47,BOM!$O$2:$O$110,0))) -> M5 x 20 flanged button-head socket screws, black, 50 pcs | C48: =IF($A48="","",INDEX(BOM!$G$2:$G$110,MATCH(47,BOM!$O$2:$O$110,0))) -> 4 | D48: =IF($A48="","",INDEX(BOM!$H$2:$H$110,MATCH(47,BOM!$O$2:$O$110,0))) -> 14.99 | E48: =IF($A48="","",INDEX(BOM!$I$2:$I$110,MATCH(47,BOM!$O$2:$O$110,0))) -> 59.96 | F48: =IF($A48="","",IF(INDEX(BOM!$K$2:$K$110,MATCH(47,BOM!$O$2:$O$110,0))="","",HYPERLINK(INDEX(BOM!$K$2:$K$110,MATCH(47,BOM!$O$2:$O$110,0)),"open on amazon.ca"))) -> open on amazon.ca | G48: =IF($A48="","",HYPERLINK(INDEX(BOM!$L$2:$L$110,MATCH(47,BOM!$O$2:$O$110,0)),"search")) -> search
A49: =IF(ISNA(MATCH(48,BOM!$O$2:$O$110,0)),"",48) -> 48 | B49: =IF($A49="","",INDEX(BOM!$B$2:$B$110,MATCH(48,BOM!$O$2:$O$110,0))) -> M5 flat washers, 200 pcs | C49: =IF($A49="","",INDEX(BOM!$G$2:$G$110,MATCH(48,BOM!$O$2:$O$110,0))) -> 1 | D49: =IF($A49="","",INDEX(BOM!$H$2:$H$110,MATCH(48,BOM!$O$2:$O$110,0))) -> 9.99 | E49: =IF($A49="","",INDEX(BOM!$I$2:$I$110,MATCH(48,BOM!$O$2:$O$110,0))) -> 9.99 | F49: =IF($A49="","",IF(INDEX(BOM!$K$2:$K$110,MATCH(48,BOM!$O$2:$O$110,0))="","",HYPERLINK(INDEX(BOM!$K$2:$K$110,MATCH(48,BOM!$O$2:$O$110,0)),"open on amazon.ca"))) -> open on amazon.ca | G49: =IF($A49="","",HYPERLINK(INDEX(BOM!$L$2:$L$110,MATCH(48,BOM!$O$2:$O$110,0)),"search")) -> search
A50: =IF(ISNA(MATCH(49,BOM!$O$2:$O$110,0)),"",49) -> 49 | B50: =IF($A50="","",INDEX(BOM!$B$2:$B$110,MATCH(49,BOM!$O$2:$O$110,0))) -> 2 mm stainless safety cable with loops, 300 mm (12"), 5 pcs | C50: =IF($A50="","",INDEX(BOM!$G$2:$G$110,MATCH(49,BOM!$O$2:$O$110,0))) -> 1 | D50: =IF($A50="","",INDEX(BOM!$H$2:$H$110,MATCH(49,BOM!$O$2:$O$110,0))) -> 9.99 | E50: =IF($A50="","",INDEX(BOM!$I$2:$I$110,MATCH(49,BOM!$O$2:$O$110,0))) -> 9.99 | F50: =IF($A50="","",IF(INDEX(BOM!$K$2:$K$110,MATCH(49,BOM!$O$2:$O$110,0))="","",HYPERLINK(INDEX(BOM!$K$2:$K$110,MATCH(49,BOM!$O$2:$O$110,0)),"open on amazon.ca"))) -> open on amazon.ca | G50: =IF($A50="","",HYPERLINK(INDEX(BOM!$L$2:$L$110,MATCH(49,BOM!$O$2:$O$110,0)),"search")) -> search
A51: =IF(ISNA(MATCH(50,BOM!$O$2:$O$110,0)),"",50) -> 50 | B51: =IF($A51="","",INDEX(BOM!$B$2:$B$110,MATCH(50,BOM!$O$2:$O$110,0))) -> 25 mm linear shaft, 1000 mm, 2 pcs | C51: =IF($A51="","",INDEX(BOM!$G$2:$G$110,MATCH(50,BOM!$O$2:$O$110,0))) -> 1 | D51: =IF($A51="","",INDEX(BOM!$H$2:$H$110,MATCH(50,BOM!$O$2:$O$110,0))) -> 46.99 | E51: =IF($A51="","",INDEX(BOM!$I$2:$I$110,MATCH(50,BOM!$O$2:$O$110,0))) -> 46.99 | F51: =IF($A51="","",IF(INDEX(BOM!$K$2:$K$110,MATCH(50,BOM!$O$2:$O$110,0))="","",HYPERLINK(INDEX(BOM!$K$2:$K$110,MATCH(50,BOM!$O$2:$O$110,0)),"open on amazon.ca"))) -> open on amazon.ca | G51: =IF($A51="","",HYPERLINK(INDEX(BOM!$L$2:$L$110,MATCH(50,BOM!$O$2:$O$110,0)),"search")) -> search
A52: =IF(ISNA(MATCH(51,BOM!$O$2:$O$110,0)),"",51) -> 51 | B52: =IF($A52="","",INDEX(BOM!$B$2:$B$110,MATCH(51,BOM!$O$2:$O$110,0))) -> SHF25 shaft supports, 4 pcs | C52: =IF($A52="","",INDEX(BOM!$G$2:$G$110,MATCH(51,BOM!$O$2:$O$110,0))) -> 2 | D52: =IF($A52="","",INDEX(BOM!$H$2:$H$110,MATCH(51,BOM!$O$2:$O$110,0))) -> 13.49 | E52: =IF($A52="","",INDEX(BOM!$I$2:$I$110,MATCH(51,BOM!$O$2:$O$110,0))) -> 26.98 | F52: =IF($A52="","",IF(INDEX(BOM!$K$2:$K$110,MATCH(51,BOM!$O$2:$O$110,0))="","",HYPERLINK(INDEX(BOM!$K$2:$K$110,MATCH(51,BOM!$O$2:$O$110,0)),"open on amazon.ca"))) -> open on amazon.ca | G52: =IF($A52="","",HYPERLINK(INDEX(BOM!$L$2:$L$110,MATCH(51,BOM!$O$2:$O$110,0)),"search")) -> search
A53: =IF(ISNA(MATCH(52,BOM!$O$2:$O$110,0)),"",52) -> 52 | B53: =IF($A53="","",INDEX(BOM!$B$2:$B$110,MATCH(52,BOM!$O$2:$O$110,0))) -> UCP205 pillow block bearings 25 mm, 2-pack | C53: =IF($A53="","",INDEX(BOM!$G$2:$G$110,MATCH(52,BOM!$O$2:$O$110,0))) -> 1 | D53: =IF($A53="","",INDEX(BOM!$H$2:$H$110,MATCH(52,BOM!$O$2:$O$110,0))) -> 37.75 | E53: =IF($A53="","",INDEX(BOM!$I$2:$I$110,MATCH(52,BOM!$O$2:$O$110,0))) -> 37.75 | F53: =IF($A53="","",IF(INDEX(BOM!$K$2:$K$110,MATCH(52,BOM!$O$2:$O$110,0))="","",HYPERLINK(INDEX(BOM!$K$2:$K$110,MATCH(52,BOM!$O$2:$O$110,0)),"open on amazon.ca"))) -> open on amazon.ca | G53: =IF($A53="","",HYPERLINK(INDEX(BOM!$L$2:$L$110,MATCH(52,BOM!$O$2:$O$110,0)),"search")) -> search
A54: =IF(ISNA(MATCH(53,BOM!$O$2:$O$110,0)),"",53) -> 53 | B54: =IF($A54="","",INDEX(BOM!$B$2:$B$110,MATCH(53,BOM!$O$2:$O$110,0))) -> UCF205 4-bolt flange bearing 25 mm | C54: =IF($A54="","",INDEX(BOM!$G$2:$G$110,MATCH(53,BOM!$O$2:$O$110,0))) -> 2 | D54: =IF($A54="","",INDEX(BOM!$H$2:$H$110,MATCH(53,BOM!$O$2:$O$110,0))) -> 20.79 | E54: =IF($A54="","",INDEX(BOM!$I$2:$I$110,MATCH(53,BOM!$O$2:$O$110,0))) -> 41.58 | F54: =IF($A54="","",IF(INDEX(BOM!$K$2:$K$110,MATCH(53,BOM!$O$2:$O$110,0))="","",HYPERLINK(INDEX(BOM!$K$2:$K$110,MATCH(53,BOM!$O$2:$O$110,0)),"open on amazon.ca"))) -> open on amazon.ca | G54: =IF($A54="","",HYPERLINK(INDEX(BOM!$L$2:$L$110,MATCH(53,BOM!$O$2:$O$110,0)),"search")) -> search
A55: =IF(ISNA(MATCH(54,BOM!$O$2:$O$110,0)),"",54) -> 54 | B55: =IF($A55="","",INDEX(BOM!$B$2:$B$110,MATCH(54,BOM!$O$2:$O$110,0))) -> 25 mm steel double-split shaft collars, 2 pcs | C55: =IF($A55="","",INDEX(BOM!$G$2:$G$110,MATCH(54,BOM!$O$2:$O$110,0))) -> 2 | D55: =IF($A55="","",INDEX(BOM!$H$2:$H$110,MATCH(54,BOM!$O$2:$O$110,0))) -> 17.49 | E55: =IF($A55="","",INDEX(BOM!$I$2:$I$110,MATCH(54,BOM!$O$2:$O$110,0))) -> 34.98 | F55: =IF($A55="","",IF(INDEX(BOM!$K$2:$K$110,MATCH(54,BOM!$O$2:$O$110,0))="","",HYPERLINK(INDEX(BOM!$K$2:$K$110,MATCH(54,BOM!$O$2:$O$110,0)),"open on amazon.ca"))) -> open on amazon.ca | G55: =IF($A55="","",HYPERLINK(INDEX(BOM!$L$2:$L$110,MATCH(54,BOM!$O$2:$O$110,0)),"search")) -> search
A56: =IF(ISNA(MATCH(55,BOM!$O$2:$O$110,0)),"",55) -> 55 | B56: =IF($A56="","",INDEX(BOM!$B$2:$B$110,MATCH(55,BOM!$O$2:$O$110,0))) -> Cradle linear actuator 12 V, 10" (254 mm) stroke, 1500 N (330 lbf), self-locking | C56: =IF($A56="","",INDEX(BOM!$G$2:$G$110,MATCH(55,BOM!$O$2:$O$110,0))) -> 2 | D56: =IF($A56="","",INDEX(BOM!$H$2:$H$110,MATCH(55,BOM!$O$2:$O$110,0))) -> 62.33 | E56: =IF($A56="","",INDEX(BOM!$I$2:$I$110,MATCH(55,BOM!$O$2:$O$110,0))) -> 124.66 | F56: =IF($A56="","",IF(INDEX(BOM!$K$2:$K$110,MATCH(55,BOM!$O$2:$O$110,0))="","",HYPERLINK(INDEX(BOM!$K$2:$K$110,MATCH(55,BOM!$O$2:$O$110,0)),"open on amazon.ca"))) -> open on amazon.ca | G56: =IF($A56="","",HYPERLINK(INDEX(BOM!$L$2:$L$110,MATCH(55,BOM!$O$2:$O$110,0)),"search")) -> search
A57: =IF(ISNA(MATCH(56,BOM!$O$2:$O$110,0)),"",56) -> 56 | B57: =IF($A57="","",INDEX(BOM!$B$2:$B$110,MATCH(56,BOM!$O$2:$O$110,0))) -> Pod linear actuator 12 V, 12" (300 mm) stroke, 1500 N (330 lbf), self-locking - ONE (left casing) | C57: =IF($A57="","",INDEX(BOM!$G$2:$G$110,MATCH(56,BOM!$O$2:$O$110,0))) -> 1 | D57: =IF($A57="","",INDEX(BOM!$H$2:$H$110,MATCH(56,BOM!$O$2:$O$110,0))) -> 67.82 | E57: =IF($A57="","",INDEX(BOM!$I$2:$I$110,MATCH(56,BOM!$O$2:$O$110,0))) -> 67.82 | F57: =IF($A57="","",IF(INDEX(BOM!$K$2:$K$110,MATCH(56,BOM!$O$2:$O$110,0))="","",HYPERLINK(INDEX(BOM!$K$2:$K$110,MATCH(56,BOM!$O$2:$O$110,0)),"open on amazon.ca"))) -> open on amazon.ca | G57: =IF($A57="","",HYPERLINK(INDEX(BOM!$L$2:$L$110,MATCH(56,BOM!$O$2:$O$110,0)),"search")) -> search
A58: =IF(ISNA(MATCH(57,BOM!$O$2:$O$110,0)),"",57) -> 57 | B58: =IF($A58="","",INDEX(BOM!$B$2:$B$110,MATCH(57,BOM!$O$2:$O$110,0))) -> Gas struts (pair), ~250 mm extended, ~1050 N (235 lbf) each, M8 eye ends | C58: =IF($A58="","",INDEX(BOM!$G$2:$G$110,MATCH(57,BOM!$O$2:$O$110,0))) -> 1 | D58: =IF($A58="","",INDEX(BOM!$H$2:$H$110,MATCH(57,BOM!$O$2:$O$110,0))) -> 60 | E58: =IF($A58="","",INDEX(BOM!$I$2:$I$110,MATCH(57,BOM!$O$2:$O$110,0))) -> 60 | F58: =IF($A58="","",IF(INDEX(BOM!$K$2:$K$110,MATCH(57,BOM!$O$2:$O$110,0))="","",HYPERLINK(INDEX(BOM!$K$2:$K$110,MATCH(57,BOM!$O$2:$O$110,0)),"open on amazon.ca"))) | G58: =IF($A58="","",HYPERLINK(INDEX(BOM!$L$2:$L$110,MATCH(57,BOM!$O$2:$O$110,0)),"search")) -> search
A59: =IF(ISNA(MATCH(58,BOM!$O$2:$O$110,0)),"",58) -> 58 | B59: =IF($A59="","",INDEX(BOM!$B$2:$B$110,MATCH(58,BOM!$O$2:$O$110,0))) -> Spring-loaded steel pawl (barrel bolt / gate latch) | C59: =IF($A59="","",INDEX(BOM!$G$2:$G$110,MATCH(58,BOM!$O$2:$O$110,0))) -> 2 | D59: =IF($A59="","",INDEX(BOM!$H$2:$H$110,MATCH(58,BOM!$O$2:$O$110,0))) -> 16.99 | E59: =IF($A59="","",INDEX(BOM!$I$2:$I$110,MATCH(58,BOM!$O$2:$O$110,0))) -> 33.98 | F59: =IF($A59="","",IF(INDEX(BOM!$K$2:$K$110,MATCH(58,BOM!$O$2:$O$110,0))="","",HYPERLINK(INDEX(BOM!$K$2:$K$110,MATCH(58,BOM!$O$2:$O$110,0)),"open on amazon.ca"))) -> open on amazon.ca | G59: =IF($A59="","",HYPERLINK(INDEX(BOM!$L$2:$L$110,MATCH(58,BOM!$O$2:$O$110,0)),"search")) -> search
A60: =IF(ISNA(MATCH(59,BOM!$O$2:$O$110,0)),"",59) -> 59 | B60: =IF($A60="","",INDEX(BOM!$B$2:$B$110,MATCH(59,BOM!$O$2:$O$110,0))) -> Bowden cables + levers (bike brake lever set) | C60: =IF($A60="","",INDEX(BOM!$G$2:$G$110,MATCH(59,BOM!$O$2:$O$110,0))) -> 1 | D60: =IF($A60="","",INDEX(BOM!$H$2:$H$110,MATCH(59,BOM!$O$2:$O$110,0))) -> 23.99 | E60: =IF($A60="","",INDEX(BOM!$I$2:$I$110,MATCH(59,BOM!$O$2:$O$110,0))) -> 23.99 | F60: =IF($A60="","",IF(INDEX(BOM!$K$2:$K$110,MATCH(59,BOM!$O$2:$O$110,0))="","",HYPERLINK(INDEX(BOM!$K$2:$K$110,MATCH(59,BOM!$O$2:$O$110,0)),"open on amazon.ca"))) -> open on amazon.ca | G60: =IF($A60="","",HYPERLINK(INDEX(BOM!$L$2:$L$110,MATCH(59,BOM!$O$2:$O$110,0)),"search")) -> search
A61: =IF(ISNA(MATCH(60,BOM!$O$2:$O$110,0)),"",60) -> 60 | B61: =IF($A61="","",INDEX(BOM!$B$2:$B$110,MATCH(60,BOM!$O$2:$O$110,0))) -> Rubber bumper / stop pads with screws (assorted) | C61: =IF($A61="","",INDEX(BOM!$G$2:$G$110,MATCH(60,BOM!$O$2:$O$110,0))) -> 1 | D61: =IF($A61="","",INDEX(BOM!$H$2:$H$110,MATCH(60,BOM!$O$2:$O$110,0))) -> 17.99 | E61: =IF($A61="","",INDEX(BOM!$I$2:$I$110,MATCH(60,BOM!$O$2:$O$110,0))) -> 17.99 | F61: =IF($A61="","",IF(INDEX(BOM!$K$2:$K$110,MATCH(60,BOM!$O$2:$O$110,0))="","",HYPERLINK(INDEX(BOM!$K$2:$K$110,MATCH(60,BOM!$O$2:$O$110,0)),"open on amazon.ca"))) -> open on amazon.ca | G61: =IF($A61="","",HYPERLINK(INDEX(BOM!$L$2:$L$110,MATCH(60,BOM!$O$2:$O$110,0)),"search")) -> search
A62: =IF(ISNA(MATCH(61,BOM!$O$2:$O$110,0)),"",61) -> 61 | B62: =IF($A62="","",INDEX(BOM!$B$2:$B$110,MATCH(61,BOM!$O$2:$O$110,0))) -> 12 V 20 A (240 W) enclosed power supply | C62: =IF($A62="","",INDEX(BOM!$G$2:$G$110,MATCH(61,BOM!$O$2:$O$110,0))) -> 1 | D62: =IF($A62="","",INDEX(BOM!$H$2:$H$110,MATCH(61,BOM!$O$2:$O$110,0))) -> 33.99 | E62: =IF($A62="","",INDEX(BOM!$I$2:$I$110,MATCH(61,BOM!$O$2:$O$110,0))) -> 33.99 | F62: =IF($A62="","",IF(INDEX(BOM!$K$2:$K$110,MATCH(61,BOM!$O$2:$O$110,0))="","",HYPERLINK(INDEX(BOM!$K$2:$K$110,MATCH(61,BOM!$O$2:$O$110,0)),"open on amazon.ca"))) -> open on amazon.ca | G62: =IF($A62="","",HYPERLINK(INDEX(BOM!$L$2:$L$110,MATCH(61,BOM!$O$2:$O$110,0)),"search")) -> search
A63: =IF(ISNA(MATCH(62,BOM!$O$2:$O$110,0)),"",62) -> 62 | B63: =IF($A63="","",INDEX(BOM!$B$2:$B$110,MATCH(62,BOM!$O$2:$O$110,0))) -> Inline ATC fuse holder 12 AWG with 20/30/40 A fuses | C63: =IF($A63="","",INDEX(BOM!$G$2:$G$110,MATCH(62,BOM!$O$2:$O$110,0))) -> 1 | D63: =IF($A63="","",INDEX(BOM!$H$2:$H$110,MATCH(62,BOM!$O$2:$O$110,0))) -> 18.99 | E63: =IF($A63="","",INDEX(BOM!$I$2:$I$110,MATCH(62,BOM!$O$2:$O$110,0))) -> 18.99 | F63: =IF($A63="","",IF(INDEX(BOM!$K$2:$K$110,MATCH(62,BOM!$O$2:$O$110,0))="","",HYPERLINK(INDEX(BOM!$K$2:$K$110,MATCH(62,BOM!$O$2:$O$110,0)),"open on amazon.ca"))) -> open on amazon.ca | G63: =IF($A63="","",HYPERLINK(INDEX(BOM!$L$2:$L$110,MATCH(62,BOM!$O$2:$O$110,0)),"search")) -> search
A64: =IF(ISNA(MATCH(63,BOM!$O$2:$O$110,0)),"",63) -> 63 | B64: =IF($A64="","",INDEX(BOM!$B$2:$B$110,MATCH(63,BOM!$O$2:$O$110,0))) -> 19 mm key switch, 2 position (MOTION key) - drives a 30 A relay | C64: =IF($A64="","",INDEX(BOM!$G$2:$G$110,MATCH(63,BOM!$O$2:$O$110,0))) -> 1 | D64: =IF($A64="","",INDEX(BOM!$H$2:$H$110,MATCH(63,BOM!$O$2:$O$110,0))) -> 26.11 | E64: =IF($A64="","",INDEX(BOM!$I$2:$I$110,MATCH(63,BOM!$O$2:$O$110,0))) -> 26.11 | F64: =IF($A64="","",IF(INDEX(BOM!$K$2:$K$110,MATCH(63,BOM!$O$2:$O$110,0))="","",HYPERLINK(INDEX(BOM!$K$2:$K$110,MATCH(63,BOM!$O$2:$O$110,0)),"open on amazon.ca"))) -> open on amazon.ca | G64: =IF($A64="","",HYPERLINK(INDEX(BOM!$L$2:$L$110,MATCH(63,BOM!$O$2:$O$110,0)),"search")) -> search
A65: =IF(ISNA(MATCH(64,BOM!$O$2:$O$110,0)),"",64) -> 64 | B65: =IF($A65="","",INDEX(BOM!$B$2:$B$110,MATCH(64,BOM!$O$2:$O$110,0))) -> 22 mm mushroom E-stop, NC, latching, twist release | C65: =IF($A65="","",INDEX(BOM!$G$2:$G$110,MATCH(64,BOM!$O$2:$O$110,0))) -> 1 | D65: =IF($A65="","",INDEX(BOM!$H$2:$H$110,MATCH(64,BOM!$O$2:$O$110,0))) -> 16.24 | E65: =IF($A65="","",INDEX(BOM!$I$2:$I$110,MATCH(64,BOM!$O$2:$O$110,0))) -> 16.24 | F65: =IF($A65="","",IF(INDEX(BOM!$K$2:$K$110,MATCH(64,BOM!$O$2:$O$110,0))="","",HYPERLINK(INDEX(BOM!$K$2:$K$110,MATCH(64,BOM!$O$2:$O$110,0)),"open on amazon.ca"))) -> open on amazon.ca | G65: =IF($A65="","",HYPERLINK(INDEX(BOM!$L$2:$L$110,MATCH(64,BOM!$O$2:$O$110,0)),"search")) -> search
A66: =IF(ISNA(MATCH(65,BOM!$O$2:$O$110,0)),"",65) -> 65 | B66: =IF($A66="","",INDEX(BOM!$B$2:$B$110,MATCH(65,BOM!$O$2:$O$110,0))) -> DPDT (ON)-OFF-(ON) momentary toggle, 12 mm bushing | C66: =IF($A66="","",INDEX(BOM!$G$2:$G$110,MATCH(65,BOM!$O$2:$O$110,0))) -> 1 | D66: =IF($A66="","",INDEX(BOM!$H$2:$H$110,MATCH(65,BOM!$O$2:$O$110,0))) -> 13.98 | E66: =IF($A66="","",INDEX(BOM!$I$2:$I$110,MATCH(65,BOM!$O$2:$O$110,0))) -> 13.98 | F66: =IF($A66="","",IF(INDEX(BOM!$K$2:$K$110,MATCH(65,BOM!$O$2:$O$110,0))="","",HYPERLINK(INDEX(BOM!$K$2:$K$110,MATCH(65,BOM!$O$2:$O$110,0)),"open on amazon.ca"))) -> open on amazon.ca | G66: =IF($A66="","",HYPERLINK(INDEX(BOM!$L$2:$L$110,MATCH(65,BOM!$O$2:$O$110,0)),"search")) -> search
A67: =IF(ISNA(MATCH(66,BOM!$O$2:$O$110,0)),"",66) -> 66 | B67: =IF($A67="","",INDEX(BOM!$B$2:$B$110,MATCH(66,BOM!$O$2:$O$110,0))) -> 12 V 30/40 A automotive relays SPDT 5-pin, 10 pcs | C67: =IF($A67="","",INDEX(BOM!$G$2:$G$110,MATCH(66,BOM!$O$2:$O$110,0))) -> 1 | D67: =IF($A67="","",INDEX(BOM!$H$2:$H$110,MATCH(66,BOM!$O$2:$O$110,0))) -> 22.99 | E67: =IF($A67="","",INDEX(BOM!$I$2:$I$110,MATCH(66,BOM!$O$2:$O$110,0))) -> 22.99 | F67: =IF($A67="","",IF(INDEX(BOM!$K$2:$K$110,MATCH(66,BOM!$O$2:$O$110,0))="","",HYPERLINK(INDEX(BOM!$K$2:$K$110,MATCH(66,BOM!$O$2:$O$110,0)),"open on amazon.ca"))) -> open on amazon.ca | G67: =IF($A67="","",HYPERLINK(INDEX(BOM!$L$2:$L$110,MATCH(66,BOM!$O$2:$O$110,0)),"search")) -> search
A68: =IF(ISNA(MATCH(67,BOM!$O$2:$O$110,0)),"",67) -> 67 | B68: =IF($A68="","",INDEX(BOM!$B$2:$B$110,MATCH(67,BOM!$O$2:$O$110,0))) -> V-15 roller-lever micro switches 15 A, 10 pcs | C68: =IF($A68="","",INDEX(BOM!$G$2:$G$110,MATCH(67,BOM!$O$2:$O$110,0))) -> 2 | D68: =IF($A68="","",INDEX(BOM!$H$2:$H$110,MATCH(67,BOM!$O$2:$O$110,0))) -> 16.69 | E68: =IF($A68="","",INDEX(BOM!$I$2:$I$110,MATCH(67,BOM!$O$2:$O$110,0))) -> 33.38 | F68: =IF($A68="","",IF(INDEX(BOM!$K$2:$K$110,MATCH(67,BOM!$O$2:$O$110,0))="","",HYPERLINK(INDEX(BOM!$K$2:$K$110,MATCH(67,BOM!$O$2:$O$110,0)),"open on amazon.ca"))) -> open on amazon.ca | G68: =IF($A68="","",HYPERLINK(INDEX(BOM!$L$2:$L$110,MATCH(67,BOM!$O$2:$O$110,0)),"search")) -> search
A69: =IF(ISNA(MATCH(68,BOM!$O$2:$O$110,0)),"",68) -> 68 | B69: =IF($A69="","",INDEX(BOM!$B$2:$B$110,MATCH(68,BOM!$O$2:$O$110,0))) -> 6A10 rectifier diodes (6 A, 1000 V), 20 pcs | C69: =IF($A69="","",INDEX(BOM!$G$2:$G$110,MATCH(68,BOM!$O$2:$O$110,0))) -> 1 | D69: =IF($A69="","",INDEX(BOM!$H$2:$H$110,MATCH(68,BOM!$O$2:$O$110,0))) -> 8.99 | E69: =IF($A69="","",INDEX(BOM!$I$2:$I$110,MATCH(68,BOM!$O$2:$O$110,0))) -> 8.99 | F69: =IF($A69="","",IF(INDEX(BOM!$K$2:$K$110,MATCH(68,BOM!$O$2:$O$110,0))="","",HYPERLINK(INDEX(BOM!$K$2:$K$110,MATCH(68,BOM!$O$2:$O$110,0)),"open on amazon.ca"))) -> open on amazon.ca | G69: =IF($A69="","",HYPERLINK(INDEX(BOM!$L$2:$L$110,MATCH(68,BOM!$O$2:$O$110,0)),"search")) -> search
A70: =IF(ISNA(MATCH(69,BOM!$O$2:$O$110,0)),"",69) -> 69 | B70: =IF($A70="","",INDEX(BOM!$B$2:$B$110,MATCH(69,BOM!$O$2:$O$110,0))) -> 14 AWG red/black 2-conductor wire, 15 m (50 ft) | C70: =IF($A70="","",INDEX(BOM!$G$2:$G$110,MATCH(69,BOM!$O$2:$O$110,0))) -> 2 | D70: =IF($A70="","",INDEX(BOM!$H$2:$H$110,MATCH(69,BOM!$O$2:$O$110,0))) -> 17.09 | E70: =IF($A70="","",INDEX(BOM!$I$2:$I$110,MATCH(69,BOM!$O$2:$O$110,0))) -> 34.18 | F70: =IF($A70="","",IF(INDEX(BOM!$K$2:$K$110,MATCH(69,BOM!$O$2:$O$110,0))="","",HYPERLINK(INDEX(BOM!$K$2:$K$110,MATCH(69,BOM!$O$2:$O$110,0)),"open on amazon.ca"))) -> open on amazon.ca | G70: =IF($A70="","",HYPERLINK(INDEX(BOM!$L$2:$L$110,MATCH(69,BOM!$O$2:$O$110,0)),"search")) -> search
A71: =IF(ISNA(MATCH(70,BOM!$O$2:$O$110,0)),"",70) -> 70 | B71: =IF($A71="","",INDEX(BOM!$B$2:$B$110,MATCH(70,BOM!$O$2:$O$110,0))) -> Heat-shrink ring terminal kit, 260 pcs (22-10 AWG) | C71: =IF($A71="","",INDEX(BOM!$G$2:$G$110,MATCH(70,BOM!$O$2:$O$110,0))) -> 1 | D71: =IF($A71="","",INDEX(BOM!$H$2:$H$110,MATCH(70,BOM!$O$2:$O$110,0))) -> 29.99 | E71: =IF($A71="","",INDEX(BOM!$I$2:$I$110,MATCH(70,BOM!$O$2:$O$110,0))) -> 29.99 | F71: =IF($A71="","",IF(INDEX(BOM!$K$2:$K$110,MATCH(70,BOM!$O$2:$O$110,0))="","",HYPERLINK(INDEX(BOM!$K$2:$K$110,MATCH(70,BOM!$O$2:$O$110,0)),"open on amazon.ca"))) -> open on amazon.ca | G71: =IF($A71="","",HYPERLINK(INDEX(BOM!$L$2:$L$110,MATCH(70,BOM!$O$2:$O$110,0)),"search")) -> search
A72: =IF(ISNA(MATCH(71,BOM!$O$2:$O$110,0)),"",71) -> 71 | B72: =IF($A72="","",INDEX(BOM!$B$2:$B$110,MATCH(71,BOM!$O$2:$O$110,0))) -> Strip brush 25 mm in aluminium holder, ~5 m | C72: =IF($A72="","",INDEX(BOM!$G$2:$G$110,MATCH(71,BOM!$O$2:$O$110,0))) -> 1 | D72: =IF($A72="","",INDEX(BOM!$H$2:$H$110,MATCH(71,BOM!$O$2:$O$110,0))) -> 60 | E72: =IF($A72="","",INDEX(BOM!$I$2:$I$110,MATCH(71,BOM!$O$2:$O$110,0))) -> 60 | F72: =IF($A72="","",IF(INDEX(BOM!$K$2:$K$110,MATCH(71,BOM!$O$2:$O$110,0))="","",HYPERLINK(INDEX(BOM!$K$2:$K$110,MATCH(71,BOM!$O$2:$O$110,0)),"open on amazon.ca"))) | G72: =IF($A72="","",HYPERLINK(INDEX(BOM!$L$2:$L$110,MATCH(71,BOM!$O$2:$O$110,0)),"search")) -> search
A73: =IF(ISNA(MATCH(72,BOM!$O$2:$O$110,0)),"",72) -> 72 | B73: =IF($A73="","",INDEX(BOM!$B$2:$B$110,MATCH(72,BOM!$O$2:$O$110,0))) -> High-density foam 25 mm (1") x 610 x 1830 mm | C73: =IF($A73="","",INDEX(BOM!$G$2:$G$110,MATCH(72,BOM!$O$2:$O$110,0))) -> 1 | D73: =IF($A73="","",INDEX(BOM!$H$2:$H$110,MATCH(72,BOM!$O$2:$O$110,0))) -> 32.15 | E73: =IF($A73="","",INDEX(BOM!$I$2:$I$110,MATCH(72,BOM!$O$2:$O$110,0))) -> 32.15 | F73: =IF($A73="","",IF(INDEX(BOM!$K$2:$K$110,MATCH(72,BOM!$O$2:$O$110,0))="","",HYPERLINK(INDEX(BOM!$K$2:$K$110,MATCH(72,BOM!$O$2:$O$110,0)),"open on amazon.ca"))) -> open on amazon.ca | G73: =IF($A73="","",HYPERLINK(INDEX(BOM!$L$2:$L$110,MATCH(72,BOM!$O$2:$O$110,0)),"search")) -> search
A74: =IF(ISNA(MATCH(73,BOM!$O$2:$O$110,0)),"",73) -> 73 | B74: =IF($A74="","",INDEX(BOM!$B$2:$B$110,MATCH(73,BOM!$O$2:$O$110,0))) -> Buckle kit: 25 mm side-release buckles + 9 m webbing (REDAPRIC) | C74: =IF($A74="","",INDEX(BOM!$G$2:$G$110,MATCH(73,BOM!$O$2:$O$110,0))) -> 1 | D74: =IF($A74="","",INDEX(BOM!$H$2:$H$110,MATCH(73,BOM!$O$2:$O$110,0))) -> 13 | E74: =IF($A74="","",INDEX(BOM!$I$2:$I$110,MATCH(73,BOM!$O$2:$O$110,0))) -> 13 | F74: =IF($A74="","",IF(INDEX(BOM!$K$2:$K$110,MATCH(73,BOM!$O$2:$O$110,0))="","",HYPERLINK(INDEX(BOM!$K$2:$K$110,MATCH(73,BOM!$O$2:$O$110,0)),"open on amazon.ca"))) -> open on amazon.ca | G74: =IF($A74="","",HYPERLINK(INDEX(BOM!$L$2:$L$110,MATCH(73,BOM!$O$2:$O$110,0)),"search")) -> search
A75: =IF(ISNA(MATCH(74,BOM!$O$2:$O$110,0)),"",74) -> 74 | B75: =IF($A75="","",INDEX(BOM!$B$2:$B$110,MATCH(74,BOM!$O$2:$O$110,0))) -> Rated 25 mm (1") webbing, >= 700 kg | C75: =IF($A75="","",INDEX(BOM!$G$2:$G$110,MATCH(74,BOM!$O$2:$O$110,0))) -> 1 | D75: =IF($A75="","",INDEX(BOM!$H$2:$H$110,MATCH(74,BOM!$O$2:$O$110,0))) -> 19.99 | E75: =IF($A75="","",INDEX(BOM!$I$2:$I$110,MATCH(74,BOM!$O$2:$O$110,0))) -> 19.99 | F75: =IF($A75="","",IF(INDEX(BOM!$K$2:$K$110,MATCH(74,BOM!$O$2:$O$110,0))="","",HYPERLINK(INDEX(BOM!$K$2:$K$110,MATCH(74,BOM!$O$2:$O$110,0)),"open on amazon.ca"))) -> open on amazon.ca | G75: =IF($A75="","",HYPERLINK(INDEX(BOM!$L$2:$L$110,MATCH(74,BOM!$O$2:$O$110,0)),"search")) -> search
A76: =IF(ISNA(MATCH(75,BOM!$O$2:$O$110,0)),"",75) -> 75 | B76: =IF($A76="","",INDEX(BOM!$B$2:$B$110,MATCH(75,BOM!$O$2:$O$110,0))) -> Welded steel O-rings 50 mm (2") OD | C76: =IF($A76="","",INDEX(BOM!$G$2:$G$110,MATCH(75,BOM!$O$2:$O$110,0))) -> 1 | D76: =IF($A76="","",INDEX(BOM!$H$2:$H$110,MATCH(75,BOM!$O$2:$O$110,0))) -> 15.99 | E76: =IF($A76="","",INDEX(BOM!$I$2:$I$110,MATCH(75,BOM!$O$2:$O$110,0))) -> 15.99 | F76: =IF($A76="","",IF(INDEX(BOM!$K$2:$K$110,MATCH(75,BOM!$O$2:$O$110,0))="","",HYPERLINK(INDEX(BOM!$K$2:$K$110,MATCH(75,BOM!$O$2:$O$110,0)),"open on amazon.ca"))) -> open on amazon.ca | G76: =IF($A76="","",HYPERLINK(INDEX(BOM!$L$2:$L$110,MATCH(75,BOM!$O$2:$O$110,0)),"search")) -> search
A77: =IF(ISNA(MATCH(76,BOM!$O$2:$O$110,0)),"",76) -> 76 | B77: =IF($A77="","",INDEX(BOM!$B$2:$B$110,MATCH(76,BOM!$O$2:$O$110,0))) -> Welded steel D-rings 25 mm (1") | C77: =IF($A77="","",INDEX(BOM!$G$2:$G$110,MATCH(76,BOM!$O$2:$O$110,0))) -> 1 | D77: =IF($A77="","",INDEX(BOM!$H$2:$H$110,MATCH(76,BOM!$O$2:$O$110,0))) -> 15.97 | E77: =IF($A77="","",INDEX(BOM!$I$2:$I$110,MATCH(76,BOM!$O$2:$O$110,0))) -> 15.97 | F77: =IF($A77="","",IF(INDEX(BOM!$K$2:$K$110,MATCH(76,BOM!$O$2:$O$110,0))="","",HYPERLINK(INDEX(BOM!$K$2:$K$110,MATCH(76,BOM!$O$2:$O$110,0)),"open on amazon.ca"))) -> open on amazon.ca | G77: =IF($A77="","",HYPERLINK(INDEX(BOM!$L$2:$L$110,MATCH(76,BOM!$O$2:$O$110,0)),"search")) -> search
A78: =IF(ISNA(MATCH(77,BOM!$O$2:$O$110,0)),"",77) -> 77 | B78: =IF($A78="","",INDEX(BOM!$B$2:$B$110,MATCH(77,BOM!$O$2:$O$110,0))) -> 2-point adjustable lap belt | C78: =IF($A78="","",INDEX(BOM!$G$2:$G$110,MATCH(77,BOM!$O$2:$O$110,0))) -> 1 | D78: =IF($A78="","",INDEX(BOM!$H$2:$H$110,MATCH(77,BOM!$O$2:$O$110,0))) -> 24.99 | E78: =IF($A78="","",INDEX(BOM!$I$2:$I$110,MATCH(77,BOM!$O$2:$O$110,0))) -> 24.99 | F78: =IF($A78="","",IF(INDEX(BOM!$K$2:$K$110,MATCH(77,BOM!$O$2:$O$110,0))="","",HYPERLINK(INDEX(BOM!$K$2:$K$110,MATCH(77,BOM!$O$2:$O$110,0)),"open on amazon.ca"))) -> open on amazon.ca | G78: =IF($A78="","",HYPERLINK(INDEX(BOM!$L$2:$L$110,MATCH(77,BOM!$O$2:$O$110,0)),"search")) -> search
A79: =IF(ISNA(MATCH(78,BOM!$O$2:$O$110,0)),"",78) -> 78 | B79: =IF($A79="","",INDEX(BOM!$B$2:$B$110,MATCH(78,BOM!$O$2:$O$110,0))) -> High-density upholstery foam 50 mm (2") x 610 x 1830 mm | C79: =IF($A79="","",INDEX(BOM!$G$2:$G$110,MATCH(78,BOM!$O$2:$O$110,0))) -> 1 | D79: =IF($A79="","",INDEX(BOM!$H$2:$H$110,MATCH(78,BOM!$O$2:$O$110,0))) -> 54.54 | E79: =IF($A79="","",INDEX(BOM!$I$2:$I$110,MATCH(78,BOM!$O$2:$O$110,0))) -> 54.54 | F79: =IF($A79="","",IF(INDEX(BOM!$K$2:$K$110,MATCH(78,BOM!$O$2:$O$110,0))="","",HYPERLINK(INDEX(BOM!$K$2:$K$110,MATCH(78,BOM!$O$2:$O$110,0)),"open on amazon.ca"))) -> open on amazon.ca | G79: =IF($A79="","",HYPERLINK(INDEX(BOM!$L$2:$L$110,MATCH(78,BOM!$O$2:$O$110,0)),"search")) -> search
A80: =IF(ISNA(MATCH(79,BOM!$O$2:$O$110,0)),"",79) -> 79 | B80: =IF($A80="","",INDEX(BOM!$B$2:$B$110,MATCH(79,BOM!$O$2:$O$110,0))) -> Marine vinyl, black, 1.5 m x 1.37 m (5 ft x 54") | C80: =IF($A80="","",INDEX(BOM!$G$2:$G$110,MATCH(79,BOM!$O$2:$O$110,0))) -> 1 | D80: =IF($A80="","",INDEX(BOM!$H$2:$H$110,MATCH(79,BOM!$O$2:$O$110,0))) -> 43.69 | E80: =IF($A80="","",INDEX(BOM!$I$2:$I$110,MATCH(79,BOM!$O$2:$O$110,0))) -> 43.69 | F80: =IF($A80="","",IF(INDEX(BOM!$K$2:$K$110,MATCH(79,BOM!$O$2:$O$110,0))="","",HYPERLINK(INDEX(BOM!$K$2:$K$110,MATCH(79,BOM!$O$2:$O$110,0)),"open on amazon.ca"))) -> open on amazon.ca | G80: =IF($A80="","",HYPERLINK(INDEX(BOM!$L$2:$L$110,MATCH(79,BOM!$O$2:$O$110,0)),"search")) -> search
A81: =IF(ISNA(MATCH(80,BOM!$O$2:$O$110,0)),"",80) | B81: =IF($A81="","",INDEX(BOM!$B$2:$B$110,MATCH(80,BOM!$O$2:$O$110,0))) | C81: =IF($A81="","",INDEX(BOM!$G$2:$G$110,MATCH(80,BOM!$O$2:$O$110,0))) | D81: =IF($A81="","",INDEX(BOM!$H$2:$H$110,MATCH(80,BOM!$O$2:$O$110,0))) | E81: =IF($A81="","",INDEX(BOM!$I$2:$I$110,MATCH(80,BOM!$O$2:$O$110,0))) | F81: =IF($A81="","",IF(INDEX(BOM!$K$2:$K$110,MATCH(80,BOM!$O$2:$O$110,0))="","",HYPERLINK(INDEX(BOM!$K$2:$K$110,MATCH(80,BOM!$O$2:$O$110,0)),"open on amazon.ca"))) | G81: =IF($A81="","",HYPERLINK(INDEX(BOM!$L$2:$L$110,MATCH(80,BOM!$O$2:$O$110,0)),"search"))
A82: =IF(ISNA(MATCH(81,BOM!$O$2:$O$110,0)),"",81) | B82: =IF($A82="","",INDEX(BOM!$B$2:$B$110,MATCH(81,BOM!$O$2:$O$110,0))) | C82: =IF($A82="","",INDEX(BOM!$G$2:$G$110,MATCH(81,BOM!$O$2:$O$110,0))) | D82: =IF($A82="","",INDEX(BOM!$H$2:$H$110,MATCH(81,BOM!$O$2:$O$110,0))) | E82: =IF($A82="","",INDEX(BOM!$I$2:$I$110,MATCH(81,BOM!$O$2:$O$110,0))) | F82: =IF($A82="","",IF(INDEX(BOM!$K$2:$K$110,MATCH(81,BOM!$O$2:$O$110,0))="","",HYPERLINK(INDEX(BOM!$K$2:$K$110,MATCH(81,BOM!$O$2:$O$110,0)),"open on amazon.ca"))) | G82: =IF($A82="","",HYPERLINK(INDEX(BOM!$L$2:$L$110,MATCH(81,BOM!$O$2:$O$110,0)),"search"))
A83: =IF(ISNA(MATCH(82,BOM!$O$2:$O$110,0)),"",82) | B83: =IF($A83="","",INDEX(BOM!$B$2:$B$110,MATCH(82,BOM!$O$2:$O$110,0))) | C83: =IF($A83="","",INDEX(BOM!$G$2:$G$110,MATCH(82,BOM!$O$2:$O$110,0))) | D83: =IF($A83="","",INDEX(BOM!$H$2:$H$110,MATCH(82,BOM!$O$2:$O$110,0))) | E83: =IF($A83="","",INDEX(BOM!$I$2:$I$110,MATCH(82,BOM!$O$2:$O$110,0))) | F83: =IF($A83="","",IF(INDEX(BOM!$K$2:$K$110,MATCH(82,BOM!$O$2:$O$110,0))="","",HYPERLINK(INDEX(BOM!$K$2:$K$110,MATCH(82,BOM!$O$2:$O$110,0)),"open on amazon.ca"))) | G83: =IF($A83="","",HYPERLINK(INDEX(BOM!$L$2:$L$110,MATCH(82,BOM!$O$2:$O$110,0)),"search"))
A84: =IF(ISNA(MATCH(83,BOM!$O$2:$O$110,0)),"",83) | B84: =IF($A84="","",INDEX(BOM!$B$2:$B$110,MATCH(83,BOM!$O$2:$O$110,0))) | C84: =IF($A84="","",INDEX(BOM!$G$2:$G$110,MATCH(83,BOM!$O$2:$O$110,0))) | D84: =IF($A84="","",INDEX(BOM!$H$2:$H$110,MATCH(83,BOM!$O$2:$O$110,0))) | E84: =IF($A84="","",INDEX(BOM!$I$2:$I$110,MATCH(83,BOM!$O$2:$O$110,0))) | F84: =IF($A84="","",IF(INDEX(BOM!$K$2:$K$110,MATCH(83,BOM!$O$2:$O$110,0))="","",HYPERLINK(INDEX(BOM!$K$2:$K$110,MATCH(83,BOM!$O$2:$O$110,0)),"open on amazon.ca"))) | G84: =IF($A84="","",HYPERLINK(INDEX(BOM!$L$2:$L$110,MATCH(83,BOM!$O$2:$O$110,0)),"search"))
A85: =IF(ISNA(MATCH(84,BOM!$O$2:$O$110,0)),"",84) | B85: =IF($A85="","",INDEX(BOM!$B$2:$B$110,MATCH(84,BOM!$O$2:$O$110,0))) | C85: =IF($A85="","",INDEX(BOM!$G$2:$G$110,MATCH(84,BOM!$O$2:$O$110,0))) | D85: =IF($A85="","",INDEX(BOM!$H$2:$H$110,MATCH(84,BOM!$O$2:$O$110,0))) | E85: =IF($A85="","",INDEX(BOM!$I$2:$I$110,MATCH(84,BOM!$O$2:$O$110,0))) | F85: =IF($A85="","",IF(INDEX(BOM!$K$2:$K$110,MATCH(84,BOM!$O$2:$O$110,0))="","",HYPERLINK(INDEX(BOM!$K$2:$K$110,MATCH(84,BOM!$O$2:$O$110,0)),"open on amazon.ca"))) | G85: =IF($A85="","",HYPERLINK(INDEX(BOM!$L$2:$L$110,MATCH(84,BOM!$O$2:$O$110,0)),"search"))
A86: =IF(ISNA(MATCH(85,BOM!$O$2:$O$110,0)),"",85) | B86: =IF($A86="","",INDEX(BOM!$B$2:$B$110,MATCH(85,BOM!$O$2:$O$110,0))) | C86: =IF($A86="","",INDEX(BOM!$G$2:$G$110,MATCH(85,BOM!$O$2:$O$110,0))) | D86: =IF($A86="","",INDEX(BOM!$H$2:$H$110,MATCH(85,BOM!$O$2:$O$110,0))) | E86: =IF($A86="","",INDEX(BOM!$I$2:$I$110,MATCH(85,BOM!$O$2:$O$110,0))) | F86: =IF($A86="","",IF(INDEX(BOM!$K$2:$K$110,MATCH(85,BOM!$O$2:$O$110,0))="","",HYPERLINK(INDEX(BOM!$K$2:$K$110,MATCH(85,BOM!$O$2:$O$110,0)),"open on amazon.ca"))) | G86: =IF($A86="","",HYPERLINK(INDEX(BOM!$L$2:$L$110,MATCH(85,BOM!$O$2:$O$110,0)),"search"))
A87: =IF(ISNA(MATCH(86,BOM!$O$2:$O$110,0)),"",86) | B87: =IF($A87="","",INDEX(BOM!$B$2:$B$110,MATCH(86,BOM!$O$2:$O$110,0))) | C87: =IF($A87="","",INDEX(BOM!$G$2:$G$110,MATCH(86,BOM!$O$2:$O$110,0))) | D87: =IF($A87="","",INDEX(BOM!$H$2:$H$110,MATCH(86,BOM!$O$2:$O$110,0))) | E87: =IF($A87="","",INDEX(BOM!$I$2:$I$110,MATCH(86,BOM!$O$2:$O$110,0))) | F87: =IF($A87="","",IF(INDEX(BOM!$K$2:$K$110,MATCH(86,BOM!$O$2:$O$110,0))="","",HYPERLINK(INDEX(BOM!$K$2:$K$110,MATCH(86,BOM!$O$2:$O$110,0)),"open on amazon.ca"))) | G87: =IF($A87="","",HYPERLINK(INDEX(BOM!$L$2:$L$110,MATCH(86,BOM!$O$2:$O$110,0)),"search"))
A88: =IF(ISNA(MATCH(87,BOM!$O$2:$O$110,0)),"",87) | B88: =IF($A88="","",INDEX(BOM!$B$2:$B$110,MATCH(87,BOM!$O$2:$O$110,0))) | C88: =IF($A88="","",INDEX(BOM!$G$2:$G$110,MATCH(87,BOM!$O$2:$O$110,0))) | D88: =IF($A88="","",INDEX(BOM!$H$2:$H$110,MATCH(87,BOM!$O$2:$O$110,0))) | E88: =IF($A88="","",INDEX(BOM!$I$2:$I$110,MATCH(87,BOM!$O$2:$O$110,0))) | F88: =IF($A88="","",IF(INDEX(BOM!$K$2:$K$110,MATCH(87,BOM!$O$2:$O$110,0))="","",HYPERLINK(INDEX(BOM!$K$2:$K$110,MATCH(87,BOM!$O$2:$O$110,0)),"open on amazon.ca"))) | G88: =IF($A88="","",HYPERLINK(INDEX(BOM!$L$2:$L$110,MATCH(87,BOM!$O$2:$O$110,0)),"search"))
A89: =IF(ISNA(MATCH(88,BOM!$O$2:$O$110,0)),"",88) | B89: =IF($A89="","",INDEX(BOM!$B$2:$B$110,MATCH(88,BOM!$O$2:$O$110,0))) | C89: =IF($A89="","",INDEX(BOM!$G$2:$G$110,MATCH(88,BOM!$O$2:$O$110,0))) | D89: =IF($A89="","",INDEX(BOM!$H$2:$H$110,MATCH(88,BOM!$O$2:$O$110,0))) | E89: =IF($A89="","",INDEX(BOM!$I$2:$I$110,MATCH(88,BOM!$O$2:$O$110,0))) | F89: =IF($A89="","",IF(INDEX(BOM!$K$2:$K$110,MATCH(88,BOM!$O$2:$O$110,0))="","",HYPERLINK(INDEX(BOM!$K$2:$K$110,MATCH(88,BOM!$O$2:$O$110,0)),"open on amazon.ca"))) | G89: =IF($A89="","",HYPERLINK(INDEX(BOM!$L$2:$L$110,MATCH(88,BOM!$O$2:$O$110,0)),"search"))
A90: =IF(ISNA(MATCH(89,BOM!$O$2:$O$110,0)),"",89) | B90: =IF($A90="","",INDEX(BOM!$B$2:$B$110,MATCH(89,BOM!$O$2:$O$110,0))) | C90: =IF($A90="","",INDEX(BOM!$G$2:$G$110,MATCH(89,BOM!$O$2:$O$110,0))) | D90: =IF($A90="","",INDEX(BOM!$H$2:$H$110,MATCH(89,BOM!$O$2:$O$110,0))) | E90: =IF($A90="","",INDEX(BOM!$I$2:$I$110,MATCH(89,BOM!$O$2:$O$110,0))) | F90: =IF($A90="","",IF(INDEX(BOM!$K$2:$K$110,MATCH(89,BOM!$O$2:$O$110,0))="","",HYPERLINK(INDEX(BOM!$K$2:$K$110,MATCH(89,BOM!$O$2:$O$110,0)),"open on amazon.ca"))) | G90: =IF($A90="","",HYPERLINK(INDEX(BOM!$L$2:$L$110,MATCH(89,BOM!$O$2:$O$110,0)),"search"))
A91: =IF(ISNA(MATCH(90,BOM!$O$2:$O$110,0)),"",90) | B91: =IF($A91="","",INDEX(BOM!$B$2:$B$110,MATCH(90,BOM!$O$2:$O$110,0))) | C91: =IF($A91="","",INDEX(BOM!$G$2:$G$110,MATCH(90,BOM!$O$2:$O$110,0))) | D91: =IF($A91="","",INDEX(BOM!$H$2:$H$110,MATCH(90,BOM!$O$2:$O$110,0))) | E91: =IF($A91="","",INDEX(BOM!$I$2:$I$110,MATCH(90,BOM!$O$2:$O$110,0))) | F91: =IF($A91="","",IF(INDEX(BOM!$K$2:$K$110,MATCH(90,BOM!$O$2:$O$110,0))="","",HYPERLINK(INDEX(BOM!$K$2:$K$110,MATCH(90,BOM!$O$2:$O$110,0)),"open on amazon.ca"))) | G91: =IF($A91="","",HYPERLINK(INDEX(BOM!$L$2:$L$110,MATCH(90,BOM!$O$2:$O$110,0)),"search"))
A92: =IF(ISNA(MATCH(91,BOM!$O$2:$O$110,0)),"",91) | B92: =IF($A92="","",INDEX(BOM!$B$2:$B$110,MATCH(91,BOM!$O$2:$O$110,0))) | C92: =IF($A92="","",INDEX(BOM!$G$2:$G$110,MATCH(91,BOM!$O$2:$O$110,0))) | D92: =IF($A92="","",INDEX(BOM!$H$2:$H$110,MATCH(91,BOM!$O$2:$O$110,0))) | E92: =IF($A92="","",INDEX(BOM!$I$2:$I$110,MATCH(91,BOM!$O$2:$O$110,0))) | F92: =IF($A92="","",IF(INDEX(BOM!$K$2:$K$110,MATCH(91,BOM!$O$2:$O$110,0))="","",HYPERLINK(INDEX(BOM!$K$2:$K$110,MATCH(91,BOM!$O$2:$O$110,0)),"open on amazon.ca"))) | G92: =IF($A92="","",HYPERLINK(INDEX(BOM!$L$2:$L$110,MATCH(91,BOM!$O$2:$O$110,0)),"search"))
A93: =IF(ISNA(MATCH(92,BOM!$O$2:$O$110,0)),"",92) | B93: =IF($A93="","",INDEX(BOM!$B$2:$B$110,MATCH(92,BOM!$O$2:$O$110,0))) | C93: =IF($A93="","",INDEX(BOM!$G$2:$G$110,MATCH(92,BOM!$O$2:$O$110,0))) | D93: =IF($A93="","",INDEX(BOM!$H$2:$H$110,MATCH(92,BOM!$O$2:$O$110,0))) | E93: =IF($A93="","",INDEX(BOM!$I$2:$I$110,MATCH(92,BOM!$O$2:$O$110,0))) | F93: =IF($A93="","",IF(INDEX(BOM!$K$2:$K$110,MATCH(92,BOM!$O$2:$O$110,0))="","",HYPERLINK(INDEX(BOM!$K$2:$K$110,MATCH(92,BOM!$O$2:$O$110,0)),"open on amazon.ca"))) | G93: =IF($A93="","",HYPERLINK(INDEX(BOM!$L$2:$L$110,MATCH(92,BOM!$O$2:$O$110,0)),"search"))
A94: =IF(ISNA(MATCH(93,BOM!$O$2:$O$110,0)),"",93) | B94: =IF($A94="","",INDEX(BOM!$B$2:$B$110,MATCH(93,BOM!$O$2:$O$110,0))) | C94: =IF($A94="","",INDEX(BOM!$G$2:$G$110,MATCH(93,BOM!$O$2:$O$110,0))) | D94: =IF($A94="","",INDEX(BOM!$H$2:$H$110,MATCH(93,BOM!$O$2:$O$110,0))) | E94: =IF($A94="","",INDEX(BOM!$I$2:$I$110,MATCH(93,BOM!$O$2:$O$110,0))) | F94: =IF($A94="","",IF(INDEX(BOM!$K$2:$K$110,MATCH(93,BOM!$O$2:$O$110,0))="","",HYPERLINK(INDEX(BOM!$K$2:$K$110,MATCH(93,BOM!$O$2:$O$110,0)),"open on amazon.ca"))) | G94: =IF($A94="","",HYPERLINK(INDEX(BOM!$L$2:$L$110,MATCH(93,BOM!$O$2:$O$110,0)),"search"))
A95: =IF(ISNA(MATCH(94,BOM!$O$2:$O$110,0)),"",94) | B95: =IF($A95="","",INDEX(BOM!$B$2:$B$110,MATCH(94,BOM!$O$2:$O$110,0))) | C95: =IF($A95="","",INDEX(BOM!$G$2:$G$110,MATCH(94,BOM!$O$2:$O$110,0))) | D95: =IF($A95="","",INDEX(BOM!$H$2:$H$110,MATCH(94,BOM!$O$2:$O$110,0))) | E95: =IF($A95="","",INDEX(BOM!$I$2:$I$110,MATCH(94,BOM!$O$2:$O$110,0))) | F95: =IF($A95="","",IF(INDEX(BOM!$K$2:$K$110,MATCH(94,BOM!$O$2:$O$110,0))="","",HYPERLINK(INDEX(BOM!$K$2:$K$110,MATCH(94,BOM!$O$2:$O$110,0)),"open on amazon.ca"))) | G95: =IF($A95="","",HYPERLINK(INDEX(BOM!$L$2:$L$110,MATCH(94,BOM!$O$2:$O$110,0)),"search"))
A96: =IF(ISNA(MATCH(95,BOM!$O$2:$O$110,0)),"",95) | B96: =IF($A96="","",INDEX(BOM!$B$2:$B$110,MATCH(95,BOM!$O$2:$O$110,0))) | C96: =IF($A96="","",INDEX(BOM!$G$2:$G$110,MATCH(95,BOM!$O$2:$O$110,0))) | D96: =IF($A96="","",INDEX(BOM!$H$2:$H$110,MATCH(95,BOM!$O$2:$O$110,0))) | E96: =IF($A96="","",INDEX(BOM!$I$2:$I$110,MATCH(95,BOM!$O$2:$O$110,0))) | F96: =IF($A96="","",IF(INDEX(BOM!$K$2:$K$110,MATCH(95,BOM!$O$2:$O$110,0))="","",HYPERLINK(INDEX(BOM!$K$2:$K$110,MATCH(95,BOM!$O$2:$O$110,0)),"open on amazon.ca"))) | G96: =IF($A96="","",HYPERLINK(INDEX(BOM!$L$2:$L$110,MATCH(95,BOM!$O$2:$O$110,0)),"search"))
A97: =IF(ISNA(MATCH(96,BOM!$O$2:$O$110,0)),"",96) | B97: =IF($A97="","",INDEX(BOM!$B$2:$B$110,MATCH(96,BOM!$O$2:$O$110,0))) | C97: =IF($A97="","",INDEX(BOM!$G$2:$G$110,MATCH(96,BOM!$O$2:$O$110,0))) | D97: =IF($A97="","",INDEX(BOM!$H$2:$H$110,MATCH(96,BOM!$O$2:$O$110,0))) | E97: =IF($A97="","",INDEX(BOM!$I$2:$I$110,MATCH(96,BOM!$O$2:$O$110,0))) | F97: =IF($A97="","",IF(INDEX(BOM!$K$2:$K$110,MATCH(96,BOM!$O$2:$O$110,0))="","",HYPERLINK(INDEX(BOM!$K$2:$K$110,MATCH(96,BOM!$O$2:$O$110,0)),"open on amazon.ca"))) | G97: =IF($A97="","",HYPERLINK(INDEX(BOM!$L$2:$L$110,MATCH(96,BOM!$O$2:$O$110,0)),"search"))
A98: =IF(ISNA(MATCH(97,BOM!$O$2:$O$110,0)),"",97) | B98: =IF($A98="","",INDEX(BOM!$B$2:$B$110,MATCH(97,BOM!$O$2:$O$110,0))) | C98: =IF($A98="","",INDEX(BOM!$G$2:$G$110,MATCH(97,BOM!$O$2:$O$110,0))) | D98: =IF($A98="","",INDEX(BOM!$H$2:$H$110,MATCH(97,BOM!$O$2:$O$110,0))) | E98: =IF($A98="","",INDEX(BOM!$I$2:$I$110,MATCH(97,BOM!$O$2:$O$110,0))) | F98: =IF($A98="","",IF(INDEX(BOM!$K$2:$K$110,MATCH(97,BOM!$O$2:$O$110,0))="","",HYPERLINK(INDEX(BOM!$K$2:$K$110,MATCH(97,BOM!$O$2:$O$110,0)),"open on amazon.ca"))) | G98: =IF($A98="","",HYPERLINK(INDEX(BOM!$L$2:$L$110,MATCH(97,BOM!$O$2:$O$110,0)),"search"))
A99: =IF(ISNA(MATCH(98,BOM!$O$2:$O$110,0)),"",98) | B99: =IF($A99="","",INDEX(BOM!$B$2:$B$110,MATCH(98,BOM!$O$2:$O$110,0))) | C99: =IF($A99="","",INDEX(BOM!$G$2:$G$110,MATCH(98,BOM!$O$2:$O$110,0))) | D99: =IF($A99="","",INDEX(BOM!$H$2:$H$110,MATCH(98,BOM!$O$2:$O$110,0))) | E99: =IF($A99="","",INDEX(BOM!$I$2:$I$110,MATCH(98,BOM!$O$2:$O$110,0))) | F99: =IF($A99="","",IF(INDEX(BOM!$K$2:$K$110,MATCH(98,BOM!$O$2:$O$110,0))="","",HYPERLINK(INDEX(BOM!$K$2:$K$110,MATCH(98,BOM!$O$2:$O$110,0)),"open on amazon.ca"))) | G99: =IF($A99="","",HYPERLINK(INDEX(BOM!$L$2:$L$110,MATCH(98,BOM!$O$2:$O$110,0)),"search"))
A100: =IF(ISNA(MATCH(99,BOM!$O$2:$O$110,0)),"",99) | B100: =IF($A100="","",INDEX(BOM!$B$2:$B$110,MATCH(99,BOM!$O$2:$O$110,0))) | C100: =IF($A100="","",INDEX(BOM!$G$2:$G$110,MATCH(99,BOM!$O$2:$O$110,0))) | D100: =IF($A100="","",INDEX(BOM!$H$2:$H$110,MATCH(99,BOM!$O$2:$O$110,0))) | E100: =IF($A100="","",INDEX(BOM!$I$2:$I$110,MATCH(99,BOM!$O$2:$O$110,0))) | F100: =IF($A100="","",IF(INDEX(BOM!$K$2:$K$110,MATCH(99,BOM!$O$2:$O$110,0))="","",HYPERLINK(INDEX(BOM!$K$2:$K$110,MATCH(99,BOM!$O$2:$O$110,0)),"open on amazon.ca"))) | G100: =IF($A100="","",HYPERLINK(INDEX(BOM!$L$2:$L$110,MATCH(99,BOM!$O$2:$O$110,0)),"search"))
...

Sheet Notes
A1: The Filament Falcon - BOM notes (built 2026-10-09, Atlantic time ADT/AST; location Fredericton, NB)
A2: Sources: filament-falcon/docs/SPEC.md; ff-fw/docs/electronics/README.md; filament-falcon (branch pod-single, frame v0.3 single pod actuator): frame/BOM.md v0.3, frame/cut_list.md, docs/mechanical/README.md, switch_bom.md, displays.md.
A3: Filament method: python trimesh volume V and surface area A of every 3MF (panels: single-material body = black, letter inserts = white; printed parts x quantities from docs/mechanical/README.md). Printed volume = shell + infill x (V - shell), shell = min(V, A x 1.2 mm) (3 perimeters x 0.4 mm, also used as top/bottom skin proxy); infill 25 % (monitor standoffs 50 %, harness hub 45 %). PETG 1.27 g/cm3, +15 % for purge/brim/failed prints.
A4: Filament result: black 3601 cm3 -> 5.26 kg (buy 6 x 1 kg); white 44 cm3 -> 0.06 kg (buy 1 x 1 kg). Red/grey parts (guard lids, throttle grip, gear arm, adapter plates) are counted in black - print them in red/grey if you have it. PLA would need ~2 % less mass, but PETG is required for the harness hub and recommended everywhere.
A5: Prices: "Verified amazon.ca price" = read from the amazon.ca product page on 2026-10-08 (buy-box price, CAD, before tax). Kent prices were read from kent.ca on 2026-10-09 with the Fredericton store selected (Fredericton South, 809 Bishop Dr, and Fredericton North, 25 Two Nations Crossing showed identical prices); they can change, check before buying. Local metal-supplier rows have Google search links for Fredericton NB. Rows marked Estimate/placeholder are NOT verified prices.
A6: Motion system (v0.3, branch pod-single): 2 cradle actuators 10"/1500 N (~364 mm retracted, self-locking); ONE pod actuator 12"/1500 N self-locking (420 mm retracted, left casing) driving both pod cheeks through a 2x2x1/8" steel torque tube; 2 gas struts ~1050 N with M8 eye ends, sized so the pod is lift-biased (actuator or clevis-pin failure sends it UP, never down); 25 mm shafts, UCP205/UCF205/SHF25; spring pawls + latch plates + Bowden release; steel hard stops; key, E-stop, 20 A fuse, hold-to-run DPDT, relays as 2 H-bridges, one pod limit set (left cheek), roller limit switches, safety edge. Check actuator retracted length and self-locking before ordering.
A7: SAFETY: the B0B3J1GCVQ buckles are plastic luggage buckles (~50 kg quoted break load, not safety-rated). Positioning harness only for a slow reclining seat. A rated metal-buckle 4-point harness is listed as an ALTERNATIVE row (excluded from totals; switch if you prefer).
A8: Displays: GPU DP1 -> C275B, HDMI -> C275W (HDMI/VGA only), DP2 -> DP-to-DVI-D -> TD2220 (VGA/DVI only), USB-A -> USB-B for touch. GPU USB-C is spare (4th display max).
A9: Owned items: PC, both Sceptres, TD2220, 3 HY300, 2 joysticks have Have it = TRUE. Buttons/switches/LEDs you may own are FALSE - tick them.
